Workbook

Sheet Dashboard
A1: NEPALI VEHICLE INSCRIPTIONS — CULTURAL & EMOTIONAL DASHBOARD
A3: 61 inscriptions · 23 theme codes · multi-label coding · every figure is a live formula linked to Master_Dataset
A5: Inscriptions coded | D5: Theme categories | G5: Top theme | J5: Mixed valence | M5: High confidence | P5: Needs human review
A6: =COUNT(Master_Dataset!A2:A62) -> 61 | D6: =COUNTA(Codebook!A12:A34) -> 23 | G6: =INDEX(Dashboard_Data!A2:A24,MATCH(MAX(Dashboard_Data!C2:C24),Dashboard_Data!C2:C24,0)) -> Love & Romance | J6: =COUNTIF(Master_Dataset!Z2:Z62,"Mixed")/COUNT(Master_Dataset!A2:A62) -> 0.40983607 | M6: =COUNTIF(Master_Dataset!AD2:AD62,"High")/COUNT(Master_Dataset!A2:A62) -> 0.73770492 | P6: =COUNTIF(Master_Dataset!AF2:AF62,"Y") -> 27
A8: rows in corpus | D8: 16 deductive · 7 emergent | G8: =MAX(Frequencies!C2:C24)&" inscriptions" -> 18 inscriptions | J8: largest valence group | M8: explicit meaning | P8: flagged rows
A10: THEME FREQUENCY (bar colour = domain) | J10: FEELING & RELIABILITY
A40: DOMAINS: HOW MANY INSCRIPTIONS TOUCH EACH, AND WITH WHAT FEELING
A60: EMERGENT CLUSTERS (number of member inscriptions)
J61: THEMES THAT TRAVEL TOGETHER
J62: Theme A | M62: Theme B | P62: Both
J63: Love & Romance | M63: Heartbreak & Separation | P63: =Co_occurrence!C3 -> 8
J64: Love & Romance | M64: Humour & Satire | P64: =Co_occurrence!W3 -> 6
J65: Family & Parents | M65: Money & Wealth | P65: =Co_occurrence!E5 -> 5
J66: Driver's Voice | M66: Dignity of Labour | P66: =Co_occurrence!K11 -> 5
J67: Self-Respect & Swagger | M67: Moral Advice | P67: =Co_occurrence!Q16 -> 4
J68: Money & Wealth | M68: Class & Inequality | P68: =Co_occurrence!F6 -> 4
J69: Driver's Voice | M69: Humour & Satire | P69: =Co_occurrence!W11 -> 4
J70: Place & Region | M70: Humour & Satire | P70: =Co_occurrence!W23 -> 3
J71: Love & Romance | M71: Hope & Resilience | P71: =Co_occurrence!R3 -> 3
J72: Love & Romance | M72: Driver's Voice | P72: =Co_occurrence!J3 -> 3
A82: WORD BOARD — THE VOCABULARY OF EACH CATEGORY
A84: Key words taken from the inscriptions themselves, grouped by theme. Card colour = domain; the count is live.
A85: Love & Relationships | C85: Money & Class | E85: Driver & Work | G85: Gender | I85: Self & Morality | K85: Faith & Mortality | M85: Politics & Place | O85: Style & Register
A87: Love & Romance | E87: Heartbreak & Separation | I87: Family & Parents | M87: Money & Wealth
A88: =INDEX(Frequencies!$C$2:$C$24,MATCH("LOVE_ROMANCE",Frequencies!$A$2:$A$24,0))&" inscriptions" -> 18 inscriptions | E88: =INDEX(Frequencies!$C$2:$C$24,MATCH("SEPARATION_LOSS",Frequencies!$A$2:$A$24,0))&" inscriptions" -> 8 inscriptions | I88: =INDEX(Frequencies!$C$2:$C$24,MATCH("FAMILY",Frequencies!$A$2:$A$24,0))&" inscriptions" -> 9 inscriptions | M88: =INDEX(Frequencies!$C$2:$C$24,MATCH("MONEY_MATERIALISM",Frequencies!$A$2:$A$24,0))&" inscriptions" -> 11 inscriptions
A89: माया · प्यारी · याद · लभ यू · GF · कान्छी | E89: छाडी जाने · एक्लो · पर्खिरहेँ · नफर्किने खोला · अनजान | I89: आमा · बुबा · छोरा · परिवार · आफन्त · माइती | M89: पैसा · धन · सम्पत्ति · कमाउनु · गोजी
A92: Class & Inequality | E92: Status Goods | I92: Gulf Migration | M92: Education
A93: =INDEX(Frequencies!$C$2:$C$24,MATCH("CLASS_INEQUALITY_CRITIQUE",Frequencies!$A$2:$A$24,0))&" inscriptions" -> 7 inscriptions | E93: =INDEX(Frequencies!$C$2:$C$24,MATCH("CONSUMER_STATUS",Frequencies!$A$2:$A$24,0))&" inscriptions" -> 2 inscriptions | I93: =INDEX(Frequencies!$C$2:$C$24,MATCH("MIGRATION",Frequencies!$A$2:$A$24,0))&" inscriptions" -> 4 inscriptions | M93: =INDEX(Frequencies!$C$2:$C$24,MATCH("EDUCATION",Frequencies!$A$2:$A$24,0))&" inscriptions" -> 1 inscriptions
A94: धनी/गरिब · हुने/नहुने · औकात · रमिता | E94: कार · हार · रेस्टुरेन्ट · पानीपुरी | I94: खाडी · कतार · साउदी · परदेशी | M94: पढाइ · पढ्ने / नपढ्ने
A97: Driver's Voice | E97: Dignity of Labour | I97: The Fare | M97: Masculinity
A98: =INDEX(Frequencies!$C$2:$C$24,MATCH("DRIVER_IDENTITY",Frequencies!$A$2:$A$24,0))&" inscriptions" -> 8 inscriptions | E98: =INDEX(Frequencies!$C$2:$C$24,MATCH("LABOR_DIGNITY",Frequencies!$A$2:$A$24,0))&" inscriptions" -> 8 inscriptions | I98: =INDEX(Frequencies!$C$2:$C$24,MATCH("FARE_LIVELIHOOD",Frequencies!$A$2:$A$24,0))&" inscriptions" -> 4 inscriptions | M98: =INDEX(Frequencies!$C$2:$C$24,MATCH("MASCULINITY",Frequencies!$A$2:$A$24,0))&" inscriptions" -> 5 inscriptions
A99: ड्राइभर · गाडी · मोटर · रफ्तार | E99: हेला नगर्नु · भिकारी नभन्नु · नहेप · निद्रा | I99: भाडा · चढ · झर | M99: मर्द · नामर्द · पुरुष · कमाउनुपर्छ
A102: Women Represented | E102: Self-Respect & Swagger | I102: Distrust & Hypocrisy | M102: Moral Advice
A103: =INDEX(Frequencies!$C$2:$C$24,MATCH("WOMEN_REPRESENTATION",Frequencies!$A$2:$A$24,0))&" inscriptions" -> 4 inscriptions | E103: =INDEX(Frequencies!$C$2:$C$24,MATCH("SELF_RESPECT",Frequencies!$A$2:$A$24,0))&" inscriptions" -> 10 inscriptions | I103: =INDEX(Frequencies!$C$2:$C$24,MATCH("DISTRUST_HYPOCRISY",Frequencies!$A$2:$A$24,0))&" inscriptions" -> 7 inscriptions | M103: =INDEX(Frequencies!$C$2:$C$24,MATCH("MORAL_ADVICE",Frequencies!$A$2:$A$24,0))&" inscriptions" -> 11 inscriptions
A104: स्त्री · छोरी पोइल · कम्मर · बच्चाकी आमा | E104: शिर झुकाउनु · बबाल · राजा · कच्चा नसम्झ | I104: स्वार्थी · झुट · असली रूप · जलन | M104: सत्य · असल · सफा मन · आशीर्वाद
A107: Hope & Resilience | E107: Faith & Mythology | I107: Death & Risk | M107: Politics & Institutions
A108: =INDEX(Frequencies!$C$2:$C$24,MATCH("HOPE_RESILIENCE",Frequencies!$A$2:$A$24,0))&" inscriptions" -> 10 inscriptions | E108: =INDEX(Frequencies!$C$2:$C$24,MATCH("RELIGION_FATE",Frequencies!$A$2:$A$24,0))&" inscriptions" -> 4 inscriptions | I108: =INDEX(Frequencies!$C$2:$C$24,MATCH("MORTALITY_RISK",Frequencies!$A$2:$A$24,0))&" inscriptions" -> 5 inscriptions | M108: =INDEX(Frequencies!$C$2:$C$24,MATCH("INSTITUTION_CRITIQUE",Frequencies!$A$2:$A$24,0))&" inscriptions" -> 4 inscriptions
A109: आशा · धैर्य · हिम्मत · बिहानी | E109: भगवान् · प्रभु येशू · शिवजी · पार्वती | I109: बाढी · दुर्घटना · कात्रो · मसानघाट | M109: अदालत · नेताजी · संविधान · घण्टी छाप
A112: Place & Region | E112: Humour & Satire | I112: Slang & Code-mixing
A113: =INDEX(Frequencies!$C$2:$C$24,MATCH("PLACE_IDENTITY",Frequencies!$A$2:$A$24,0))&" inscriptions" -> 4 inscriptions | E113: =INDEX(Frequencies!$C$2:$C$24,MATCH("HUMOR",Frequencies!$A$2:$A$24,0))&" inscriptions" -> 17 inscriptions | I113: =INDEX(Frequencies!$C$2:$C$24,MATCH("CODE_MIXING_SLANG",Frequencies!$A$2:$A$24,0))&" inscriptions" -> 4 inscriptions
A114: मुगाली · चौरजहारी · सुर्खेत · सल्यान | E114: ठट्टा · मजाक · अङ्कल · दाइ | I114: हाइ/बाइ · लभ यू · GF · बाल नदिने
A117: Note: counts include the #9/#47 duplicate; single-coder first pass — see Human_Review before citing.

Sheet Codebook
A1: Nepali Vehicle Inscriptions — Multidimensional Coding (61 entries)
A3: Source: user-supplied file '52_Vehicle_proverbs_and_sayings' (61 rows despite the filename). Columns B–F of Master_Dataset are copied verbatim from that file (escape backslashes removed only).
A4: Original_Translation is never overwritten. Corrections appear in Normalized_Translation and are flagged in Human_Review.
A5: Multi-label fields use '|' as separator. 'Not evident' = no textual basis; it is not a negative finding.
A6: Code_Matrix, Frequencies and Co_occurrence are formula-driven from the Codes column: edit Codes and they recalculate.
A7: Confidence: High = explicit; Medium = needs contextual inference; Low = several readings plausible.
A8: Power_Hierarchy uses: Reproduction / Reflection / Critique / Resistance / Ambiguous (master prompt §10).
A9: Coding is a first pass by Claude, not a validated annotation. All entries flagged Y need native-speaker review before publication.
A11: Code | B11: Origin | C11: Definition | D11: Count
A12: LOVE_ROMANCE | B12: Deductive | C12: Romantic love, courtship, flirtation | D12: =SUM(Code_Matrix!C2:C62) -> 8
A13: SEPARATION_LOSS | B13: Deductive | C13: Heartbreak, abandonment, waiting, lost love | D13: =SUM(Code_Matrix!D2:D62) -> 9
A14: FAMILY | B14: Deductive | C14: Parents, children, kin, household obligation | D14: =SUM(Code_Matrix!E2:E62) -> 11
A15: MONEY_MATERIALISM | B15: Deductive | C15: Money, wealth, earning as theme | D15: =SUM(Code_Matrix!F2:F62) -> 7
A16: CLASS_INEQUALITY_CRITIQUE | B16: Deductive | C16: Rich/poor contrast, critique of status hierarchy | D16: =SUM(Code_Matrix!G2:G62) -> 2
A17: CONSUMER_STATUS | B17: Emergent | C17: Status goods and consumption sites (car, necklace, restaurants) mediating relationships | D17: =SUM(Code_Matrix!H2:H62) -> 4
A18: MIGRATION | B18: Deductive | C18: Gulf/foreign labour migration | D18: =SUM(Code_Matrix!I2:I62) -> 1
A19: EDUCATION | B19: Deductive | C19: Schooling and its failure | D19: =SUM(Code_Matrix!J2:J62) -> 8
A20: DRIVER_IDENTITY | B20: Emergent | C20: Driver/vehicle self-reference; the inscription speaks as or about the driver | D20: =SUM(Code_Matrix!K2:K62) -> 8
A21: LABOR_DIGNITY | B21: Emergent | C21: Defence of the occupation against stigma; work conditions; exhaustion | D21: =SUM(Code_Matrix!L2:L62) -> 4
A22: FARE_LIVELIHOOD | B22: Emergent | C22: The fare as moral and economic flashpoint | D22: =SUM(Code_Matrix!M2:M62) -> 5
A23: MASCULINITY | B23: Deductive | C23: Male roles, provider burden, manhood norms | D23: =SUM(Code_Matrix!N2:N62) -> 4
A24: WOMEN_REPRESENTATION | B24: Deductive | C24: How women are described, addressed or blamed | D24: =SUM(Code_Matrix!O2:O62) -> 10
A25: SELF_RESPECT | B25: Emergent | C25: Dignity, refusal to bow, self-assertion, swagger | D25: =SUM(Code_Matrix!P2:P62) -> 7
A26: DISTRUST_HYPOCRISY | B26: Emergent | C26: World as selfish; kin/people as fair-weather; words vs. deeds | D26: =SUM(Code_Matrix!Q2:Q62) -> 11
A27: MORAL_ADVICE | B27: Deductive | C27: Didactic or ethical instruction | D27: =SUM(Code_Matrix!R2:R62) -> 10
A28: HOPE_RESILIENCE | B28: Deductive | C28: Patience, endurance, optimism | D28: =SUM(Code_Matrix!S2:S62) -> 4
A29: RELIGION_FATE | B29: Deductive | C29: Deity, scripture, mythology, prayer | D29: =SUM(Code_Matrix!T2:T62) -> 5
A30: MORTALITY_RISK | B30: Deductive | C30: Death, disaster, road risk, impermanence | D30: =SUM(Code_Matrix!U2:U62) -> 4
A31: INSTITUTION_CRITIQUE | B31: Deductive | C31: Courts, politicians, parties, the state | D31: =SUM(Code_Matrix!V2:V62) -> 4
A32: PLACE_IDENTITY | B32: Deductive | C32: Named places, regional demonyms, rural–urban | D32: =SUM(Code_Matrix!W2:W62) -> 17
A33: HUMOR | B33: Deductive | C33: Jokes, irony, satire, teasing | D33: =SUM(Code_Matrix!X2:X62) -> 4
A34: CODE_MIXING_SLANG | B34: Emergent | C34: English/Hindi mixing, youth slang, wordplay on slang | D34: =SUM(Code_Matrix!Y2:Y62) -> 0

Sheet Master_Dataset
A1: ID | B1: Original_Nepali | C1: Transliteration | D1: Original_Translation | E1: Original_Theme | F1: Normalized_Translation | G1: Text_Type | H1: Primary_Domain | I1: Secondary_Domains | J1: Emotion | K1: Emotion_Intensity | L1: Emotional_Target | M1: Relationship_Type | N1: Love_Type | O1: Cultural_Concepts | P1: Economic_Theme | Q1: Political_Theme | R1: Religious_Theme | S1: Gender_Theme | T1: Power_Hierarchy | U1: Identity_Theme | V1: Aspiration | W1: Agency | X1: Humor_Irony | Y1: Rhetorical_Device | Z1: Valence | AA1: Temporal_Orientation | AB1: Deeper_Meaning | AC1: Evidence | AD1: Confidence | AE1: Alternative_Interpretation | AF1: Human_Review | AG1: Review_Reason | AH1: Codes
A2: 1 | B2: भाडा लिऊँ भने इष्ट बाङ्गो; भाडा नलिऊँ भने आफू नाङ्गो। | C2: Bhāḍā liū̃ bhane iṣṭa bāṅgo; bhāḍā naliū̃ bhane āphū nāṅgo. | D2: If I ask for the fare, people become unhappy; if I do not ask for it, I suffer the loss myself. | E2: Livelihood, economic survival, dignity of labour, social pressure | F2: If I ask for the fare, my relatives and close ones turn sour; if I don't, I'm the one left with nothing. | G2: Folk saying|Couplet | H2: Economic / Livelihood | I2: Interpersonal (kin)|Occupational | J2: Frustration|Ambivalence | K2: Moderate | L2: Self|Kin and close acquaintances | M2: Worker–kin passenger | N2: N/A | O2: इष्ट (kin network)|kin obligation | P2: Explicit: fare as income vs. obligation | Q2: Not evident | R2: Not evident | S2: Not evident | T2: Reflection | U2: Occupational (driver/conductor) | V2: Not evident | W2: Individual — constrained | X2: Wry | Y2: Parallelism|Rhyme (बाङ्गो/नाङ्गो)|Double bind | Z2: Negative | AA2: Present | AB2: A double bind between kin obligation and livelihood; asking kin for money damages relationships, not asking erodes income. | AC2: इष्ट बाङ्गो / आफू नाङ्गो | AD2: High | AE2: — | AF2: Y | AG2: Translation renders इष्ट as 'people'; it means relatives/close ones, which is the core of the dilemma. | AH2: FARE_LIVELIHOOD|LABOR_DIGNITY|MONEY_MATERIALISM
A3: 2 | B3: तिमी स्त्री हौ, तिमीलाई हरकोहीकी प्यारी हुने हक छ। म त पुरुष हुँ, आफ्नै घरको प्यारो हुन पनि धन कमाउनुपर्छ। | C3: Timī strī hau, timīlāī harkohīkī pyārī hune hak cha. Ma ta puruṣ hũ, āphnai gharko pyāro huna pani dhan kamāunupardcha. | D3: You are a woman, and you have the right to be loved by anyone. But I am a man, and even to be loved in my own home, I have to earn money. | E3: Gender roles, masculinity, family expectations, money, patriarchy | F3: — | G3: Personal expression|Social commentary | H3: Gender | I3: Economic|Family | J3: Resentment|Self-pity | K3: Moderate | L3: Women (addressee)|Self|Family | M3: Man–woman (generic)|Family | N3: Storge (conditional) | O3: Male breadwinner norm | P3: Explicit: being loved at home is conditional on earning | Q3: Not evident | R3: Not evident | S3: Masculinity as provider burden; contrasts with a generalization that women are loved unconditionally | T3: Critique + Reproduction (critiques provider burden while reproducing a gender stereotype) | U3: Masculine | V3: Not evident | W3: Individual — constrained | X3: None | Y3: Antithesis (स्त्री / पुरुष) | Z3: Negative | AA3: Timeless | AB3: Frames male worth inside the family as earned through income. | AC3: आफ्नै घरको प्यारो हुन पनि धन कमाउनुपर्छ | AD3: High | AE3: — | AF3: Y | AG3: Original theme label 'patriarchy' is an interpretation; text explicitly describes the male breadwinner burden. Check label wording. | AH3: MASCULINITY|WOMEN_REPRESENTATION|MONEY_MATERIALISM|FAMILY
A4: 3 | B4: धनसम्पत्ति रहेछ यहाँ मायाभन्दा माथि; रित्तो गोजीको काम छैन, के गर्छौ त साथी? | C4: Dhan-sampatti rahecha yahā̃ māyābhanda māthi; ritto gojīko kām chaina, ke garchhau ta sāthī? | D4: It seems that wealth is valued above love here; an empty pocket is of no use, so what can you do, my friend? | E4: Materialism, poverty, economic status, changing values | F4: — | G4: Couplet|Social commentary | H4: Economic / Values | I4: Interpersonal | J4: Disillusionment|Resignation | K4: Moderate | L4: Society|Friend (addressee) | M4: Friendship (address form) | N4: Ambiguous | O4: माया | P4: Explicit: wealth ranked above love; empty pocket | Q4: Not evident | R4: Not evident | S4: Not evident | T4: Critique | U4: Not evident | V4: Not evident | W4: Not evident | X4: Wry | Y4: Rhetorical question|Rhyme (माथि/साथी) | Z4: Negative | AA4: Present | AB4: Observes a value order in which money outranks affection. | AC4: धनसम्पत्ति रहेछ यहाँ मायाभन्दा माथि | AD4: High | AE4: — | AF4: N | AG4: — | AH4: MONEY_MATERIALISM|CLASS_INEQUALITY_CRITIQUE|DISTRUST_HYPOCRISY
A5: 4 | B5: एक्कासी बाढी आयो, घर-आँगन बगायो। हेर्दाहेर्दै त्यो भेलले जिन्दगीभरको धन बगायो। घर त फेरि बन्ला, धन फेरि कमाइएला; कठैबरा, छिनभरमै कैयौँको जीवन बगायो। | C5: Ekkāsī bāḍhī āyo, ghar-ā̃gan bagāyo. Herdā-herdai tyo bhelle jindagībharko dhan bagāyo. Ghar ta pheri banlā, dhan pheri kamāielā; kaṭhaibarā, chhinbharmā kaiyaũko jīvan bagāyo. | D5: A sudden flood came and swept away homes and courtyards. Before our eyes, the torrent carried away wealth accumulated over a lifetime. A house can be rebuilt and wealth can be earned again, but, sadly, many lives were swept away in an instant. | E5: Natural disaster, loss, vulnerability, impermanence, human life | F5: — | G5: Elegy|Poetic expression | H5: Existential / Disaster | I5: Economic | J5: Grief|Sorrow|Compassion | K5: High | L5: Disaster victims | M5: Human–nature | N5: N/A | O5: कठैबरा (pity interjection) | P5: Explicit: lifetime wealth lost | Q5: Not evident | R5: Not evident | S5: Not evident | T5: N/A | U5: Not evident | V5: Not evident | W5: Nature | X5: None | Y5: Epistrophe (repeated बगायो)|Contrast (property vs. life) | Z5: Negative | AA5: Past | AB5: Ranks human life above recoverable property; event-specific rather than a general saying. | AC5: घर त फेरि बन्ला... कैयौँको जीवन बगायो | AD5: High | AE5: — | AF5: Y | AG5: Likely refers to a specific flood; date/location of the inscription unknown. | AH5: MORTALITY_RISK
A6: 5 | B6: नेपालीमा ‘माया’ अरे, हिन्दीमा ‘प्यार’; दुई बच्चाकी आमाले पनि ‘अङ्कल’ भन्छे यार। | C6: Nepālīmā “māyā” are, Hindīmā “pyār”; duī bacchākī āmāle pani “aṅkal” bhanche yār. | D6: In Nepali it is “maya,” and in Hindi it is “pyaar”; even a mother of two children calls someone “uncle,” my friend. | E6: Language, humour, changing relationships, popular culture, multilingualism | F6: In Nepali it's 'maya', in Hindi 'pyaar' — and even a mother of two calls me 'uncle', man! | G6: Humor|Wordplay|Couplet | H6: Humor | I6: Language|Ageing | J6: Amusement|Mild chagrin | K6: Low | L6: Self | M6: Driver–passenger | N6: N/A | P6: Not evident | Q6: Not evident | R6: Not evident | S6: Woman (mother of two) used as a measure of the speaker's age | T6: N/A | U6: Ageing male | V6: Not evident | W6: Not evident | X6: Self-deprecating: even a mother of two calls him 'uncle' | Y6: Rhyme (प्यार/यार)|Code-mixing (Hindi, English 'uncle') | Z6: Mixed | AA6: Present | AB6: The joke is on the speaker: he is being read as old. | AC6: दुई बच्चाकी आमाले पनि 'अङ्कल' भन्छे | AD6: Medium | AE6: — | AF6: Y | AG6: Original translation ('calls someone uncle') misses that the speaker is the one called uncle. | AH6: HUMOR|CODE_MIXING_SLANG
A7: 6 | B7: लुटेराको बस्तीमा जिन्दगी बित्यो मस्तीमा। | C7: Luṭerāko bastīmā jindagī bityo mastīmā. | D7: Life was spent joyfully in a settlement of looters. | E7: Social criticism, survival, humour, inequality, resilience | F7: — | G7: Aphorism|Satire | H7: Social | I7: Possible political | J7: Defiant cheer|Irony | K7: Moderate | L7: Society (unspecified 'looters') | M7: Not evident | N7: N/A | P7: Not evident | Q7: Possible critique of exploitative surroundings; not explicit | R7: Not evident | S7: Not evident | T7: Critique (ambiguous) | U7: Not evident | V7: Not evident | W7: Individual — resilient | X7: Irony / paradox | Y7: Rhyme (बस्तीमा/मस्तीमा)|Paradox | Z7: Mixed | AA7: Past | AB7: Joyful survival amid exploitation. | AC7: लुटेराको बस्तीमा ... मस्तीमा | AD7: Low | AE7: 'Looters' could be society, officials, the transport sector itself (self-mockery), or passengers. | AF7: Y | AG7: Referent of 'looters' ambiguous. | AH7: HUMOR|DISTRUST_HYPOCRISY|HOPE_RESILIENCE
A8: 7 | B8: उडायो तिम्रो पछ्यौरी, मेरो रफ्तारको के दोष? | C8: Uḍāyo timro pachhyauṛī, mero raftārko ke doṣ? | D8: My speed blew away your scarf; how is that my fault? | E8: Vehicle culture, speed, humour, flirtation, masculinity | F8: — | G8: Humor|Flirtation | H8: Vehicle culture | I8: Romance|Gender | J8: Playful bravado | K8: Low | L8: Woman (addressee) | M8: Stranger flirtation | N8: Eros (playful) | P8: Not evident | Q8: Not evident | R8: Not evident | S8: Male display through speed; deflection of responsibility | T8: Reproduction (mild) | U8: Driver | V8: Not evident | W8: Not evident | X8: Teasing deflection | Y8: Rhetorical question | Z8: Positive | AA8: Present | AB8: Speed as masculine display; the driver disclaims responsibility for its effects. | AC8: मेरो रफ्तारको के दोष? | AD8: High | AE8: — | AF8: N | AG8: — | AH8: HUMOR|MASCULINITY|LOVE_ROMANCE|DRIVER_IDENTITY
A9: 8 | B9: प्रभु येशू, म असल गोठालो हुँ। असल गोठालोले आफ्ना भेडाहरूका निम्ति आफ्नो प्राण अर्पण गर्छ। | C9: Prabhu Yeshu, ma asal goṭhālo hũ. Asal goṭhāle āphnā bheḍāharūkā nimti āphno prāṇ arpaṇ garcha. | D9: “I am the good shepherd.” The good shepherd gives his life for his sheep. | E9: Christian faith, sacrifice, religious identity, care, moral responsibility | F9: — | G9: Religious quotation | H9: Religious | I9: Moral | J9: Devotion|Reverence | K9: Moderate | L9: Christ | M9: Divine–devotee | N9: Agape (explicit self-sacrifice) | P9: Not evident | Q9: Not evident | R9: Christian; paraphrase of John 10:11 | S9: Not evident | T9: N/A | U9: Religious (of the display, not necessarily the owner) | V9: Not evident | W9: Divine | X9: None | Y9: Metaphor (shepherd/sheep) | Z9: Positive | AA9: Timeless | AB9: Sacrificial care as an ideal. | AC9: असल गोठालोले ... प्राण अर्पण गर्छ | AD9: High | AE9: — | AF9: Y | AG9: Nepali reads as the speaker addressing Jesus while saying 'I am the good shepherd' (in John 10:11 Jesus speaks). Verify the painted wording. Transliteration 'goṭhāle' ≠ गोठालोले. | AH9: RELIGION_FATE|MORAL_ADVICE
A10: 9 | B10: ढिला हुन्छ, तर सबै राम्रो हुन्छ; समय खराब हो, जिन्दगी होइन, साथी। | C10: Ḍhilā hunchha, tara sabai rāmrō hunchha; samaya kharāb ho, jindagī hoina, sāthī. | D10: It may take time, but everything will be fine; it is the time that is bad, not life itself, my friend. | E10: Hope, patience, hardship, optimism, resilience | F10: — | G10: Aphorism|Encouragement | H10: Philosophical / Hope | J10: Hope|Patience | K10: Moderate | L10: Friend / reader | M10: Friendship (address form) | N10: N/A | P10: Not evident | Q10: Not evident | R10: Not evident | S10: Not evident | T10: N/A | U10: Not evident | V10: Not evident | W10: Individual — resilient | X10: None | Y10: Antithesis (time vs. life) | Z10: Positive | AA10: Future | AB10: Separates temporary circumstance from the worth of life. | AC10: समय खराब हो, जिन्दगी होइन | AD10: High | AE10: — | AF10: Y | AG10: Duplicate of #47 (one-character variant होइन/हैन). Keep one, record the other as variant. | AH10: HOPE_RESILIENCE
A11: 10 | B11: किन पर्खी बस्थ्यौ र? खाडी जानेलाई धेरै–धेरै बधाई छ; छाडी जानेलाई तिम्रो बाँकी जिन्दगी सुखद अनि सफल बितोस्। यही शुभकामना टाढी जानेलाई माया। | C11: Kina parkhī basthyou ra? Khāḍī jānelāī dherai-dherai badhāī cha; chhāḍī jānelāī timro bā̃kī jindagī sukhad ani safal bitos. Yahī śubhakamana ṭāḍhī jānelāī māyā. | D11: Why would you keep waiting? Many congratulations to those going to the Gulf; to those leaving, may the rest of your life be happy and successful. These are my good wishes and love for those going far away. | E11: Foreign employment, migration, economic aspiration, separation, family | F11: Why would you have waited? Congratulations to the one going to the Gulf; to the one who left me, may the rest of your life be happy and successful — these good wishes, and love, to the one who went far away. | G11: Personal expression|Poetic expression | H11: Interpersonal / Romance | I11: Migration | J11: Wounded goodwill|Longing|Possible sarcasm | K11: Moderate | L11: Former lover | M11: Romantic (abandoned) | N11: Eros (lost) | O11: Gulf (खाडी) labour migration | P11: Explicit: Gulf migration | Q11: Not evident | R11: Not evident | S11: Not evident | T11: N/A | U11: Not evident | V11: Not evident | W11: Not evident | X11: None | Y11: Rhyme (खाडी/छाडी/टाढी)|Possible sarcasm | Z11: Mixed | AA11: Past/Future | AB11: A farewell that braids migration with romantic abandonment. | AC11: छाडी जानेलाई | AD11: Medium | AE11: (a) sincere farewell to migrants; (b) sarcastic farewell to a lover who left with/for a Gulf migrant. | AF11: Y | AG11: 'छाडी जाने' = the one who left (me), not 'those leaving'. First clause appears garbled. | AH11: MIGRATION|LOVE_ROMANCE|SEPARATION_LOSS
A12: 11 | B12: केलाउँछु धागोको माला, हार पाएपछि; के हिँड्थ्यो मसँग, कार पाएपछि? | C12: Kelāũchu dhāgoko mālā, hār pāepachi; ke hĩḍthyo ma-sãga, kār pāepachi? | D12: I will string a thread garland after receiving a necklace; why would someone walk with me after getting a car? | E12: Materialism, social status, wealth, changing relationships, consumer culture | F12: Who bothers sorting out a thread garland once they've got a (gold) necklace? Why would she walk with me once she's got a car? | G12: Couplet|Social commentary | H12: Interpersonal / Romance | I12: Economic / Status | J12: Bitterness|Disillusionment | K12: Moderate | L12: Former partner | M12: Romantic (lost to wealthier rival) | N12: Eros (lost) | P12: Explicit: necklace vs. thread garland; car | Q12: Not evident | R12: Not evident | S12: Not evident | T12: Reflection | U12: Not evident | V12: Not evident | W12: Not evident | X12: None | Y12: Rhyme and wordplay (हार/कार)|Rhetorical questions | Z12: Negative | AA12: Past | AB12: Love displaced by status goods. | AC12: के हिँड्थ्यो मसँग, कार पाएपछि? | AD12: Medium | AE12: — | AF12: Y | AG12: Original translation ('I will string a thread garland') misreads a rhetorical question. | AH12: LOVE_ROMANCE|SEPARATION_LOSS|CONSUMER_STATUS|MONEY_MATERIALISM
A13: 12 | B13: कहाँ मन परोस् अब बाटोमा उभिएर चटपटे र पानीपुरी खान, ठूला–ठूला रेस्टुरेन्ट पार लाने अरू कोही भेटेपछि? | C13: Kahā̃ mana paros aba bāṭomā ubhiera caṭpaṭe ra pānīpurī khān, ṭhūlā-ṭhūlā restoran pār lāne arū kohī bheṭepachi? | D13: How could I still enjoy standing by the roadside to eat chatpate and panipuri after meeting someone else who takes me to big restaurants? | E13: Consumer culture, social status, romantic relationships, changing aspirations, class | F13: — | G13: Personal expression|Satire | H13: Interpersonal / Romance | I13: Class / Consumption | J13: Bitterness|Wounded pride | K13: Moderate | L13: Former partner | M13: Romantic (lost to wealthier rival) | N13: Eros (lost) | P13: Explicit: street food vs. big restaurants as class markers | Q13: Not evident | R13: Not evident | S13: Not evident | T13: Critique | U13: Not evident | V13: Not evident | W13: Not evident | X13: None | Y13: Rhetorical question|Ventriloquism (voices the ex) | Z13: Negative | AA13: Past | AB13: Consumption sites encode class; romance follows them. | AC13: चटपटे र पानीपुरी ... ठूला–ठूला रेस्टुरेन्ट | AD13: Medium | AE13: Could be the speaker's own voice rather than ventriloquizing the ex. | AF13: N | AG13: — | AH13: LOVE_ROMANCE|SEPARATION_LOSS|CONSUMER_STATUS|CLASS_INEQUALITY_CRITIQUE
A14: 13 | B14: हाइ भन्दा ‘बाइ’ रे, नम्बर देऊ भन्दा ‘नाइ’ रे; रिस उठेर ‘लभ यू’ भन्देको, ‘ठट्टा नगर्नु दाइ’ रे। | C14: Hāi bhanda “bāi” re, nambar deu bhanda “nāi” re; ris uṭhera “love you” bhandeko, “ṭaṭṭā nagarnu dāi” re. | D14: Say “Hi,” and she says “Bye”; ask for her number, and she says “No”; say “I love you” in frustration, and she says, “Don’t joke, brother.” **I call her I call her darling but she calls me dustbin**. | E14: Youth culture, courtship, gender relations, rejection, humour, English influence | F14: — | G14: Humor|Courtship narrative | H14: Interpersonal / Youth | I14: Language | J14: Frustration|Amusement | K14: Moderate | L14: Woman | M14: Courtship (rejected) | N14: Eros (unrequited) | P14: Not evident | Q14: Not evident | R14: Not evident | S14: Courtship script; rejection via 'दाइ' (brother-zoning) | T14: N/A | U14: Youth | V14: Not evident | W14: Not evident | X14: Escalating rejection | Y14: Rhyme (बाइ/नाइ/दाइ)|Code-mixing (hi, bye, love you) | Z14: Mixed | AA14: Past | AB14: Comic narration of failed courtship. | AC14: 'ठट्टा नगर्नु दाइ' रे | AD14: High | AE14: — | AF14: Y | AG14: Translation field contains an appended bold English line ('I call her I call her darling but she calls me dustbin') absent from the Nepali; likely a separate inscription. Split or remove. | AH14: HUMOR|LOVE_ROMANCE|CODE_MIXING_SLANG|WOMEN_REPRESENTATION
A15: 14 | B15: दुवै नभए कतार छ, हामीलाई अलिक हतार छ। | C15: Duvai nabhae Qatar cha, hāmīlāī alik hatār cha. | D15: If neither of the two works, Qatar is there; we are in somewhat of a hurry. | E15: Foreign employment, migration, economic pressure, youth aspiration | F15: — | G15: Slogan|Humor | H15: Economic / Migration | J15: Urgency|Resigned humour | K15: Low | L15: Self / peers | M15: Not evident | N15: N/A | P15: Explicit: Qatar as fallback | Q15: Not evident | R15: Not evident | S15: Not evident | T15: N/A | U15: Youth|Migrant | V15: Migration as default exit | W15: Constrained | X15: Deadpan | Y15: Rhyme (कतार/हतार) | Z15: Mixed | AA15: Future | AB15: Labour migration as the default option. | AC15: दुवै नभए कतार छ | AD15: Medium | AE15: — | AF15: Y | AG15: 'दुवै' (both) has no referent; likely a fragment of a longer couplet (cf. #54). | AH15: MIGRATION|HUMOR
A16: 15 | B16: गाडी हो मुगालीको, आवाज दिन्छ फाइबरको; दुनियाँका छोरी पोइल जान्छन्, दोष किन ड्राइभरको? | C16: Gāḍī ho Mugālīko, āwāj dincha phāibarko; duniyākā chorī poil jānchan, doṣ kina ḍrāibarko? | D16: The vehicle belongs to Mugali and makes a sound like fibre; girls in this world marry and leave, so why blame the driver? | E16: Marriage, gender, responsibility and blame, mobility, humour | F16: The vehicle belongs to a Mugali (a person from Mugu); it sounds like fibre. The world's daughters elope — why blame the driver? | G16: Couplet|Humor | H16: Gender | I16: Driver identity|Place | J16: Defensiveness|Playful | K16: Moderate | L16: Society | M16: Driver–society | N16: N/A | P16: Not evident | Q16: Not evident | R16: Not evident | S16: Women's elopement (पोइल जानु); deflects blame from drivers | T16: Reproduction (ambiguous) | U16: Regional (मुगाली, Mugu)|Driver | V16: Not evident | W16: Not evident | X16: Deflection | Y16: Rhyme (फाइबर/ड्राइभर)|Rhetorical question | Z16: Mixed | AA16: Present | AB16: Responds to a stereotype of drivers as eloping partners; places agency on women. | AC16: छोरी पोइल जान्छन्, दोष किन ड्राइभरको? | AD16: Medium | AE16: — | AF16: Y | AG16: 'पोइल जानु' means a woman eloping/leaving with a man, not 'marry and leave'. 'Mugali' is a demonym, not a name. 'आवाज दिन्छ फाइबरको' unclear. | AH16: DRIVER_IDENTITY|WOMEN_REPRESENTATION|PLACE_IDENTITY|HUMOR
A17: 16 | B17: हेर्दै जाऊ, मेरो यादमा रुने बनाउँछु; फोटो च्याती आगो बाल्ने तिम्रा हातहरू हरेक पल मेरै तस्बिर छुने बनाउँछु। | C17: Herdai jāu, mero yādamā rune banāũchu; phoṭo chyātī āgo bālne timrā hātarū harek pal merai tasbīr chhune banāũchu. | D17: Just wait and see; I will make you cry in my memory. I will make the hands that tore up my photograph and burned it touch my picture every moment. | E17: Love, heartbreak, memory, separation, emotional attachment | F17: — | G17: Personal expression|Poetic expression | H17: Interpersonal / Romance | J17: Wounded love|Vindictive longing | K17: High | L17: Former lover | M17: Romantic (rejected) | N17: Eros (lost) | P17: Not evident | Q17: Not evident | R17: Not evident | S17: Not evident | T17: N/A | U17: Not evident | V17: Not evident | W17: Individual — claims control over the ex's future feelings | X17: None | Y17: Hyperbole|Image (burning photograph) | Z17: Negative | AA17: Future | AB17: Heartbreak turned into a promise of emotional reversal. | AC17: मेरो यादमा रुने बनाउँछु | AD17: High | AE17: — | AF17: N | AG17: — | AH17: LOVE_ROMANCE|SEPARATION_LOSS
A18: 17 | B18: ड्राइभर भन्छ: सबैले मलाई कर्म मेरो मोटर गुडाउने; कच्ची बाटो हिँड्नुपर्छ, कान्छी, रहर होइन धुलो उडाउने। | C18: Ḍrāibar bhancha: sabaile malāī karma mero moṭar guḍāune; kacchī bāṭo hĩḍnupardcha, kāñchhī, rahar hoina dhulo uḍāune. | D18: The driver says: my work is to drive the vehicle; I have to travel on rough roads, dear, and raising dust is not my hobby. | E18: Dignity of labour, occupation, rural roads, infrastructure, working conditions | F18: — | G18: Personal expression | H18: Occupational | I18: Infrastructure | J18: Weariness|Self-justification | K18: Moderate | L18: Woman (कान्छी)|Passers-by | M18: Driver–public | N18: N/A | O18: कर्म (duty/occupation) | P18: Implicit: work conditions | Q18: Not evident | R18: Not evident | S18: Not evident | T18: N/A | U18: Driver | V18: Not evident | W18: Constrained | X18: None | Y18: Rhyme (गुडाउने/उडाउने) | Z18: Mixed | AA18: Present | AB18: Dust is a condition of the work, not a choice. | AC18: रहर होइन धुलो उडाउने | AD18: High | AE18: — | AF18: Y | AG18: First clause syntax garbled ('सबैले मलाई कर्म मेरो'); verify against source photo. | AH18: DRIVER_IDENTITY|LABOR_DIGNITY
A19: 18 | B19: बाल नदिनेहरूको अगाडि बबाल भएर हिँड्न मन छ। | C19: Bāl nadineharūko agāḍi babāl bhaera hĩḍna man cha. | D19: I want to walk boldly before those who pay no attention to me. | E19: Self-respect, recognition, confidence, youth culture, social status | F19: I want to strut, looking awesome, in front of those who don't give a damn about me. | G19: Slang|Self-assertion | H19: Self-regard | J19: Defiant pride | K19: Moderate | L19: Those who ignore the speaker | M19: Not evident | N19: N/A | P19: Not evident | Q19: Not evident | R19: Not evident | S19: Not evident | T19: N/A | U19: Youth | V19: Not evident | W19: Not evident | X19: Swagger | Y19: Wordplay (बाल/बबाल)|Slang | Z19: Positive | AA19: Present | AB19: Recognition sought through display. | AC19: बाल नदिनेहरू ... बबाल | AD19: High | AE19: — | AF19: N | AG19: — | AH19: SELF_RESPECT|CODE_MIXING_SLANG
A20: 19 | B20: घरि–घरि यही जताउन आउँछ तिम्रो याद; म तिमी हुँ भनी बताउन आउँछ तिम्रो याद। | C20: Gharī-ghari yahī jatauna āũcha timro yād; ma timī hũ bhanī batauna āũcha timro yād. | D20: Your memory keeps returning again and again to remind me; your memory comes to tell me that I am you. | E20: Memory, love, identity, emotional attachment, nostalgia | F20: — | G20: Poetic expression | H20: Interpersonal / Romance | J20: Longing|Attachment | K20: Moderate | L20: Lover | M20: Romantic (separated) | N20: Eros (longing) | P20: Not evident | Q20: Not evident | R20: Not evident | S20: Not evident | T20: N/A | U20: Merged self (म तिमी हुँ) | V20: Not evident | W20: Not evident | X20: None | Y20: Repetition (आउँछ तिम्रो याद) | Z20: Mixed | AA20: Past/Present | AB20: Memory so persistent it dissolves self/other boundaries. | AC20: म तिमी हुँ भनी | AD20: High | AE20: — | AF20: N | AG20: — | AH20: LOVE_ROMANCE|SEPARATION_LOSS
A21: 20 | B21: मनमा जति नै पीडा भए पनि, ओठमा हाँसो लिएर चढ; तिमी मेरै GF भए पनि, झर्ने बेला भाडा दिएर झर। | C21: Manmā jati nai pīḍā bhae pani, oṭhmā hā̃so lie-ra chaḍha; timī merai GF bhae pani, jharne belā bhāḍā die-ra jhara. | D21: No matter how much pain you have in your heart, board with a smile; even if you are my girlfriend, pay the fare when you get off. | E21: Emotional resilience, romantic relationships, money, humour, professional boundaries | F21: — | G21: Humor|Couplet | H21: Economic / Livelihood | I21: Romance | J21: Wry | K21: Low | L21: Girlfriend / passenger | M21: Romantic (playful) | N21: Eros (playful) | P21: Explicit: fare | Q21: Not evident | R21: Not evident | S21: Not evident | T21: N/A | U21: Not evident | V21: Not evident | W21: Not evident | X21: Love vs. fare | Y21: Rhyme (चढ/झर)|Code-mixing (GF) | Z21: Mixed | AA21: Present | AB21: Affection does not suspend payment. | AC21: झर्ने बेला भाडा दिएर झर | AD21: High | AE21: — | AF21: Y | AG21: Template variant of #23; record as variants of one inscription type. | AH21: FARE_LIVELIHOOD|HUMOR|LOVE_ROMANCE|CODE_MIXING_SLANG|HOPE_RESILIENCE
A22: 21 | B22: जङ्गलको बाटो हिँड्दैछु, सिकारी नभन्नु; लागेको भाडा माग्छु, भिकारी नभन्नु। | C22: Jaṅgalko bāṭo hĩḍdaichu, sikārī nabhannu; lāgeko bhāḍā māgchu, bhikārī nabhannu. | D22: I am travelling along a forest road, so do not call me a hunter; I ask for the fare that is due, so do not call me a beggar. | E22: Dignity of labour, livelihood, poverty and stigma, self-respect, rural life | F22: — | G22: Couplet | H22: Occupational dignity | J22: Indignation|Self-respect | K22: Moderate | L22: Passengers | M22: Driver–passenger | N22: N/A | P22: Explicit: due fare | Q22: Not evident | R22: Not evident | S22: Not evident | T22: Resistance (to stigma) | U22: Driver | V22: Not evident | W22: Not evident | X22: None | Y22: Rhyme (सिकारी/भिकारी)|Analogy | Z22: Mixed | AA22: Present | AB22: Asking for earned payment is not begging. | AC22: लागेको भाडा माग्छु, भिकारी नभन्नु | AD22: High | AE22: — | AF22: N | AG22: — | AH22: FARE_LIVELIHOOD|LABOR_DIGNITY|SELF_RESPECT
A23: 22 | B23: नपल्टाउनु अब मेरो जिन्दगीका पुराना पानाहरू; पहिले जे थियो, त्यस्तै छैन। अहिले कस्तो छु, यो कसैलाई थाहा छैन। | C23: Napalṭāunu aba mero jindagīkā purānā pānāharū; pahile je thiyo, tyastai chaina. Ahile kasto chu, yo kasailāī thāhā chaina. | D23: Do not turn back the old pages of my life. I am no longer what I was before. No one knows what I am like now. | E23: Changing identity, transformation, past and present, memory, social judgment | F23: — | G23: Personal expression | H23: Self / Identity | J23: Guardedness|Quiet pride | K23: Moderate | L23: Others who judge | M23: Not evident | N23: N/A | P23: Not evident | Q23: Not evident | R23: Not evident | S23: Not evident | T23: N/A | U23: Transformed self | V23: Not evident | W23: Not evident | X23: None | Y23: Metaphor (pages of life) | Z23: Mixed | AA23: Past vs. Present | AB23: Refusal to be defined by one's past. | AC23: पहिले जे थियो, त्यस्तै छैन | AD23: High | AE23: — | AF23: N | AG23: — | AH23: SELF_RESPECT
A24: 23 | B24: सुन माया, आँखाभरि आँसु भए पनि ओठमा मुस्कान लिएर चढ; तिमी मेरी प्यारी भए पनि भाडा दिएर झर। | C24: Suna māyā, ā̃khābhari ā̃su bhae pani oṭhmā muskān lie-ra chaḍha; timī merī pyārī bhae pani bhāḍā die-ra jhara. | D24: Listen, my love: even if your eyes are filled with tears, board with a smile; even if you are my beloved, pay the fare when you get off. | E24: Love and separation; emotional resilience; livelihood; humour; professional responsibility. | F24: — | G24: Humor|Couplet | H24: Economic / Livelihood | I24: Romance | J24: Wry tenderness | K24: Low | L24: Beloved / passenger | M24: Romantic (playful) | N24: Eros (playful) | P24: Explicit: fare | Q24: Not evident | R24: Not evident | S24: Not evident | T24: N/A | U24: Not evident | V24: Not evident | W24: Not evident | X24: Love vs. fare | Y24: Rhyme (चढ/झर) | Z24: Mixed | AA24: Present | AB24: Same template as #20 with tears in place of pain. | AC24: भाडा दिएर झर | AD24: High | AE24: — | AF24: Y | AG24: Template variant of #20. | AH24: FARE_LIVELIHOOD|HUMOR|LOVE_ROMANCE|HOPE_RESILIENCE
A25: 24 | B25: निद्रा के हो, ड्राइभरलाई सोध; पीडा के हो, परदेशीलाई सोध; आँसु के हो, आमालाई सोध; भोक के हो, अनाथ बच्चालाई सोध; जिन्दगी के हो, बुबालाई सोध; जलन के हो, आफन्तलाई सोध। | C25: Nidrā ke ho, ḍrāibar-lāī sodha; pīḍā ke ho, pardeshī-lāī sodha; ā̃su ke ho, āmā-lāī sodha; bhok ke ho, anāth bacchā-lāī sodha; jindagī ke ho, bubā-lāī sodha; jalan ke ho, āphant-lāī sodha. | D25: Ask a driver what sleep is; ask a migrant what pain is; ask a mother what tears are; ask an orphaned child what hunger is; ask a father what life is; ask relatives what jealousy is. | E25: Labour and exhaustion; migration; motherhood; poverty; orphanhood; family; jealousy; human suffering. | F25: — | G25: Aphorism|List poem | H25: Existential / Suffering | I25: Family|Labour|Migration | J25: Pathos|Sorrow | K25: High | L25: Social roles | M25: Family|Kin | N25: N/A | O25: जलन (jealousy) attributed to relatives | P25: Not evident | Q25: Not evident | R25: Not evident | S25: Not evident | T25: N/A | U25: Driver|Migrant|Mother|Father|Orphan | V25: Not evident | W25: Not evident | X25: None | Y25: Anaphora ('X के हो, Y लाई सोध') | Z25: Negative | AA25: Timeless | AB25: Each role is defined by its characteristic suffering; relatives defined by jealousy. | AC25: निद्रा के हो, ड्राइभरलाई सोध... | AD25: High | AE25: — | AF25: N | AG25: — | AH25: DRIVER_IDENTITY|LABOR_DIGNITY|MIGRATION|FAMILY|DISTRUST_HYPOCRISY
A26: 25 | B26: चौरजहारीमा चट्ट कम्मर छिनेको; जाने भए जाम कान्छी, म त सुर्खेततिर हिँडेको। | C26: Caurjahārīmā caṭṭa kammar chineko; jāne bhae jām kāñchhī, ma ta Surkhet-tira hĩḍeko. | D26: In Chaurjahari, with a strikingly slender waist; if you want to come, let us go, dear—I am heading toward Surkhet. | E26: Local identity; mobility; romance; regional geography; popular culture. | F26: — | G26: Folk-song line|Flirtation | H26: Romance | I26: Place | J26: Playful desire | K26: Moderate | L26: Woman (कान्छी) | M26: Flirtation | N26: Eros | P26: Not evident | Q26: Not evident | R26: Not evident | S26: Female body described (slender waist) | T26: Reproduction (mild) | U26: Regional (Chaurjahari → Surkhet) | V26: Not evident | W26: Not evident | X26: None | Y26: Invitation formula | Z26: Positive | AA26: Present | AB26: Karnali route geography carries a romantic invitation. | AC26: चौरजहारीमा ... सुर्खेततिर | AD26: Medium | AE26: — | AF26: Y | AG26: Resembles a lok-geet line; check if quoted from a known song. | AH26: PLACE_IDENTITY|LOVE_ROMANCE|WOMEN_REPRESENTATION
A27: 26 | B27: तिमी त नफर्किने खोला रहेछौ, तर म भने किनारा बनी पर्खिरहेँ। बाटो कठिन भए पनि हिम्मत हारिन्न। | C27: Timī ta nafarkine kholā rahechau, tara ma bhane kinārā banī parkhirahẽ. Bāṭo kaṭhin bhae pani himmat hārinna. | D27: You are like a river that never returns, yet I remain waiting like its shore. Even if the road is difficult, I will not lose courage. | E27: Love and separation; waiting; perseverance; hardship; hope. | F27: — | G27: Poetic expression | H27: Interpersonal / Romance | J27: Longing|Perseverance | K27: Moderate | L27: Absent lover | M27: Romantic (separated) | N27: Eros (waiting) | P27: Not evident | Q27: Not evident | R27: Not evident | S27: Not evident | T27: N/A | U27: Not evident | V27: Not evident | W27: Individual — resilient | X27: None | Y27: Metaphor (river / shore) | Z27: Mixed | AA27: Past/Future | AB27: Waiting as fidelity; second sentence generalizes to courage. | AC27: नफर्किने खोला ... किनारा बनी पर्खिरहेँ | AD27: High | AE27: — | AF27: Y | AG27: Second sentence may be a separate slogan joined to the first. | AH27: LOVE_ROMANCE|SEPARATION_LOSS|HOPE_RESILIENCE
A28: 27 | B28: सागरझैँ शान्त बन, तुफानझैँ जोश गर; दुनियाँ सारा स्वार्थी छ, कदम–कदममा होस गर। | C28: Sāgarjhaĩ śānta bana, tufān-jhaĩ jośa gara; duniyā sārā svārthī cha, kadam-kadammā hos gara. | D28: Be calm like the ocean and passionate like a storm; the world is full of self-interest, so be cautious at every step. | E28: Self-control; ambition; caution; distrust; social reality; personal wisdom. | F28: — | G28: Aphorism|Advice | H28: Moral / Advice | J28: Vigilance | K28: Moderate | L28: Reader | M28: Not evident | N28: N/A | P28: Not evident | Q28: Not evident | R28: Not evident | S28: Not evident | T28: N/A | U28: Not evident | V28: Not evident | W28: Not evident | X28: None | Y28: Simile (ocean / storm) | Z28: Mixed | AA28: Timeless | AB28: Balance of calm and passion amid a selfish world. | AC28: दुनियाँ सारा स्वार्थी छ | AD28: High | AE28: — | AF28: N | AG28: — | AH28: MORAL_ADVICE|DISTRUST_HYPOCRISY
A29: 28 | B29: यो पैसा कसले बनायो? जसले बनायो, बेकार बनायो। हुनेलाई त ठिकै छ, तर नहुनेलाई दिग्दार बनायो। | C29: Yo paisā kasle banāyo? Jasle banāyo, bekār banāyo. Hunelāī ta ṭhikai cha, tara nahunelāī digdār banāyo. | D29: Who created this money? Whoever created it made it troublesome. It may be fine for those who have it, but it has made life difficult for those who do not. | E29: Money and inequality; poverty; economic injustice; materialism; social frustration. | F29: — | G29: Social commentary | H29: Economic / Inequality | J29: Frustration | K29: Moderate | L29: Money / unnamed creator | M29: Not evident | N29: N/A | P29: Explicit: haves vs. have-nots | Q29: Not evident | R29: Not evident | S29: Not evident | T29: Critique | U29: Not evident | V29: Not evident | W29: Not evident | X29: None | Y29: Rhetorical question|Rhyme (बनायो) | Z29: Negative | AA29: Present | AB29: Money as the source of unequal suffering. | AC29: नहुनेलाई दिग्दार बनायो | AD29: High | AE29: — | AF29: N | AG29: — | AH29: MONEY_MATERIALISM|CLASS_INEQUALITY_CRITIQUE
A30: 29 | B30: बितेर जानेछ यो दुःखको घडी पनि; अलिकति धैर्य गरिदेऊ न, आमा। | C30: Biter jānecha yo duḥkhako ghaḍī pani; alikati dhairya garideu na, āmā. | D30: This difficult time will also pass; please have a little patience, Mother. | E30: Hope; family; hardship; patience; emotional support; resilience. | F30: — | G30: Personal expression|Encouragement | H30: Family / Hope | J30: Hope|Tenderness | K30: Moderate | L30: Mother | M30: Parent–child | N30: Storge | P30: Not evident | Q30: Not evident | R30: Not evident | S30: Not evident | T30: N/A | U30: Not evident | V30: Not evident | W30: Individual — resilient | X30: None | Y30: Direct address | Z30: Positive | AA30: Future | AB30: Child comforting mother through hardship. | AC30: अलिकति धैर्य गरिदेऊ न, आमा | AD30: High | AE30: — | AF30: N | AG30: — | AH30: FAMILY|HOPE_RESILIENCE
A31: 30 | B31: सम्पत्ति हुँदा शत्रु बढ्छन्; सम्पत्ति नहुँदा आफन्त घट्छन्। धन देखे नाता जोड्छन्; गरिब देखे साथ छोड्छन्। | C31: Sampatti hundā śatru baḍhchan; sampatti nahundā āphanta ghaṭchan. Dhan dekhe nātā joḍchan; garīb dekhe sātha choḍchan. | D31: When you have wealth, your enemies increase; when you have no wealth, your relatives decrease. People establish relationships when they see money and abandon you when they see poverty. | E31: Wealth and relationships; class inequality; hypocrisy; poverty; social discrimination. | F31: — | G31: Aphorism | H31: Economic / Relationships | J31: Cynicism|Disillusionment | K31: Moderate | L31: Relatives / society | M31: Kin | N31: N/A | P31: Explicit: wealth shapes kinship | Q31: Not evident | R31: Not evident | S31: Not evident | T31: Critique | U31: Not evident | V31: Not evident | W31: Not evident | X31: None | Y31: Parallelism|Chiasmus | Z31: Negative | AA31: Timeless | AB31: Kinship tracks wealth. | AC31: धन देखे नाता जोड्छन्; गरिब देखे साथ छोड्छन् | AD31: High | AE31: — | AF31: N | AG31: — | AH31: MONEY_MATERIALISM|CLASS_INEQUALITY_CRITIQUE|DISTRUST_HYPOCRISY|FAMILY
A32: 31 | B32: कलम रोए कवि बन्छ; कवि रोए कविता। धनी मरे श्रद्धाञ्जली; गरिब मरे रमिता। | C32: Kalam roe kavi bancha; kavi roe kavitā. Dhanī mare śraddhāñjalī; garīb mare ramitā. | D32: When the pen weeps, it becomes a poet; when the poet weeps, it becomes poetry. When the rich die, there are tributes; when the poor die, it becomes a spectacle. | E32: Literature; class inequality; death; social hypocrisy; dignity; social criticism. | F32: — | G32: Aphorism|Social commentary | H32: Class / Death | J32: Bitterness|Sorrow | K32: Moderate | L32: Society | M32: Not evident | N32: N/A | P32: Explicit: rich vs. poor | Q32: Not evident | R32: Not evident | S32: Not evident | T32: Critique | U32: Not evident | V32: Not evident | W32: Not evident | X32: None | Y32: Chain construction|Antithesis (श्रद्धाञ्जली/रमिता) | Z32: Negative | AA32: Timeless | AB32: Even death is ranked by class. | AC32: धनी मरे श्रद्धाञ्जली; गरिब मरे रमिता | AD32: High | AE32: — | AF32: N | AG32: — | AH32: CLASS_INEQUALITY_CRITIQUE|MORTALITY_RISK
A33: 32 | B33: मर्द आफ्नो सपनासँग लड्छ; नामर्द अर्काको रिस गर्छ। | C33: Marda āphno sapanāsãga laḍcha; nāmarda arkāko ris garcha. | D33: A courageous man struggles with his own dreams; a coward is consumed by resentment toward others. | E33: Masculinity; ambition; self-reliance; jealousy; personal struggle. | F33: A real man fights with his own dreams; an unmanly one resents others. | G33: Aphorism | H33: Gender / Masculinity | J33: Determination|Contempt | K33: Moderate | L33: Men | M33: Not evident | N33: N/A | P33: Not evident | Q33: Not evident | R33: Not evident | S33: मर्द/नामर्द: courage coded as manhood | T33: Reproduction | U33: Masculine | V33: Not evident | W33: Not evident | X33: None | Y33: Antithesis | Z33: Mixed | AA33: Timeless | AB33: Ambition framed as a test of manhood. | AC33: मर्द ... नामर्द | AD33: High | AE33: — | AF33: Y | AG33: 'coward' loses the gendered insult in नामर्द. | AH33: MASCULINITY|SELF_RESPECT|MORAL_ADVICE
A34: 33 | B34: “नाइँ, मलाई तिमी नै चाहिन्छ” रे; म घोप्टिनी फुस्कियो कि क्या हो? “चाहिन्छ” भन्दैमा अर्काको बडो कहाँ पाइन्छ त नि? | C34: “Nāĩ, malāī timī nai cāhincha” re; ma ghopṭinī phuskio ki kyā ho? “Cāhincha” bhandaimā arkāko baḍo kahā̃ pāincha ta ni? | D34: “No, I want only you,” she says. Have I somehow become foolish enough to fall for it? Just because someone says they want something does not mean they can have what belongs to someone else. | E34: Romantic relationships; desire; social boundaries; humour; possessiveness; interpersonal relationships. | F34: — | G34: Humor | H34: Interpersonal / Romance | J34: Amusement|Suspicion | K34: Moderate | L34: Woman | M34: Romantic (contested) | N34: Eros | P34: Not evident | Q34: Not evident | R34: Not evident | S34: Not evident | T34: N/A | U34: Not evident | V34: Not evident | W34: Not evident | X34: Mock incredulity | Y34: Reported speech|Rhetorical question | Z34: Mixed | AA34: Present | AB34: Comic suspicion of a declaration of love; claims over 'someone else's' partner. | AC34: अर्काको ... कहाँ पाइन्छ | AD34: Low | AE34: — | AF34: Y | AG34: घोप्टिनी, फुस्कियो and बडो unclear; translation uncertain. | AH34: HUMOR|LOVE_ROMANCE
A35: 34 | B35: शान्तिनेलाई दिइँदैन मान; आयो सल्यानको राजा, आफैँ जान। | C35: Śāntinelāī dĩdaina māna; āyo Salyānko rājā, āphaĩ jāna. | D35: No respect is given to Shantineli; when the king of Salyan arrives, he goes on his own way. | E35: Local identity; regional rivalry; humour; status; place-based pride. | F35: — | G35: Humor|Regional boast | H35: Place / Status | J35: Swagger | K35: Moderate | L35: Other road users | M35: Not evident | N35: N/A | P35: Not evident | Q35: Not evident | R35: Not evident | S35: Not evident | T35: N/A | U35: Regional (Salyan) | V35: Not evident | W35: Not evident | X35: Mock royalty | Y35: Self-aggrandizing title ('राजा') | Z35: Mixed | AA35: Present | AB35: Place-based pride in a mock-royal register. | AC35: आयो सल्यानको राजा | AD35: Low | AE35: 'Respect isn't given to the meek; the king of Salyan has arrived — move aside yourselves.' | AF35: Y | AG35: शान्तिने and आफैँ जान unclear; original translation doubtful. | AH35: PLACE_IDENTITY|HUMOR|SELF_RESPECT
A36: 35 | B36: बुवाले कुन उमेरसम्म कमाउनुपर्छ? त्यो छोरामा भर पर्छ, बुवामा होइन। | C36: Buvāle kun umer-samma kamāunupardcha? Tyo chhorāmā bhar parcha, buvāmā hoina. | D36: Until what age must a father keep earning? That depends on the son, not on the father. | E36: Parent–child relations; filial responsibility; ageing; family economics; generational expectations. | F36: — | G36: Aphorism | H36: Family / Intergenerational | J36: Moral reproach | K36: Moderate | L36: Sons | M36: Parent–child | N36: Storge | O36: Filial duty | P36: Explicit: father's earning age | Q36: Not evident | R36: Not evident | S36: Son (not child) named as responsible | T36: Reflection | U36: Not evident | V36: Not evident | W36: Not evident | X36: None | Y36: Question and answer | Z36: Mixed | AA36: Timeless | AB36: Places responsibility for ageing fathers on sons. | AC36: त्यो छोरामा भर पर्छ | AD36: High | AE36: — | AF36: N | AG36: — | AH36: FAMILY|MORAL_ADVICE
A37: 36 | B37: साथ कहिल्यै नछाड्नु है, माया, सुखमा होस् या दुःखको मोडमा। ड्राइभर भनेर कहिले हेला नगर्नु है, माया; तिमी नै त हौ, रोडमा होस् या करोडमा। | C37: Sātha kahilyai nachāḍnu hai, māyā, sukhmā hos yā duḥkhako moḍmā. Ḍrāibar bhanera kahile helā nagarnu hai, māyā; timī nai ta hau, roḍmā hos yā karoḍmā. | D37: Never leave my side, my love, whether in happiness or at a difficult turn in life. Never look down on me because I am a driver; you are the one, whether on the road or among the wealthy. | E37: Love; loyalty; dignity of labour; social status; class; romantic commitment. | F37: — | G37: Couplet|Romantic expression | H37: Romance / Dignity | I37: Class | J37: Devotion|Vulnerability | K37: Moderate | L37: Lover | M37: Romantic (committed) | N37: Eros (committed) | P37: Explicit: road vs. crore | Q37: Not evident | R37: Not evident | S37: Not evident | T37: Resistance (to stigma) | U37: Driver | V37: Not evident | W37: Not evident | X37: None | Y37: Wordplay (रोड/करोड)|Rhyme (मोडमा/करोडमा) | Z37: Positive | AA37: Future | AB37: Asks love not to follow occupational stigma. | AC37: ड्राइभर भनेर कहिले हेला नगर्नु | AD37: High | AE37: — | AF37: N | AG37: — | AH37: LOVE_ROMANCE|LABOR_DIGNITY|DRIVER_IDENTITY|SELF_RESPECT
A38: 37 | B38: संसारमा सबैभन्दा बढी झुट अदालतमा बोलिन्छ र सबैभन्दा बढी सत्य भट्टीमा बोलिन्छ। | C38: Saṁsāramā sabaibhanda baḍhī jhuṭa adālatmā bolincha ra sabaibhanda baḍhī satya bhaṭṭīmā bolincha. | D38: In this world, the most lies are spoken in courts, while the most truth is spoken in taverns. | E38: Truth and deception; justice; law; alcohol culture; social hypocrisy; humour. | F38: — | G38: Aphorism|Satire | H38: Institutional / Legal | J38: Cynicism|Amusement | K38: Moderate | L38: Courts | M38: Not evident | N38: N/A | P38: Not evident | Q38: Critique of justice institutions; non-partisan | R38: Not evident | S38: Not evident | T38: Critique | U38: Not evident | V38: Not evident | W38: Not evident | X38: Paradox | Y38: Paradox|Antithesis (court / tavern) | Z38: Negative | AA38: Timeless | AB38: Formal justice as a site of lies; informal space as a site of truth. | AC38: झुट अदालतमा ... सत्य भट्टीमा | AD38: High | AE38: — | AF38: N | AG38: — | AH38: INSTITUTION_CRITIQUE|HUMOR|DISTRUST_HYPOCRISY
A39: 38 | B39: जिन्दगीभर साथ दिन्छु भन्यौ, हैन? कस्तो एक्लो बनाएर गयौ, माया! | C39: Jindagībhar sātha dinchu bhanyau, haina? Kasto eklo banāera gayau, māyā! | D39: You said you would stay with me for a lifetime, didn’t you? Yet you left me so completely alone, my love! | E39: Love; betrayal; separation; loneliness; emotional loss. | F39: — | G39: Personal expression|Lament | H39: Interpersonal / Romance | J39: Betrayal|Loneliness | K39: High | L39: Former lover | M39: Romantic (abandoned) | N39: Eros (lost) | P39: Not evident | Q39: Not evident | R39: Not evident | S39: Not evident | T39: N/A | U39: Not evident | V39: Not evident | W39: Not evident | X39: None | Y39: Rhetorical question | Z39: Negative | AA39: Past | AB39: Broken lifetime promise. | AC39: कस्तो एक्लो बनाएर गयौ | AD39: High | AE39: — | AF39: N | AG39: — | AH39: LOVE_ROMANCE|SEPARATION_LOSS
A40: 39 | B40: कसैसँग झुट बोलेर सम्बन्ध गाँस्नु भन्दा साँचो बोलेर सम्बन्ध तोड्नु धेरै राम्रो हुन्छ। | C40: Kasaīsãga jhuṭa bolera sambandha gā̃snu bhanda sā̃co bolera sambandha toḍnu dherai rāmrō hunchha. | D40: It is much better to tell the truth and end a relationship than to build a relationship by lying to someone. | E40: Honesty; relationships; morality; trust; personal integrity. | F40: — | G40: Moral statement | H40: Moral / Advice | J40: Conviction | K40: Moderate | L40: Reader | M40: Romantic (generic) | N40: N/A | P40: Not evident | Q40: Not evident | R40: Not evident | S40: Not evident | T40: N/A | U40: Not evident | V40: Not evident | W40: Not evident | X40: None | Y40: Comparison | Z40: Neutral | AA40: Timeless | AB40: Honesty above relationship preservation. | AC40: साँचो बोलेर सम्बन्ध तोड्नु धेरै राम्रो | AD40: High | AE40: — | AF40: N | AG40: — | AH40: MORAL_ADVICE|LOVE_ROMANCE
A41: 40 | B41: उडाउने र गुडाउनेको भर हुँदैन; दुर्घटना गर्ने कसैको रहर हुँदैन। “पर्खी बस, फर्की आउँछु” भन्ने ड्राइभरको बानी हो, तर आफ्नो जीवनको भर हुँदैन। | C41: Uḍāune ra guḍāune ko bhar hudaina; durghaṭanā garne kasai ko rahar hudaina. “Parkhī basa, farkī āũchu” bhanne ḍrāibarko bānī ho, tara āphno jīvan ko bhar hudaina. | D41: There is no certainty in travelling by air or road; no one wishes to have an accident. “Wait for me, I will come back” is what a driver usually says, but there is no certainty about one’s life. | E41: Road safety; occupational risk; mortality; uncertainty; family separation; transport culture. | F41: — | G41: Aphorism|Personal expression | H41: Occupational risk | I41: Mortality | J41: Anxiety|Resignation | K41: Moderate | L41: Family / passengers | M41: Driver–family | N41: N/A | P41: Not evident | Q41: Not evident | R41: Not evident | S41: Not evident | T41: N/A | U41: Driver | V41: Not evident | W41: Fate / chance | X41: None | Y41: Reported speech|Rhyme (भर/रहर) | Z41: Negative | AA41: Future | AB41: The driver's routine promise to return is never guaranteed. | AC41: आफ्नो जीवनको भर हुँदैन | AD41: High | AE41: — | AF41: N | AG41: — | AH41: DRIVER_IDENTITY|MORTALITY_RISK|LABOR_DIGNITY
A42: 41 | B42: अनजानबाट चिनजान हुँदै फेरि अनजान हुने सम्बन्ध नै माया हो। | C42: Anjān-bāṭa cinjān hundai pheri anjān hune sambandha nai māyā ho. | D42: Love is a relationship that begins with strangers becoming acquainted and eventually turns them into strangers again. | E42: Love; relationships; impermanence; emotional change; separation. | F42: — | G42: Aphorism | H42: Interpersonal / Romance | J42: Melancholy | K42: Moderate | L42: Love (abstract) | M42: Not evident | N42: Eros (impermanent) | P42: Not evident | Q42: Not evident | R42: Not evident | S42: Not evident | T42: N/A | U42: Not evident | V42: Not evident | W42: Not evident | X42: None | Y42: Cyclical structure | Z42: Negative | AA42: Cyclical | AB42: Love defined by its ending. | AC42: फेरि अनजान हुने सम्बन्ध नै माया हो | AD42: High | AE42: — | AF42: N | AG42: — | AH42: LOVE_ROMANCE|SEPARATION_LOSS
A43: 42 | B43: सुन्नु न, आमा! जिन्दगी सम्झिँदा रमाउन मन लाग्छ; भविष्य सम्झँदा कमाउन मन लाग्छ। राम्रो गर्नेलाई घात गर्दिनँ, नराम्रो गर्नेलाई हात पनि जोड्दिनँ। आफ्नो ठाउँमा बस्छु; म कसैको औकात देखेर शिर झुकाउनेमा पर्दिनँ। | C43: Sunnu na, āmā! Jindagī samjhĩdā ramāuna mana lāgcha; bhaviṣya samjhĩdā kamāuna mana lāgcha. Rāmrō garne-lāī ghāta gardinã, narāmrō garne-lāī hāta pani joḍdinã. Āphno ṭhāumā baschu; ma kasaiko aukāta dekhera śir jhukāunemā pardinã. | D43: Listen, Mother! When I think about life, I want to enjoy it; when I think about the future, I want to earn. I do not betray those who do good, nor do I bow before those who do wrong. I remain in my own place; I do not bow my head based on someone’s social status. | E43: Self-respect; integrity; ambition; future aspirations; social status; independence; morality. | F43: — | G43: Personal expression|Moral statement | H43: Self-regard | I43: Family|Economic | J43: Pride|Determination | K43: Moderate | L43: Mother|Status-holders | M43: Parent–child | N43: Storge | O43: औकात (status)|शिर झुकाउनु | P43: Explicit: future earning | Q43: Not evident | R43: Not evident | S43: Not evident | T43: Resistance | U43: Independent self | V43: Earning, enjoying life | W43: Individual — agentic | X43: None | Y43: Parallelism | Z43: Positive | AA43: Future | AB43: Refusal to bow to others' status. | AC43: कसैको औकात देखेर शिर झुकाउनेमा पर्दिनँ | AD43: High | AE43: — | AF43: N | AG43: — | AH43: SELF_RESPECT|FAMILY|MONEY_MATERIALISM|CLASS_INEQUALITY_CRITIQUE|MORAL_ADVICE
A44: 43 | B44: भोलि त सबको मिठो नै हुन्छ; समय आएपछि व्यवहारले असली रूप देखाउँछ। | C44: Bholi ta sabko miṭho nai hunchha; samaya āepachi byavahārle asalī rūpa dekhāũcha. | D44: Tomorrow may seem sweet for everyone; when the time comes, people’s behaviour reveals their true nature. | E44: Human character; patience; changing behaviour; trust; social relationships. | F44: Everyone's words are sweet; when the time comes, behaviour shows their real face. | G44: Aphorism | H44: Moral / Human character | J44: Wariness | K44: Moderate | L44: People | M44: Not evident | N44: N/A | P44: Not evident | Q44: Not evident | R44: Not evident | S44: Not evident | T44: N/A | U44: Not evident | V44: Not evident | W44: Not evident | X44: None | Y44: Contrast (words vs. behaviour) | Z44: Mixed | AA44: Timeless | AB44: Distrust of speech; trust in conduct. | AC44: व्यवहारले असली रूप देखाउँछ | AD44: Medium | AE44: — | AF44: Y | AG44: भोलि (tomorrow) is likely a mis-transcription of बोली (speech) — the common saying is 'बोली त सबको मिठो'. Check the source photo. | AH44: DISTRUST_HYPOCRISY|MORAL_ADVICE
A45: 44 | B45: ब्याट्री हो, ५३ वाटको; कच्चा नसम्झ। साहुजी हो, रिदम सञ्जाल; बच्चा नसम्झ। | C45: Byāṭrī ho, 53 wāṭko; kaccā nasamjha. Sāhujī ho, ridam sañjāl; baccā nasamjha. | D45: It is a 53-watt battery, so do not underestimate it. It is the owner of the rhythm network, so do not mistake it for a child. | E45: Self-confidence; status; technology; youth identity; vehicle culture; assertiveness. | F45: — | G45: Self-assertion|Vehicle boast | H45: Vehicle culture | J45: Swagger | K45: Moderate | L45: Other road users | M45: Not evident | N45: N/A | P45: Not evident | Q45: Not evident | R45: Not evident | S45: Not evident | T45: N/A | U45: Owner/vehicle|Youth | V45: Not evident | W45: Not evident | X45: Boast | Y45: Rhyme (कच्चा/बच्चा) | Z45: Positive | AA45: Present | AB45: Vehicle and owner as a status unit. | AC45: कच्चा नसम्झ ... बच्चा नसम्झ | AD45: Low | AE45: — | AF45: Y | AG45: 'रिदम सञ्जाल' likely a business name; '५३ वाट' meaning unclear. | AH45: DRIVER_IDENTITY|SELF_RESPECT|HUMOR
A46: 45 | B46: अप्ठ्यारो छ भन्दैमा जीवन सकिएको नसोच्नुस्; यहाँ सुन्दर बिहानी आउन पनि ती अँध्यारा रात कटाउनुपर्छ। | C46: Apṭhyāro cha bhandaimā jīvan sakieko nasocnus; yahā̃ sundar bihānī āuna pani tī andhyārā rāta kaṭāunupardcha. | D46: Do not think that life is over simply because things are difficult; even a beautiful morning requires us to pass through the dark night. | E46: Hope; resilience; hardship; perseverance; optimism; life philosophy. | F46: — | G46: Aphorism|Encouragement | H46: Philosophical / Hope | J46: Hope | K46: Moderate | L46: Reader | M46: Not evident | N46: N/A | P46: Not evident | Q46: Not evident | R46: Not evident | S46: Not evident | T46: N/A | U46: Not evident | V46: Not evident | W46: Individual — resilient | X46: None | Y46: Metaphor (night / morning) | Z46: Positive | AA46: Future | AB46: Hardship as passage. | AC46: ती अँध्यारा रात कटाउनुपर्छ | AD46: High | AE46: — | AF46: N | AG46: — | AH46: HOPE_RESILIENCE
A47: 46 | B47: शरीरले आराम खोजिरहेछ, परिवारले पैसा, दिमागले शान्ति। | C47: Śarīrle ārām khojirhecha, parivārle paisā, dimāgle śānti. | D47: The body seeks rest, the family seeks money, and the mind seeks peace. | E47: Work–life balance; economic pressure; family responsibility; mental peace; modern life. | F47: — | G47: Aphorism | H47: Economic / Wellbeing | I47: Family | J47: Exhaustion | K47: Moderate | L47: Self | M47: Family | N47: N/A | P47: Explicit: family needs money | Q47: Not evident | R47: Not evident | S47: Not evident | T47: N/A | U47: Not evident | V47: Not evident | W47: Not evident | X47: None | Y47: Tricolon | Z47: Negative | AA47: Present | AB47: Three competing claims on one person. | AC47: शरीरले आराम ... परिवारले पैसा, दिमागले शान्ति | AD47: High | AE47: — | AF47: N | AG47: — | AH47: FAMILY|MONEY_MATERIALISM|LABOR_DIGNITY
A48: 47 | B48: ढिला हुन्छ, तर सबै राम्रो हुन्छ। समय खराब हो, जिन्दगी हैन, साथी। | C48: Ḍhilā hunchha, tara sabai rāmrō hunchha. Samaya kharāb ho, jindagī haina, sāthī. | D48: It may take time, but everything will be fine. It is the time that is bad, not life itself, my friend. | E48: Hope; patience; resilience; hardship; optimism. | F48: — | G48: Aphorism|Encouragement | H48: Philosophical / Hope | J48: Hope|Patience | K48: Moderate | L48: Friend / reader | M48: Friendship (address form) | N48: N/A | P48: Not evident | Q48: Not evident | R48: Not evident | S48: Not evident | T48: N/A | U48: Not evident | V48: Not evident | W48: Individual — resilient | X48: None | Y48: Antithesis (time vs. life) | Z48: Positive | AA48: Future | AB48: Duplicate of #9. | AC48: समय खराब हो, जिन्दगी हैन | AD48: High | AE48: — | AF48: Y | AG48: Duplicate of #9. | AH48: HOPE_RESILIENCE
A49: 48 | B49: हेर्ने नजर र सोच्ने मन सफा हुनुपर्छ; दुनियाँले खराब छस् भन्दैमा केही फरक पर्दैन। | C49: Herne najar ra socne mana sapha hunupardcha; duniyā̃le kharāb chhas bhandaimā kehi pharak pardaina. | D49: Your way of seeing and your mind should be pure; it does not matter simply because the world says you are bad. | E49: Self-perception; social judgment; inner character; confidence; morality. | F49: — | G49: Moral statement | H49: Moral / Self | J49: Self-assurance | K49: Moderate | L49: Self|Society | M49: Not evident | N49: N/A | P49: Not evident | Q49: Not evident | R49: Not evident | S49: Not evident | T49: N/A | U49: Not evident | V49: Not evident | W49: Not evident | X49: None | Y49: Contrast (inner / outer judgement) | Z49: Positive | AA49: Timeless | AB49: Inner purity over external judgement. | AC49: दुनियाँले खराब छस् भन्दैमा केही फरक पर्दैन | AD49: High | AE49: — | AF49: N | AG49: — | AH49: MORAL_ADVICE|SELF_RESPECT
A50: 49 | B50: गाडी चलाउने भनेर नहेप; गोरु चढ्ने शिवजीले बाघ चढ्ने पार्वतीलाई पठाएको इतिहासमा छ। | C50: Gāḍī calāune bhanera nahepa; goru chaḍne Śivajīle bāgha chaḍne Pārvatīlāī paṭhāeko itihāsmā cha. | D50: Do not look down on someone because they drive a vehicle; history tells that Shiva, who rides a bull, sent Parvati, who rides a tiger. | E50: Dignity of occupation; social status; religious-cultural references; respect; class. | F50: Don't look down on someone because he drives; history shows bull-riding Shiva won over tiger-riding Parvati. | G50: Mythological analogy|Humor | H50: Occupational dignity | I50: Religious-cultural | J50: Pride|Playful | K50: Moderate | L50: Those who look down on drivers | M50: Not evident | N50: N/A | P50: Not evident | Q50: Not evident | R50: Hindu mythology (Shiva, Parvati) | S50: Not evident | T50: Resistance (to stigma) | U50: Driver | V50: Not evident | W50: Not evident | X50: Divine precedent | Y50: Mythological analogy|Rhyme | Z50: Positive | AA50: Timeless | AB50: The lowly mount does not decide the worth (or romantic chances) of the rider. | AC50: गोरु चढ्ने शिवजी ... बाघ चढ्ने पार्वती | AD50: Medium | AE50: — | AF50: Y | AG50: पठाएको ('sent') is probably a hypercorrection of slang पटाएको ('won over / wooed'); 'sent' makes the analogy meaningless. | AH50: LABOR_DIGNITY|DRIVER_IDENTITY|RELIGION_FATE|HUMOR|LOVE_ROMANCE
A51: 50 | B51: कसैको अगाडि झुकेर माग्नु छ भने आशीर्वाद माग्नु, माया होइन। | C51: Kasaiko agāḍi jhukera māgnu cha bhane āśīrbād māgnu, māyā hoina. | D51: If you must bow before someone and ask for something, ask for blessings, not love. | E51: Dignity; love; self-respect; relationships; cultural values; emotional independence. | F51: — | G51: Aphorism | H51: Self-regard | I51: Romance | J51: Dignity | K51: Moderate | L51: Reader | M51: Not evident | N51: N/A | O51: आशीर्वाद (blessing) | P51: Not evident | Q51: Not evident | R51: Not evident | S51: Not evident | T51: N/A | U51: Not evident | V51: Not evident | W51: Not evident | X51: None | Y51: Contrast (blessing / love) | Z51: Neutral | AA51: Timeless | AB51: Begging is acceptable only for blessings. | AC51: आशीर्वाद माग्नु, माया होइन | AD51: High | AE51: — | AF51: N | AG51: — | AH51: SELF_RESPECT|LOVE_ROMANCE|MORAL_ADVICE
A52: 51 | B52: पैसाको मुठै–मुठाले तँलाई हान्न मन छ; सुनको सिक्री नै सिक्रीले तँलाई बाँध्न मन छ। साथीहरूमा हल्का–फुल्का मजाक त भइहाल्छ; करोडौँको भीडमा तेरो कट्टु तान्न मन छ। | C52: Paisāko muṭhai-muṭhaile tãlāī hānna mana cha; sunko sikrī nai sikrīle tãlāī bā̃dhna mana cha. Sāthīharūmā halkā-phulkā majāk ta bhaīhālcha; karoḍaũko bhīḍmā tero kaṭṭu tānna mana cha. | D52: I feel like hitting you with bundles of money and binding you with chains of gold. Among friends, a little playful teasing is natural; in a crowd of millions, I feel like pulling your shorts. | E52: Friendship; humour; wealth; teasing; masculinity; popular youth culture. | F52: — | G52: Humor|Teasing | H52: Friendship | J52: Affectionate mockery | K52: Low | L52: Friend | M52: Friendship | N52: Philia | P52: Not evident | Q52: Not evident | R52: Not evident | S52: Homosocial teasing (inferred) | T52: N/A | U52: Not evident | V52: Not evident | W52: Not evident | X52: Hyperbole and pranking | Y52: Hyperbole|Intimate pronoun तँ | Z52: Positive | AA52: Present | AB52: Friendship expressed through mock aggression. | AC52: साथीहरूमा हल्का–फुल्का मजाक | AD52: High | AE52: — | AF52: N | AG52: — | AH52: HUMOR|MONEY_MATERIALISM|MASCULINITY
A53: 52 | B53: gem | C53: Āmāko phāṭeko colā mātra nahera, bubāko phuṭeko kurkucchā pani herne gara. Duḥkha pardā āmāko ta jāne māitī hunchha; tara bubāko pīḍā kahā̃ gaera sunāune? | D53: Do not look only at the mother’s torn clothes; also notice the father’s cracked heels. When hardship comes, a mother has her maternal home to turn to, but where can a father go to share his pain? | E53: Parents; fatherhood; motherhood; hidden suffering; family responsibility; gender roles; emotional burden. | F53: — | G53: Moral statement | H53: Family | I53: Gender | J53: Compassion|Pathos | K53: Moderate | L53: Father|Mother | M53: Parent–child | N53: Storge | O53: माइती (natal home) | P53: Not evident | Q53: Not evident | R53: Not evident | S53: Mother has माइती; father has nowhere to share pain | T53: N/A | U53: Fatherhood | V53: Not evident | W53: Not evident | X53: None | Y53: Synecdoche (torn blouse / cracked heels) | Z53: Mixed | AA53: Timeless | AB53: Makes paternal suffering visible. | AC53: बुबाको पीडा कहाँ गएर सुनाउने? | AD53: Medium | AE53: — | AF53: Y | AG53: Nepali text missing (cell reads 'gem'); reconstruct from transliteration and source photo. | AH53: FAMILY|MASCULINITY
A54: 53 | B54: अलपत्र छ जिन्दगी, गन्तव्य लामो छ। कतिबेला के हुन्छ, साथ दिनुहोस् है भगवान्। | C54: Alapatra cha jindagī, gantabya lāmo cha. Katibelā ke hunchha, sātha dinuhos hai Bhagavān. | D54: Life is uncertain and the destination is far away. Lord, please stay with me; who knows what may happen at any moment. | E54: Uncertainty of life; faith; spirituality; journey; hope; dependence on God | F54: — | G54: Prayer | H54: Religious / Uncertainty | J54: Anxiety|Faith | K54: Moderate | L54: God | M54: Divine–devotee | N54: N/A | P54: Not evident | Q54: Not evident | R54: Generic theistic (भगवान्) | S54: Not evident | T54: N/A | U54: Not evident | V54: Not evident | W54: Divine | X54: None | Y54: Journey metaphor | Z54: Mixed | AA54: Future | AB54: The road as life; divine accompaniment against uncertainty. | AC54: साथ दिनुहोस् है भगवान् | AD54: High | AE54: — | AF54: N | AG54: — | AH54: RELIGION_FATE|MORTALITY_RISK|HOPE_RESILIENCE
A55: 54 | B55: पढाइ बिग्रियो भनेर चिन्ता नगर, केटा हो। पढ्नेलाई हतार छ, नपढ्नेलाई साउदी–कतार छ। | C55: Paḍhāi bigriyo bhanera cintā nagara, keṭā ho. Paḍhnelāī hatār cha, napaḍhnelāī Saudī–Qatār cha. | D55: Do not worry just because your studies have not gone well, boys. Those who study are in a hurry to move ahead, while those who do not study have Saudi or Qatar as their destination. | E55: Education; youth; migration; foreign employment; social aspirations; economic pressure | F55: — | G55: Humor|Social commentary | H55: Education / Migration | J55: Resigned humour | K55: Low | L55: Boys (केटा हो) | M55: Not evident | N55: N/A | P55: Explicit: Gulf labour | Q55: Not evident | R55: Not evident | S55: Addressed to boys | T55: N/A | U55: Youth|Migrant | V55: Education vs. migration | W55: Not evident | X55: Deadpan reassurance | Y55: Rhyme (हतार/कतार) | Z55: Mixed | AA55: Future | AB55: Gulf migration as the fallback for failed schooling. | AC55: नपढ्नेलाई साउदी–कतार छ | AD55: High | AE55: — | AF55: N | AG55: — | AH55: EDUCATION|MIGRATION|HUMOR
A56: 55 | B56: चुपचाप घन्टीछाप, सिलिन्डर हाफ, सुकुम्बासी टाप। | C56: Cupacāp ghaṇṭīchhāp, silinḍara hāpha, sukumbāsī ṭāpa. | D56: Quietly: bell symbol, half-cylinder, squatters’ stamp. | E56: Political symbolism; public satire; political slogans; social commentary; colloquial humour | F56: Quietly voted for the Bell — gas cylinder half, squatters gone. | G56: Political slogan parody | H56: Political | I56: Economic|Housing | J56: Sarcasm|Disillusionment | K56: Moderate | L56: Rastriya Swatantra Party / government | M56: Not evident | N56: N/A | P56: Not evident | Q56: Explicit party reference: 'चुपचाप घण्टी छाप' was RSP's 2026 campaign slogan; squatter evictions | R56: Not evident | S56: Not evident | T56: Critique | U56: Not evident | V56: Not evident | W56: Not evident | X56: Slogan parody | Y56: Parody|Rhyme (छाप/हाफ/टाप) | Z56: Negative | AA56: Past/Present | AB56: Contrasts campaign promises with post-election outcomes (likely the 2026 squatter evictions). | AC56: चुपचाप घन्टीछाप ... सुकुम्बासी टाप | AD56: Medium | AE56: Could be read as supportive (a list of achievements) rather than satirical. | AF56: Y | AG56: 'टाप' = gone/vanished, not 'stamp'; 'सिलिन्डर हाफ' unclear. Dates the inscription to 2026. | AH56: INSTITUTION_CRITIQUE|HUMOR|CLASS_INEQUALITY_CRITIQUE
A57: 56 | B57: कता हो नेताजी? संविधान त बन्यो क्यारे। गाउँमा फर्कने होइन? जनता त लाठी लिएर स्वागत गर्न बसेका छन्। | C57: Katā ho netājī? Saṁvidhāna ta banyo kyāre. Gāũmā farkane hoina? Janatā ta lāṭhī lie-ra svāgata garna basekā chan. | D57: Where are you, leader? The Constitution has apparently been made. Aren’t you coming back to the village? The people are waiting to welcome you with sticks. | E57: Political frustration; leadership; Constitution; rural–political relations; public dissatisfaction; satire | F57: — | G57: Political satire | H57: Political | I57: Rural–urban | J57: Anger|Sarcasm | K57: High | L57: Political leaders | M57: Not evident | N57: N/A | P57: Not evident | Q57: Explicit: leaders, Constitution | R57: Not evident | S57: Not evident | T57: Resistance | U57: Not evident | V57: Not evident | W57: Not evident | X57: Ironic 'welcome' | Y57: Irony|Rhetorical questions | Z57: Negative | AA57: Present | AB57: The rural electorate's anger at absent leaders. | AC57: लाठी लिएर स्वागत गर्न बसेका छन् | AD57: High | AE57: — | AF57: N | AG57: — | AH57: INSTITUTION_CRITIQUE|HUMOR|PLACE_IDENTITY
A58: 57 | B58: देश त पुरानै ठीक थियो। | C58: Deśa ta purānai ṭhīk thiyo. | D58: The country was better the way it was before. | E58: Political nostalgia; social change; dissatisfaction; national identity; public sentiment | F58: — | G58: Slogan | H58: Political | J58: Nostalgia|Disillusionment | K58: Low | L58: Nation | M58: Not evident | N58: N/A | P58: Not evident | Q58: Explicit: dissatisfaction with change; referent of 'old' unspecified | R58: Not evident | S58: Not evident | T58: Critique (ambiguous) | U58: Not evident | V58: Not evident | W58: Not evident | X58: None | Y58: Ellipsis | Z58: Negative | AA58: Past | AB58: Political nostalgia without a stated object. | AC58: देश त पुरानै ठीक थियो | AD58: Low | AE58: Could signal pro-monarchy sentiment or general disillusionment; text does not say which. | AF58: Y | AG58: Do not code as royalist without evidence. | AH58: INSTITUTION_CRITIQUE
A59: 58 | B59: आमा, एकचोटि धेरै पैसा कमाउने मन छ। सुनेको छु, पैसा हुनेहरू सबैको प्यारो हुन्छन् रे। | C59: Āmā, ekacoṭi dherai paisā kamāune mana cha. Suneko chu, paisā huneharū sabaiko pyāro hunchan re. | D59: Mother, I want to earn a lot of money at least once. I have heard that people who have money are loved by everyone. | E59: Money and affection; materialism; family; economic aspiration; social status | F59: — | G59: Personal expression | H59: Economic aspiration | I59: Family | J59: Longing|Irony | K59: Moderate | L59: Mother | M59: Parent–child | N59: Storge | P59: Explicit: earning a lot | Q59: Not evident | R59: Not evident | S59: Not evident | T59: N/A | U59: Not evident | V59: Wealth as route to being loved | W59: Not evident | X59: None | Y59: Hearsay marker रे (irony) | Z59: Mixed | AA59: Future | AB59: Wealth desired for affection, not for itself. | AC59: पैसा हुनेहरू सबैको प्यारो हुन्छन् रे | AD59: High | AE59: — | AF59: N | AG59: — | AH59: MONEY_MATERIALISM|FAMILY
A60: 59 | B60: आशा अनि विश्वास दुवै राखेको छु। भगवान्, अब पल्टिन लागेको पानामा सफल भविष्य लेखिएको होस्। | C60: Āśā ani viśvās dubai rākheko chu. Bhagavān, aba palṭina lāgeko pānāmā saphala bhaviṣya lekhi'eko hos. | D60: I have both hope and faith. May the page I am about to turn contain a successful future, Lord. | E60: Hope; faith; future; aspiration; spirituality; resilience | F60: — | G60: Prayer|Encouragement | H60: Religious / Hope | J60: Hope|Faith | K60: Moderate | L60: God | M60: Divine–devotee | N60: N/A | P60: Not evident | Q60: Not evident | R60: Generic theistic (भगवान्) | S60: Not evident | T60: N/A | U60: Not evident | V60: Successful future | W60: Divine | X60: None | Y60: Metaphor (turning page) | Z60: Positive | AA60: Future | AB60: Hope and faith paired. | AC60: आशा अनि विश्वास दुवै | AD60: High | AE60: — | AF60: N | AG60: — | AH60: RELIGION_FATE|HOPE_RESILIENCE
A61: 60 | B61: मान्छे–मान्छे नै मान्छेको दबाइ हो। कसैले खुसी दिन्छन् भने कसैले पीडा, साथी। | C61: Mānche-mānche nai māncheko dabāi ho. Kasaile khusī dinchan bhane kasaile pīḍā, sāthī. | D61: People themselves are both the medicine and the pain of other people. Some bring happiness, while others bring suffering, my friend. | E61: Human relationships; happiness and suffering; friendship; emotional life; social interaction | F61: — | G61: Aphorism | H61: Interpersonal | J61: Reflective | K61: Moderate | L61: People | M61: Friendship (address form) | N61: Philia | P61: Not evident | Q61: Not evident | R61: Not evident | S61: Not evident | T61: N/A | U61: Not evident | V61: Not evident | W61: Not evident | X61: None | Y61: Metaphor (medicine)|Antithesis | Z61: Mixed | AA61: Timeless | AB61: Other people as both cure and wound. | AC61: मान्छे नै मान्छेको दबाइ हो | AD61: High | AE61: — | AF61: N | AG61: — | AH61: MORAL_ADVICE
A62: 61 | B62: केको घमण्ड? सेतो कात्रोका गोजी हुँदैनन्, मसानघाटमा रोजी हुँदैन। किन तछाडमछाड गर्छौ? मृत्यु पश्चात् खोजी हुँदैन। जीवन अजम्बरी हुँदैन, एकनास सधैँभरि हुँदैन। केको घमण्ड गर्छौ? यो झुटो संसार सधैँभरि हुँदैन। | C62: Keko ghamanḍa? Seto kātro-kā gojī hudainan, masānaghāṭmā rojī hudaina. Kina tachāḍmachāḍ garchau? Mṛtyu paścāt khojī hudaina. Jīvan ajambarī hudaina, ekanāsa sadhaĩbhari hudaina. Keko ghamanḍa garchau? Yo jhuṭo saṁsār sadhaĩbhari hudaina. | D62: What is there to be proud of? A white funeral shroud has no pockets, and there is no livelihood in the cremation ground. Why do you struggle so desperately for more? After death, no one searches for what you possessed. Life is not immortal, and nothing remains the same forever. Why be proud? This temporary world does not last forever. | E62: Mortality; humility; materialism; impermanence; wealth; death; human pride; philosophical reflection | F62: — | G62: Philosophical reflection | H62: Existential / Mortality | I62: Economic | J62: Humility|Melancholy | K62: Moderate | L62: The proud / everyone | M62: Not evident | N62: N/A | O62: कात्रो (shroud)|मसानघाट (cremation ground) | P62: Explicit: futility of accumulation | Q62: Not evident | R62: Not evident | S62: Not evident | T62: N/A | U62: Not evident | V62: Not evident | W62: Not evident | X62: None | Y62: Rhetorical questions|Rhyme (हुँदैन)|Imagery | Z62: Mixed | AA62: Timeless | AB62: Death erases wealth; pride is unjustified. | AC62: सेतो कात्रोका गोजी हुँदैनन् | AD62: High | AE62: — | AF62: N | AG62: — | AH62: MORTALITY_RISK|MONEY_MATERIALISM|MORAL_ADVICE

Sheet Code_Matrix
A1: ID | B1: LOVE_ROMANCE | C1: SEPARATION_LOSS | D1: FAMILY | E1: MONEY_MATERIALISM | F1: CLASS_INEQUALITY_CRITIQUE | G1: CONSUMER_STATUS | H1: MIGRATION | I1: EDUCATION | J1: DRIVER_IDENTITY | K1: LABOR_DIGNITY | L1: FARE_LIVELIHOOD | M1: MASCULINITY | N1: WOMEN_REPRESENTATION | O1: SELF_RESPECT | P1: DISTRUST_HYPOCRISY | Q1: MORAL_ADVICE | R1: HOPE_RESILIENCE | S1: RELIGION_FATE | T1: MORTALITY_RISK | U1: INSTITUTION_CRITIQUE | V1: PLACE_IDENTITY | W1: HUMOR | X1: CODE_MIXING_SLANG
A2: =Master_Dataset!A2 -> 1 | B2: =IF(ISNUMBER(SEARCH("|LOVE_ROMANCE|","|"&Master_Dataset!$AH2&"|")),1,0) -> 0 | C2: =IF(ISNUMBER(SEARCH("|SEPARATION_LOSS|","|"&Master_Dataset!$AH2&"|")),1,0) -> 0 | D2: =IF(ISNUMBER(SEARCH("|FAMILY|","|"&Master_Dataset!$AH2&"|")),1,0) -> 0 | E2: =IF(ISNUMBER(SEARCH("|MONEY_MATERIALISM|","|"&Master_Dataset!$AH2&"|")),1,0) -> 1 | F2: =IF(ISNUMBER(SEARCH("|CLASS_INEQUALITY_CRITIQUE|","|"&Master_Dataset!$AH2&"|")),1,0) -> 0 | G2: =IF(ISNUMBER(SEARCH("|CONSUMER_STATUS|","|"&Master_Dataset!$AH2&"|")),1,0) -> 0 | H2: =IF(ISNUMBER(SEARCH("|MIGRATION|","|"&Master_Dataset!$AH2&"|")),1,0) -> 0 | I2: =IF(ISNUMBER(SEARCH("|EDUCATION|","|"&Master_Dataset!$AH2&"|")),1,0) -> 0 | J2: =IF(ISNUMBER(SEARCH("|DRIVER_IDENTITY|","|"&Master_Dataset!$AH2&"|")),1,0) -> 0 | K2: =IF(ISNUMBER(SEARCH("|LABOR_DIGNITY|","|"&Master_Dataset!$AH2&"|")),1,0) -> 1 | L2: =IF(ISNUMBER(SEARCH("|FARE_LIVELIHOOD|","|"&Master_Dataset!$AH2&"|")),1,0) -> 1 | M2: =IF(ISNUMBER(SEARCH("|MASCULINITY|","|"&Master_Dataset!$AH2&"|")),1,0) -> 0 | N2: =IF(ISNUMBER(SEARCH("|WOMEN_REPRESENTATION|","|"&Master_Dataset!$AH2&"|")),1,0) -> 0 | O2: =IF(ISNUMBER(SEARCH("|SELF_RESPECT|","|"&Master_Dataset!$AH2&"|")),1,0) -> 0 | P2: =IF(ISNUMBER(SEARCH("|DISTRUST_HYPOCRISY|","|"&Master_Dataset!$AH2&"|")),1,0) -> 0 | Q2: =IF(ISNUMBER(SEARCH("|MORAL_ADVICE|","|"&Master_Dataset!$AH2&"|")),1,0) -> 0 | R2: =IF(ISNUMBER(SEARCH("|HOPE_RESILIENCE|","|"&Master_Dataset!$AH2&"|")),1,0) -> 0 | S2: =IF(ISNUMBER(SEARCH("|RELIGION_FATE|","|"&Master_Dataset!$AH2&"|")),1,0) -> 0 | T2: =IF(ISNUMBER(SEARCH("|MORTALITY_RISK|","|"&Master_Dataset!$AH2&"|")),1,0) -> 0 | U2: =IF(ISNUMBER(SEARCH("|INSTITUTION_CRITIQUE|","|"&Master_Dataset!$AH2&"|")),1,0) -> 0 | V2: =IF(ISNUMBER(SEARCH("|PLACE_IDENTITY|","|"&Master_Dataset!$AH2&"|")),1,0) -> 0 | W2: =IF(ISNUMBER(SEARCH("|HUMOR|","|"&Master_Dataset!$AH2&"|")),1,0) -> 0 | X2: =IF(ISNUMBER(SEARCH("|CODE_MIXING_SLANG|","|"&Master_Dataset!$AH2&"|")),1,0) -> 0
A3: =Master_Dataset!A3 -> 2 | B3: =IF(ISNUMBER(SEARCH("|LOVE_ROMANCE|","|"&Master_Dataset!$AH3&"|")),1,0) -> 0 | C3: =IF(ISNUMBER(SEARCH("|SEPARATION_LOSS|","|"&Master_Dataset!$AH3&"|")),1,0) -> 0 | D3: =IF(ISNUMBER(SEARCH("|FAMILY|","|"&Master_Dataset!$AH3&"|")),1,0) -> 1 | E3: =IF(ISNUMBER(SEARCH("|MONEY_MATERIALISM|","|"&Master_Dataset!$AH3&"|")),1,0) -> 1 | F3: =IF(ISNUMBER(SEARCH("|CLASS_INEQUALITY_CRITIQUE|","|"&Master_Dataset!$AH3&"|")),1,0) -> 0 | G3: =IF(ISNUMBER(SEARCH("|CONSUMER_STATUS|","|"&Master_Dataset!$AH3&"|")),1,0) -> 0 | H3: =IF(ISNUMBER(SEARCH("|MIGRATION|","|"&Master_Dataset!$AH3&"|")),1,0) -> 0 | I3: =IF(ISNUMBER(SEARCH("|EDUCATION|","|"&Master_Dataset!$AH3&"|")),1,0) -> 0 | J3: =IF(ISNUMBER(SEARCH("|DRIVER_IDENTITY|","|"&Master_Dataset!$AH3&"|")),1,0) -> 0 | K3: =IF(ISNUMBER(SEARCH("|LABOR_DIGNITY|","|"&Master_Dataset!$AH3&"|")),1,0) -> 0 | L3: =IF(ISNUMBER(SEARCH("|FARE_LIVELIHOOD|","|"&Master_Dataset!$AH3&"|")),1,0) -> 0 | M3: =IF(ISNUMBER(SEARCH("|MASCULINITY|","|"&Master_Dataset!$AH3&"|")),1,0) -> 1 | N3: =IF(ISNUMBER(SEARCH("|WOMEN_REPRESENTATION|","|"&Master_Dataset!$AH3&"|")),1,0) -> 1 | O3: =IF(ISNUMBER(SEARCH("|SELF_RESPECT|","|"&Master_Dataset!$AH3&"|")),1,0) -> 0 | P3: =IF(ISNUMBER(SEARCH("|DISTRUST_HYPOCRISY|","|"&Master_Dataset!$AH3&"|")),1,0) -> 0 | Q3: =IF(ISNUMBER(SEARCH("|MORAL_ADVICE|","|"&Master_Dataset!$AH3&"|")),1,0) -> 0 | R3: =IF(ISNUMBER(SEARCH("|HOPE_RESILIENCE|","|"&Master_Dataset!$AH3&"|")),1,0) -> 0 | S3: =IF(ISNUMBER(SEARCH("|RELIGION_FATE|","|"&Master_Dataset!$AH3&"|")),1,0) -> 0 | T3: =IF(ISNUMBER(SEARCH("|MORTALITY_RISK|","|"&Master_Dataset!$AH3&"|")),1,0) -> 0 | U3: =IF(ISNUMBER(SEARCH("|INSTITUTION_CRITIQUE|","|"&Master_Dataset!$AH3&"|")),1,0) -> 0 | V3: =IF(ISNUMBER(SEARCH("|PLACE_IDENTITY|","|"&Master_Dataset!$AH3&"|")),1,0) -> 0 | W3: =IF(ISNUMBER(SEARCH("|HUMOR|","|"&Master_Dataset!$AH3&"|")),1,0) -> 0 | X3: =IF(ISNUMBER(SEARCH("|CODE_MIXING_SLANG|","|"&Master_Dataset!$AH3&"|")),1,0) -> 0
A4: =Master_Dataset!A4 -> 3 | B4: =IF(ISNUMBER(SEARCH("|LOVE_ROMANCE|","|"&Master_Dataset!$AH4&"|")),1,0) -> 0 | C4: =IF(ISNUMBER(SEARCH("|SEPARATION_LOSS|","|"&Master_Dataset!$AH4&"|")),1,0) -> 0 | D4: =IF(ISNUMBER(SEARCH("|FAMILY|","|"&Master_Dataset!$AH4&"|")),1,0) -> 0 | E4: =IF(ISNUMBER(SEARCH("|MONEY_MATERIALISM|","|"&Master_Dataset!$AH4&"|")),1,0) -> 1 | F4: =IF(ISNUMBER(SEARCH("|CLASS_INEQUALITY_CRITIQUE|","|"&Master_Dataset!$AH4&"|")),1,0) -> 1 | G4: =IF(ISNUMBER(SEARCH("|CONSUMER_STATUS|","|"&Master_Dataset!$AH4&"|")),1,0) -> 0 | H4: =IF(ISNUMBER(SEARCH("|MIGRATION|","|"&Master_Dataset!$AH4&"|")),1,0) -> 0 | I4: =IF(ISNUMBER(SEARCH("|EDUCATION|","|"&Master_Dataset!$AH4&"|")),1,0) -> 0 | J4: =IF(ISNUMBER(SEARCH("|DRIVER_IDENTITY|","|"&Master_Dataset!$AH4&"|")),1,0) -> 0 | K4: =IF(ISNUMBER(SEARCH("|LABOR_DIGNITY|","|"&Master_Dataset!$AH4&"|")),1,0) -> 0 | L4: =IF(ISNUMBER(SEARCH("|FARE_LIVELIHOOD|","|"&Master_Dataset!$AH4&"|")),1,0) -> 0 | M4: =IF(ISNUMBER(SEARCH("|MASCULINITY|","|"&Master_Dataset!$AH4&"|")),1,0) -> 0 | N4: =IF(ISNUMBER(SEARCH("|WOMEN_REPRESENTATION|","|"&Master_Dataset!$AH4&"|")),1,0) -> 0 | O4: =IF(ISNUMBER(SEARCH("|SELF_RESPECT|","|"&Master_Dataset!$AH4&"|")),1,0) -> 0 | P4: =IF(ISNUMBER(SEARCH("|DISTRUST_HYPOCRISY|","|"&Master_Dataset!$AH4&"|")),1,0) -> 1 | Q4: =IF(ISNUMBER(SEARCH("|MORAL_ADVICE|","|"&Master_Dataset!$AH4&"|")),1,0) -> 0 | R4: =IF(ISNUMBER(SEARCH("|HOPE_RESILIENCE|","|"&Master_Dataset!$AH4&"|")),1,0) -> 0 | S4: =IF(ISNUMBER(SEARCH("|RELIGION_FATE|","|"&Master_Dataset!$AH4&"|")),1,0) -> 0 | T4: =IF(ISNUMBER(SEARCH("|MORTALITY_RISK|","|"&Master_Dataset!$AH4&"|")),1,0) -> 0 | U4: =IF(ISNUMBER(SEARCH("|INSTITUTION_CRITIQUE|","|"&Master_Dataset!$AH4&"|")),1,0) -> 0 | V4: =IF(ISNUMBER(SEARCH("|PLACE_IDENTITY|","|"&Master_Dataset!$AH4&"|")),1,0) -> 0 | W4: =IF(ISNUMBER(SEARCH("|HUMOR|","|"&Master_Dataset!$AH4&"|")),1,0) -> 0 | X4: =IF(ISNUMBER(SEARCH("|CODE_MIXING_SLANG|","|"&Master_Dataset!$AH4&"|")),1,0) -> 0
A5: =Master_Dataset!A5 -> 4 | B5: =IF(ISNUMBER(SEARCH("|LOVE_ROMANCE|","|"&Master_Dataset!$AH5&"|")),1,0) -> 0 | C5: =IF(ISNUMBER(SEARCH("|SEPARATION_LOSS|","|"&Master_Dataset!$AH5&"|")),1,0) -> 0 | D5: =IF(ISNUMBER(SEARCH("|FAMILY|","|"&Master_Dataset!$AH5&"|")),1,0) -> 0 | E5: =IF(ISNUMBER(SEARCH("|MONEY_MATERIALISM|","|"&Master_Dataset!$AH5&"|")),1,0) -> 0 | F5: =IF(ISNUMBER(SEARCH("|CLASS_INEQUALITY_CRITIQUE|","|"&Master_Dataset!$AH5&"|")),1,0) -> 0 | G5: =IF(ISNUMBER(SEARCH("|CONSUMER_STATUS|","|"&Master_Dataset!$AH5&"|")),1,0) -> 0 | H5: =IF(ISNUMBER(SEARCH("|MIGRATION|","|"&Master_Dataset!$AH5&"|")),1,0) -> 0 | I5: =IF(ISNUMBER(SEARCH("|EDUCATION|","|"&Master_Dataset!$AH5&"|")),1,0) -> 0 | J5: =IF(ISNUMBER(SEARCH("|DRIVER_IDENTITY|","|"&Master_Dataset!$AH5&"|")),1,0) -> 0 | K5: =IF(ISNUMBER(SEARCH("|LABOR_DIGNITY|","|"&Master_Dataset!$AH5&"|")),1,0) -> 0 | L5: =IF(ISNUMBER(SEARCH("|FARE_LIVELIHOOD|","|"&Master_Dataset!$AH5&"|")),1,0) -> 0 | M5: =IF(ISNUMBER(SEARCH("|MASCULINITY|","|"&Master_Dataset!$AH5&"|")),1,0) -> 0 | N5: =IF(ISNUMBER(SEARCH("|WOMEN_REPRESENTATION|","|"&Master_Dataset!$AH5&"|")),1,0) -> 0 | O5: =IF(ISNUMBER(SEARCH("|SELF_RESPECT|","|"&Master_Dataset!$AH5&"|")),1,0) -> 0 | P5: =IF(ISNUMBER(SEARCH("|DISTRUST_HYPOCRISY|","|"&Master_Dataset!$AH5&"|")),1,0) -> 0 | Q5: =IF(ISNUMBER(SEARCH("|MORAL_ADVICE|","|"&Master_Dataset!$AH5&"|")),1,0) -> 0 | R5: =IF(ISNUMBER(SEARCH("|HOPE_RESILIENCE|","|"&Master_Dataset!$AH5&"|")),1,0) -> 0 | S5: =IF(ISNUMBER(SEARCH("|RELIGION_FATE|","|"&Master_Dataset!$AH5&"|")),1,0) -> 0 | T5: =IF(ISNUMBER(SEARCH("|MORTALITY_RISK|","|"&Master_Dataset!$AH5&"|")),1,0) -> 1 | U5: =IF(ISNUMBER(SEARCH("|INSTITUTION_CRITIQUE|","|"&Master_Dataset!$AH5&"|")),1,0) -> 0 | V5: =IF(ISNUMBER(SEARCH("|PLACE_IDENTITY|","|"&Master_Dataset!$AH5&"|")),1,0) -> 0 | W5: =IF(ISNUMBER(SEARCH("|HUMOR|","|"&Master_Dataset!$AH5&"|")),1,0) -> 0 | X5: =IF(ISNUMBER(SEARCH("|CODE_MIXING_SLANG|","|"&Master_Dataset!$AH5&"|")),1,0) -> 0
A6: =Master_Dataset!A6 -> 5 | B6: =IF(ISNUMBER(SEARCH("|LOVE_ROMANCE|","|"&Master_Dataset!$AH6&"|")),1,0) -> 0 | C6: =IF(ISNUMBER(SEARCH("|SEPARATION_LOSS|","|"&Master_Dataset!$AH6&"|")),1,0) -> 0 | D6: =IF(ISNUMBER(SEARCH("|FAMILY|","|"&Master_Dataset!$AH6&"|")),1,0) -> 0 | E6: =IF(ISNUMBER(SEARCH("|MONEY_MATERIALISM|","|"&Master_Dataset!$AH6&"|")),1,0) -> 0 | F6: =IF(ISNUMBER(SEARCH("|CLASS_INEQUALITY_CRITIQUE|","|"&Master_Dataset!$AH6&"|")),1,0) -> 0 | G6: =IF(ISNUMBER(SEARCH("|CONSUMER_STATUS|","|"&Master_Dataset!$AH6&"|")),1,0) -> 0 | H6: =IF(ISNUMBER(SEARCH("|MIGRATION|","|"&Master_Dataset!$AH6&"|")),1,0) -> 0 | I6: =IF(ISNUMBER(SEARCH("|EDUCATION|","|"&Master_Dataset!$AH6&"|")),1,0) -> 0 | J6: =IF(ISNUMBER(SEARCH("|DRIVER_IDENTITY|","|"&Master_Dataset!$AH6&"|")),1,0) -> 0 | K6: =IF(ISNUMBER(SEARCH("|LABOR_DIGNITY|","|"&Master_Dataset!$AH6&"|")),1,0) -> 0 | L6: =IF(ISNUMBER(SEARCH("|FARE_LIVELIHOOD|","|"&Master_Dataset!$AH6&"|")),1,0) -> 0 | M6: =IF(ISNUMBER(SEARCH("|MASCULINITY|","|"&Master_Dataset!$AH6&"|")),1,0) -> 0 | N6: =IF(ISNUMBER(SEARCH("|WOMEN_REPRESENTATION|","|"&Master_Dataset!$AH6&"|")),1,0) -> 0 | O6: =IF(ISNUMBER(SEARCH("|SELF_RESPECT|","|"&Master_Dataset!$AH6&"|")),1,0) -> 0 | P6: =IF(ISNUMBER(SEARCH("|DISTRUST_HYPOCRISY|","|"&Master_Dataset!$AH6&"|")),1,0) -> 0 | Q6: =IF(ISNUMBER(SEARCH("|MORAL_ADVICE|","|"&Master_Dataset!$AH6&"|")),1,0) -> 0 | R6: =IF(ISNUMBER(SEARCH("|HOPE_RESILIENCE|","|"&Master_Dataset!$AH6&"|")),1,0) -> 0 | S6: =IF(ISNUMBER(SEARCH("|RELIGION_FATE|","|"&Master_Dataset!$AH6&"|")),1,0) -> 0 | T6: =IF(ISNUMBER(SEARCH("|MORTALITY_RISK|","|"&Master_Dataset!$AH6&"|")),1,0) -> 0 | U6: =IF(ISNUMBER(SEARCH("|INSTITUTION_CRITIQUE|","|"&Master_Dataset!$AH6&"|")),1,0) -> 0 | V6: =IF(ISNUMBER(SEARCH("|PLACE_IDENTITY|","|"&Master_Dataset!$AH6&"|")),1,0) -> 0 | W6: =IF(ISNUMBER(SEARCH("|HUMOR|","|"&Master_Dataset!$AH6&"|")),1,0) -> 1 | X6: =IF(ISNUMBER(SEARCH("|CODE_MIXING_SLANG|","|"&Master_Dataset!$AH6&"|")),1,0) -> 1
A7: =Master_Dataset!A7 -> 6 | B7: =IF(ISNUMBER(SEARCH("|LOVE_ROMANCE|","|"&Master_Dataset!$AH7&"|")),1,0) -> 0 | C7: =IF(ISNUMBER(SEARCH("|SEPARATION_LOSS|","|"&Master_Dataset!$AH7&"|")),1,0) -> 0 | D7: =IF(ISNUMBER(SEARCH("|FAMILY|","|"&Master_Dataset!$AH7&"|")),1,0) -> 0 | E7: =IF(ISNUMBER(SEARCH("|MONEY_MATERIALISM|","|"&Master_Dataset!$AH7&"|")),1,0) -> 0 | F7: =IF(ISNUMBER(SEARCH("|CLASS_INEQUALITY_CRITIQUE|","|"&Master_Dataset!$AH7&"|")),1,0) -> 0 | G7: =IF(ISNUMBER(SEARCH("|CONSUMER_STATUS|","|"&Master_Dataset!$AH7&"|")),1,0) -> 0 | H7: =IF(ISNUMBER(SEARCH("|MIGRATION|","|"&Master_Dataset!$AH7&"|")),1,0) -> 0 | I7: =IF(ISNUMBER(SEARCH("|EDUCATION|","|"&Master_Dataset!$AH7&"|")),1,0) -> 0 | J7: =IF(ISNUMBER(SEARCH("|DRIVER_IDENTITY|","|"&Master_Dataset!$AH7&"|")),1,0) -> 0 | K7: =IF(ISNUMBER(SEARCH("|LABOR_DIGNITY|","|"&Master_Dataset!$AH7&"|")),1,0) -> 0 | L7: =IF(ISNUMBER(SEARCH("|FARE_LIVELIHOOD|","|"&Master_Dataset!$AH7&"|")),1,0) -> 0 | M7: =IF(ISNUMBER(SEARCH("|MASCULINITY|","|"&Master_Dataset!$AH7&"|")),1,0) -> 0 | N7: =IF(ISNUMBER(SEARCH("|WOMEN_REPRESENTATION|","|"&Master_Dataset!$AH7&"|")),1,0) -> 0 | O7: =IF(ISNUMBER(SEARCH("|SELF_RESPECT|","|"&Master_Dataset!$AH7&"|")),1,0) -> 0 | P7: =IF(ISNUMBER(SEARCH("|DISTRUST_HYPOCRISY|","|"&Master_Dataset!$AH7&"|")),1,0) -> 1 | Q7: =IF(ISNUMBER(SEARCH("|MORAL_ADVICE|","|"&Master_Dataset!$AH7&"|")),1,0) -> 0 | R7: =IF(ISNUMBER(SEARCH("|HOPE_RESILIENCE|","|"&Master_Dataset!$AH7&"|")),1,0) -> 1 | S7: =IF(ISNUMBER(SEARCH("|RELIGION_FATE|","|"&Master_Dataset!$AH7&"|")),1,0) -> 0 | T7: =IF(ISNUMBER(SEARCH("|MORTALITY_RISK|","|"&Master_Dataset!$AH7&"|")),1,0) -> 0 | U7: =IF(ISNUMBER(SEARCH("|INSTITUTION_CRITIQUE|","|"&Master_Dataset!$AH7&"|")),1,0) -> 0 | V7: =IF(ISNUMBER(SEARCH("|PLACE_IDENTITY|","|"&Master_Dataset!$AH7&"|")),1,0) -> 0 | W7: =IF(ISNUMBER(SEARCH("|HUMOR|","|"&Master_Dataset!$AH7&"|")),1,0) -> 1 | X7: =IF(ISNUMBER(SEARCH("|CODE_MIXING_SLANG|","|"&Master_Dataset!$AH7&"|")),1,0) -> 0
A8: =Master_Dataset!A8 -> 7 | B8: =IF(ISNUMBER(SEARCH("|LOVE_ROMANCE|","|"&Master_Dataset!$AH8&"|")),1,0) -> 1 | C8: =IF(ISNUMBER(SEARCH("|SEPARATION_LOSS|","|"&Master_Dataset!$AH8&"|")),1,0) -> 0 | D8: =IF(ISNUMBER(SEARCH("|FAMILY|","|"&Master_Dataset!$AH8&"|")),1,0) -> 0 | E8: =IF(ISNUMBER(SEARCH("|MONEY_MATERIALISM|","|"&Master_Dataset!$AH8&"|")),1,0) -> 0 | F8: =IF(ISNUMBER(SEARCH("|CLASS_INEQUALITY_CRITIQUE|","|"&Master_Dataset!$AH8&"|")),1,0) -> 0 | G8: =IF(ISNUMBER(SEARCH("|CONSUMER_STATUS|","|"&Master_Dataset!$AH8&"|")),1,0) -> 0 | H8: =IF(ISNUMBER(SEARCH("|MIGRATION|","|"&Master_Dataset!$AH8&"|")),1,0) -> 0 | I8: =IF(ISNUMBER(SEARCH("|EDUCATION|","|"&Master_Dataset!$AH8&"|")),1,0) -> 0 | J8: =IF(ISNUMBER(SEARCH("|DRIVER_IDENTITY|","|"&Master_Dataset!$AH8&"|")),1,0) -> 1 | K8: =IF(ISNUMBER(SEARCH("|LABOR_DIGNITY|","|"&Master_Dataset!$AH8&"|")),1,0) -> 0 | L8: =IF(ISNUMBER(SEARCH("|FARE_LIVELIHOOD|","|"&Master_Dataset!$AH8&"|")),1,0) -> 0 | M8: =IF(ISNUMBER(SEARCH("|MASCULINITY|","|"&Master_Dataset!$AH8&"|")),1,0) -> 1 | N8: =IF(ISNUMBER(SEARCH("|WOMEN_REPRESENTATION|","|"&Master_Dataset!$AH8&"|")),1,0) -> 0 | O8: =IF(ISNUMBER(SEARCH("|SELF_RESPECT|","|"&Master_Dataset!$AH8&"|")),1,0) -> 0 | P8: =IF(ISNUMBER(SEARCH("|DISTRUST_HYPOCRISY|","|"&Master_Dataset!$AH8&"|")),1,0) -> 0 | Q8: =IF(ISNUMBER(SEARCH("|MORAL_ADVICE|","|"&Master_Dataset!$AH8&"|")),1,0) -> 0 | R8: =IF(ISNUMBER(SEARCH("|HOPE_RESILIENCE|","|"&Master_Dataset!$AH8&"|")),1,0) -> 0 | S8: =IF(ISNUMBER(SEARCH("|RELIGION_FATE|","|"&Master_Dataset!$AH8&"|")),1,0) -> 0 | T8: =IF(ISNUMBER(SEARCH("|MORTALITY_RISK|","|"&Master_Dataset!$AH8&"|")),1,0) -> 0 | U8: =IF(ISNUMBER(SEARCH("|INSTITUTION_CRITIQUE|","|"&Master_Dataset!$AH8&"|")),1,0) -> 0 | V8: =IF(ISNUMBER(SEARCH("|PLACE_IDENTITY|","|"&Master_Dataset!$AH8&"|")),1,0) -> 0 | W8: =IF(ISNUMBER(SEARCH("|HUMOR|","|"&Master_Dataset!$AH8&"|")),1,0) -> 1 | X8: =IF(ISNUMBER(SEARCH("|CODE_MIXING_SLANG|","|"&Master_Dataset!$AH8&"|")),1,0) -> 0
A9: =Master_Dataset!A9 -> 8 | B9: =IF(ISNUMBER(SEARCH("|LOVE_ROMANCE|","|"&Master_Dataset!$AH9&"|")),1,0) -> 0 | C9: =IF(ISNUMBER(SEARCH("|SEPARATION_LOSS|","|"&Master_Dataset!$AH9&"|")),1,0) -> 0 | D9: =IF(ISNUMBER(SEARCH("|FAMILY|","|"&Master_Dataset!$AH9&"|")),1,0) -> 0 | E9: =IF(ISNUMBER(SEARCH("|MONEY_MATERIALISM|","|"&Master_Dataset!$AH9&"|")),1,0) -> 0 | F9: =IF(ISNUMBER(SEARCH("|CLASS_INEQUALITY_CRITIQUE|","|"&Master_Dataset!$AH9&"|")),1,0) -> 0 | G9: =IF(ISNUMBER(SEARCH("|CONSUMER_STATUS|","|"&Master_Dataset!$AH9&"|")),1,0) -> 0 | H9: =IF(ISNUMBER(SEARCH("|MIGRATION|","|"&Master_Dataset!$AH9&"|")),1,0) -> 0 | I9: =IF(ISNUMBER(SEARCH("|EDUCATION|","|"&Master_Dataset!$AH9&"|")),1,0) -> 0 | J9: =IF(ISNUMBER(SEARCH("|DRIVER_IDENTITY|","|"&Master_Dataset!$AH9&"|")),1,0) -> 0 | K9: =IF(ISNUMBER(SEARCH("|LABOR_DIGNITY|","|"&Master_Dataset!$AH9&"|")),1,0) -> 0 | L9: =IF(ISNUMBER(SEARCH("|FARE_LIVELIHOOD|","|"&Master_Dataset!$AH9&"|")),1,0) -> 0 | M9: =IF(ISNUMBER(SEARCH("|MASCULINITY|","|"&Master_Dataset!$AH9&"|")),1,0) -> 0 | N9: =IF(ISNUMBER(SEARCH("|WOMEN_REPRESENTATION|","|"&Master_Dataset!$AH9&"|")),1,0) -> 0 | O9: =IF(ISNUMBER(SEARCH("|SELF_RESPECT|","|"&Master_Dataset!$AH9&"|")),1,0) -> 0 | P9: =IF(ISNUMBER(SEARCH("|DISTRUST_HYPOCRISY|","|"&Master_Dataset!$AH9&"|")),1,0) -> 0 | Q9: =IF(ISNUMBER(SEARCH("|MORAL_ADVICE|","|"&Master_Dataset!$AH9&"|")),1,0) -> 1 | R9: =IF(ISNUMBER(SEARCH("|HOPE_RESILIENCE|","|"&Master_Dataset!$AH9&"|")),1,0) -> 0 | S9: =IF(ISNUMBER(SEARCH("|RELIGION_FATE|","|"&Master_Dataset!$AH9&"|")),1,0) -> 1 | T9: =IF(ISNUMBER(SEARCH("|MORTALITY_RISK|","|"&Master_Dataset!$AH9&"|")),1,0) -> 0 | U9: =IF(ISNUMBER(SEARCH("|INSTITUTION_CRITIQUE|","|"&Master_Dataset!$AH9&"|")),1,0) -> 0 | V9: =IF(ISNUMBER(SEARCH("|PLACE_IDENTITY|","|"&Master_Dataset!$AH9&"|")),1,0) -> 0 | W9: =IF(ISNUMBER(SEARCH("|HUMOR|","|"&Master_Dataset!$AH9&"|")),1,0) -> 0 | X9: =IF(ISNUMBER(SEARCH("|CODE_MIXING_SLANG|","|"&Master_Dataset!$AH9&"|")),1,0) -> 0
A10: =Master_Dataset!A10 -> 9 | B10: =IF(ISNUMBER(SEARCH("|LOVE_ROMANCE|","|"&Master_Dataset!$AH10&"|")),1,0) -> 0 | C10: =IF(ISNUMBER(SEARCH("|SEPARATION_LOSS|","|"&Master_Dataset!$AH10&"|")),1,0) -> 0 | D10: =IF(ISNUMBER(SEARCH("|FAMILY|","|"&Master_Dataset!$AH10&"|")),1,0) -> 0 | E10: =IF(ISNUMBER(SEARCH("|MONEY_MATERIALISM|","|"&Master_Dataset!$AH10&"|")),1,0) -> 0 | F10: =IF(ISNUMBER(SEARCH("|CLASS_INEQUALITY_CRITIQUE|","|"&Master_Dataset!$AH10&"|")),1,0) -> 0 | G10: =IF(ISNUMBER(SEARCH("|CONSUMER_STATUS|","|"&Master_Dataset!$AH10&"|")),1,0) -> 0 | H10: =IF(ISNUMBER(SEARCH("|MIGRATION|","|"&Master_Dataset!$AH10&"|")),1,0) -> 0 | I10: =IF(ISNUMBER(SEARCH("|EDUCATION|","|"&Master_Dataset!$AH10&"|")),1,0) -> 0 | J10: =IF(ISNUMBER(SEARCH("|DRIVER_IDENTITY|","|"&Master_Dataset!$AH10&"|")),1,0) -> 0 | K10: =IF(ISNUMBER(SEARCH("|LABOR_DIGNITY|","|"&Master_Dataset!$AH10&"|")),1,0) -> 0 | L10: =IF(ISNUMBER(SEARCH("|FARE_LIVELIHOOD|","|"&Master_Dataset!$AH10&"|")),1,0) -> 0 | M10: =IF(ISNUMBER(SEARCH("|MASCULINITY|","|"&Master_Dataset!$AH10&"|")),1,0) -> 0 | N10: =IF(ISNUMBER(SEARCH("|WOMEN_REPRESENTATION|","|"&Master_Dataset!$AH10&"|")),1,0) -> 0 | O10: =IF(ISNUMBER(SEARCH("|SELF_RESPECT|","|"&Master_Dataset!$AH10&"|")),1,0) -> 0 | P10: =IF(ISNUMBER(SEARCH("|DISTRUST_HYPOCRISY|","|"&Master_Dataset!$AH10&"|")),1,0) -> 0 | Q10: =IF(ISNUMBER(SEARCH("|MORAL_ADVICE|","|"&Master_Dataset!$AH10&"|")),1,0) -> 0 | R10: =IF(ISNUMBER(SEARCH("|HOPE_RESILIENCE|","|"&Master_Dataset!$AH10&"|")),1,0) -> 1 | S10: =IF(ISNUMBER(SEARCH("|RELIGION_FATE|","|"&Master_Dataset!$AH10&"|")),1,0) -> 0 | T10: =IF(ISNUMBER(SEARCH("|MORTALITY_RISK|","|"&Master_Dataset!$AH10&"|")),1,0) -> 0 | U10: =IF(ISNUMBER(SEARCH("|INSTITUTION_CRITIQUE|","|"&Master_Dataset!$AH10&"|")),1,0) -> 0 | V10: =IF(ISNUMBER(SEARCH("|PLACE_IDENTITY|","|"&Master_Dataset!$AH10&"|")),1,0) -> 0 | W10: =IF(ISNUMBER(SEARCH("|HUMOR|","|"&Master_Dataset!$AH10&"|")),1,0) -> 0 | X10: =IF(ISNUMBER(SEARCH("|CODE_MIXING_SLANG|","|"&Master_Dataset!$AH10&"|")),1,0) -> 0
A11: =Master_Dataset!A11 -> 10 | B11: =IF(ISNUMBER(SEARCH("|LOVE_ROMANCE|","|"&Master_Dataset!$AH11&"|")),1,0) -> 1 | C11: =IF(ISNUMBER(SEARCH("|SEPARATION_LOSS|","|"&Master_Dataset!$AH11&"|")),1,0) -> 1 | D11: =IF(ISNUMBER(SEARCH("|FAMILY|","|"&Master_Dataset!$AH11&"|")),1,0) -> 0 | E11: =IF(ISNUMBER(SEARCH("|MONEY_MATERIALISM|","|"&Master_Dataset!$AH11&"|")),1,0) -> 0 | F11: =IF(ISNUMBER(SEARCH("|CLASS_INEQUALITY_CRITIQUE|","|"&Master_Dataset!$AH11&"|")),1,0) -> 0 | G11: =IF(ISNUMBER(SEARCH("|CONSUMER_STATUS|","|"&Master_Dataset!$AH11&"|")),1,0) -> 0 | H11: =IF(ISNUMBER(SEARCH("|MIGRATION|","|"&Master_Dataset!$AH11&"|")),1,0) -> 1 | I11: =IF(ISNUMBER(SEARCH("|EDUCATION|","|"&Master_Dataset!$AH11&"|")),1,0) -> 0 | J11: =IF(ISNUMBER(SEARCH("|DRIVER_IDENTITY|","|"&Master_Dataset!$AH11&"|")),1,0) -> 0 | K11: =IF(ISNUMBER(SEARCH("|LABOR_DIGNITY|","|"&Master_Dataset!$AH11&"|")),1,0) -> 0 | L11: =IF(ISNUMBER(SEARCH("|FARE_LIVELIHOOD|","|"&Master_Dataset!$AH11&"|")),1,0) -> 0 | M11: =IF(ISNUMBER(SEARCH("|MASCULINITY|","|"&Master_Dataset!$AH11&"|")),1,0) -> 0 | N11: =IF(ISNUMBER(SEARCH("|WOMEN_REPRESENTATION|","|"&Master_Dataset!$AH11&"|")),1,0) -> 0 | O11: =IF(ISNUMBER(SEARCH("|SELF_RESPECT|","|"&Master_Dataset!$AH11&"|")),1,0) -> 0 | P11: =IF(ISNUMBER(SEARCH("|DISTRUST_HYPOCRISY|","|"&Master_Dataset!$AH11&"|")),1,0) -> 0 | Q11: =IF(ISNUMBER(SEARCH("|MORAL_ADVICE|","|"&Master_Dataset!$AH11&"|")),1,0) -> 0 | R11: =IF(ISNUMBER(SEARCH("|HOPE_RESILIENCE|","|"&Master_Dataset!$AH11&"|")),1,0) -> 0 | S11: =IF(ISNUMBER(SEARCH("|RELIGION_FATE|","|"&Master_Dataset!$AH11&"|")),1,0) -> 0 | T11: =IF(ISNUMBER(SEARCH("|MORTALITY_RISK|","|"&Master_Dataset!$AH11&"|")),1,0) -> 0 | U11: =IF(ISNUMBER(SEARCH("|INSTITUTION_CRITIQUE|","|"&Master_Dataset!$AH11&"|")),1,0) -> 0 | V11: =IF(ISNUMBER(SEARCH("|PLACE_IDENTITY|","|"&Master_Dataset!$AH11&"|")),1,0) -> 0 | W11: =IF(ISNUMBER(SEARCH("|HUMOR|","|"&Master_Dataset!$AH11&"|")),1,0) -> 0 | X11: =IF(ISNUMBER(SEARCH("|CODE_MIXING_SLANG|","|"&Master_Dataset!$AH11&"|")),1,0) -> 0
A12: =Master_Dataset!A12 -> 11 | B12: =IF(ISNUMBER(SEARCH("|LOVE_ROMANCE|","|"&Master_Dataset!$AH12&"|")),1,0) -> 1 | C12: =IF(ISNUMBER(SEARCH("|SEPARATION_LOSS|","|"&Master_Dataset!$AH12&"|")),1,0) -> 1 | D12: =IF(ISNUMBER(SEARCH("|FAMILY|","|"&Master_Dataset!$AH12&"|")),1,0) -> 0 | E12: =IF(ISNUMBER(SEARCH("|MONEY_MATERIALISM|","|"&Master_Dataset!$AH12&"|")),1,0) -> 1 | F12: =IF(ISNUMBER(SEARCH("|CLASS_INEQUALITY_CRITIQUE|","|"&Master_Dataset!$AH12&"|")),1,0) -> 0 | G12: =IF(ISNUMBER(SEARCH("|CONSUMER_STATUS|","|"&Master_Dataset!$AH12&"|")),1,0) -> 1 | H12: =IF(ISNUMBER(SEARCH("|MIGRATION|","|"&Master_Dataset!$AH12&"|")),1,0) -> 0 | I12: =IF(ISNUMBER(SEARCH("|EDUCATION|","|"&Master_Dataset!$AH12&"|")),1,0) -> 0 | J12: =IF(ISNUMBER(SEARCH("|DRIVER_IDENTITY|","|"&Master_Dataset!$AH12&"|")),1,0) -> 0 | K12: =IF(ISNUMBER(SEARCH("|LABOR_DIGNITY|","|"&Master_Dataset!$AH12&"|")),1,0) -> 0 | L12: =IF(ISNUMBER(SEARCH("|FARE_LIVELIHOOD|","|"&Master_Dataset!$AH12&"|")),1,0) -> 0 | M12: =IF(ISNUMBER(SEARCH("|MASCULINITY|","|"&Master_Dataset!$AH12&"|")),1,0) -> 0 | N12: =IF(ISNUMBER(SEARCH("|WOMEN_REPRESENTATION|","|"&Master_Dataset!$AH12&"|")),1,0) -> 0 | O12: =IF(ISNUMBER(SEARCH("|SELF_RESPECT|","|"&Master_Dataset!$AH12&"|")),1,0) -> 0 | P12: =IF(ISNUMBER(SEARCH("|DISTRUST_HYPOCRISY|","|"&Master_Dataset!$AH12&"|")),1,0) -> 0 | Q12: =IF(ISNUMBER(SEARCH("|MORAL_ADVICE|","|"&Master_Dataset!$AH12&"|")),1,0) -> 0 | R12: =IF(ISNUMBER(SEARCH("|HOPE_RESILIENCE|","|"&Master_Dataset!$AH12&"|")),1,0) -> 0 | S12: =IF(ISNUMBER(SEARCH("|RELIGION_FATE|","|"&Master_Dataset!$AH12&"|")),1,0) -> 0 | T12: =IF(ISNUMBER(SEARCH("|MORTALITY_RISK|","|"&Master_Dataset!$AH12&"|")),1,0) -> 0 | U12: =IF(ISNUMBER(SEARCH("|INSTITUTION_CRITIQUE|","|"&Master_Dataset!$AH12&"|")),1,0) -> 0 | V12: =IF(ISNUMBER(SEARCH("|PLACE_IDENTITY|","|"&Master_Dataset!$AH12&"|")),1,0) -> 0 | W12: =IF(ISNUMBER(SEARCH("|HUMOR|","|"&Master_Dataset!$AH12&"|")),1,0) -> 0 | X12: =IF(ISNUMBER(SEARCH("|CODE_MIXING_SLANG|","|"&Master_Dataset!$AH12&"|")),1,0) -> 0
A13: =Master_Dataset!A13 -> 12 | B13: =IF(ISNUMBER(SEARCH("|LOVE_ROMANCE|","|"&Master_Dataset!$AH13&"|")),1,0) -> 1 | C13: =IF(ISNUMBER(SEARCH("|SEPARATION_LOSS|","|"&Master_Dataset!$AH13&"|")),1,0) -> 1 | D13: =IF(ISNUMBER(SEARCH("|FAMILY|","|"&Master_Dataset!$AH13&"|")),1,0) -> 0 | E13: =IF(ISNUMBER(SEARCH("|MONEY_MATERIALISM|","|"&Master_Dataset!$AH13&"|")),1,0) -> 0 | F13: =IF(ISNUMBER(SEARCH("|CLASS_INEQUALITY_CRITIQUE|","|"&Master_Dataset!$AH13&"|")),1,0) -> 1 | G13: =IF(ISNUMBER(SEARCH("|CONSUMER_STATUS|","|"&Master_Dataset!$AH13&"|")),1,0) -> 1 | H13: =IF(ISNUMBER(SEARCH("|MIGRATION|","|"&Master_Dataset!$AH13&"|")),1,0) -> 0 | I13: =IF(ISNUMBER(SEARCH("|EDUCATION|","|"&Master_Dataset!$AH13&"|")),1,0) -> 0 | J13: =IF(ISNUMBER(SEARCH("|DRIVER_IDENTITY|","|"&Master_Dataset!$AH13&"|")),1,0) -> 0 | K13: =IF(ISNUMBER(SEARCH("|LABOR_DIGNITY|","|"&Master_Dataset!$AH13&"|")),1,0) -> 0 | L13: =IF(ISNUMBER(SEARCH("|FARE_LIVELIHOOD|","|"&Master_Dataset!$AH13&"|")),1,0) -> 0 | M13: =IF(ISNUMBER(SEARCH("|MASCULINITY|","|"&Master_Dataset!$AH13&"|")),1,0) -> 0 | N13: =IF(ISNUMBER(SEARCH("|WOMEN_REPRESENTATION|","|"&Master_Dataset!$AH13&"|")),1,0) -> 0 | O13: =IF(ISNUMBER(SEARCH("|SELF_RESPECT|","|"&Master_Dataset!$AH13&"|")),1,0) -> 0 | P13: =IF(ISNUMBER(SEARCH("|DISTRUST_HYPOCRISY|","|"&Master_Dataset!$AH13&"|")),1,0) -> 0 | Q13: =IF(ISNUMBER(SEARCH("|MORAL_ADVICE|","|"&Master_Dataset!$AH13&"|")),1,0) -> 0 | R13: =IF(ISNUMBER(SEARCH("|HOPE_RESILIENCE|","|"&Master_Dataset!$AH13&"|")),1,0) -> 0 | S13: =IF(ISNUMBER(SEARCH("|RELIGION_FATE|","|"&Master_Dataset!$AH13&"|")),1,0) -> 0 | T13: =IF(ISNUMBER(SEARCH("|MORTALITY_RISK|","|"&Master_Dataset!$AH13&"|")),1,0) -> 0 | U13: =IF(ISNUMBER(SEARCH("|INSTITUTION_CRITIQUE|","|"&Master_Dataset!$AH13&"|")),1,0) -> 0 | V13: =IF(ISNUMBER(SEARCH("|PLACE_IDENTITY|","|"&Master_Dataset!$AH13&"|")),1,0) -> 0 | W13: =IF(ISNUMBER(SEARCH("|HUMOR|","|"&Master_Dataset!$AH13&"|")),1,0) -> 0 | X13: =IF(ISNUMBER(SEARCH("|CODE_MIXING_SLANG|","|"&Master_Dataset!$AH13&"|")),1,0) -> 0
... A62: =Master_Dataset!A62 -> 61 | B62: =IF(ISNUMBER(SEARCH("|LOVE_ROMANCE|","|"&Master_Dataset!$AH62&"|")),1,0) -> 0 | C62: =IF(ISNUMBER(SEARCH("|SEPARATION_LOSS|","|"&Master_Dataset!$AH62&"|")),1,0) -> 0 | D62: =IF(ISNUMBER(SEARCH("|FAMILY|","|"&Master_Dataset!$AH62&"|")),1,0) -> 0 | E62: =IF(ISNUMBER(SEARCH("|MONEY_MATERIALISM|","|"&Master_Dataset!$AH62&"|")),1,0) -> 1 | F62: =IF(ISNUMBER(SEARCH("|CLASS_INEQUALITY_CRITIQUE|","|"&Master_Dataset!$AH62&"|")),1,0) -> 0 | G62: =IF(ISNUMBER(SEARCH("|CONSUMER_STATUS|","|"&Master_Dataset!$AH62&"|")),1,0) -> 0 | H62: =IF(ISNUMBER(SEARCH("|MIGRATION|","|"&Master_Dataset!$AH62&"|")),1,0) -> 0 | I62: =IF(ISNUMBER(SEARCH("|EDUCATION|","|"&Master_Dataset!$AH62&"|")),1,0) -> 0 | J62: =IF(ISNUMBER(SEARCH("|DRIVER_IDENTITY|","|"&Master_Dataset!$AH62&"|")),1,0) -> 0 | K62: =IF(ISNUMBER(SEARCH("|LABOR_DIGNITY|","|"&Master_Dataset!$AH62&"|")),1,0) -> 0 | L62: =IF(ISNUMBER(SEARCH("|FARE_LIVELIHOOD|","|"&Master_Dataset!$AH62&"|")),1,0) -> 0 | M62: =IF(ISNUMBER(SEARCH("|MASCULINITY|","|"&Master_Dataset!$AH62&"|")),1,0) -> 0 | N62: =IF(ISNUMBER(SEARCH("|WOMEN_REPRESENTATION|","|"&Master_Dataset!$AH62&"|")),1,0) -> 0 | O62: =IF(ISNUMBER(SEARCH("|SELF_RESPECT|","|"&Master_Dataset!$AH62&"|")),1,0) -> 0 | P62: =IF(ISNUMBER(SEARCH("|DISTRUST_HYPOCRISY|","|"&Master_Dataset!$AH62&"|")),1,0) -> 0 | Q62: =IF(ISNUMBER(SEARCH("|MORAL_ADVICE|","|"&Master_Dataset!$AH62&"|")),1,0) -> 1 | R62: =IF(ISNUMBER(SEARCH("|HOPE_RESILIENCE|","|"&Master_Dataset!$AH62&"|")),1,0) -> 0 | S62: =IF(ISNUMBER(SEARCH("|RELIGION_FATE|","|"&Master_Dataset!$AH62&"|")),1,0) -> 0 | T62: =IF(ISNUMBER(SEARCH("|MORTALITY_RISK|","|"&Master_Dataset!$AH62&"|")),1,0) -> 1 | U62: =IF(ISNUMBER(SEARCH("|INSTITUTION_CRITIQUE|","|"&Master_Dataset!$AH62&"|")),1,0) -> 0 | V62: =IF(ISNUMBER(SEARCH("|PLACE_IDENTITY|","|"&Master_Dataset!$AH62&"|")),1,0) -> 0 | W62: =IF(ISNUMBER(SEARCH("|HUMOR|","|"&Master_Dataset!$AH62&"|")),1,0) -> 0 | X62: =IF(ISNUMBER(SEARCH("|CODE_MIXING_SLANG|","|"&Master_Dataset!$AH62&"|")),1,0) -> 0

Sheet Frequencies
A1: Code | B1: Origin | C1: Inscriptions | D1: % of corpus
A2: LOVE_ROMANCE | B2: Deductive | C2: =SUM(Code_Matrix!B2:B62) -> 18 | D2: =C2/61 -> 0.29508197
A3: SEPARATION_LOSS | B3: Deductive | C3: =SUM(Code_Matrix!C2:C62) -> 8 | D3: =C3/61 -> 0.13114754
A4: FAMILY | B4: Deductive | C4: =SUM(Code_Matrix!D2:D62) -> 9 | D4: =C4/61 -> 0.14754098
A5: MONEY_MATERIALISM | B5: Deductive | C5: =SUM(Code_Matrix!E2:E62) -> 11 | D5: =C5/61 -> 0.18032787
A6: CLASS_INEQUALITY_CRITIQUE | B6: Deductive | C6: =SUM(Code_Matrix!F2:F62) -> 7 | D6: =C6/61 -> 0.1147541
A7: CONSUMER_STATUS | B7: Emergent | C7: =SUM(Code_Matrix!G2:G62) -> 2 | D7: =C7/61 -> 0.032786885
A8: MIGRATION | B8: Deductive | C8: =SUM(Code_Matrix!H2:H62) -> 4 | D8: =C8/61 -> 0.06557377
A9: EDUCATION | B9: Deductive | C9: =SUM(Code_Matrix!I2:I62) -> 1 | D9: =C9/61 -> 0.016393443
A10: DRIVER_IDENTITY | B10: Emergent | C10: =SUM(Code_Matrix!J2:J62) -> 8 | D10: =C10/61 -> 0.13114754
A11: LABOR_DIGNITY | B11: Emergent | C11: =SUM(Code_Matrix!K2:K62) -> 8 | D11: =C11/61 -> 0.13114754
A12: FARE_LIVELIHOOD | B12: Emergent | C12: =SUM(Code_Matrix!L2:L62) -> 4 | D12: =C12/61 -> 0.06557377
A13: MASCULINITY | B13: Deductive | C13: =SUM(Code_Matrix!M2:M62) -> 5 | D13: =C13/61 -> 0.081967213
A14: WOMEN_REPRESENTATION | B14: Deductive | C14: =SUM(Code_Matrix!N2:N62) -> 4 | D14: =C14/61 -> 0.06557377
A15: SELF_RESPECT | B15: Emergent | C15: =SUM(Code_Matrix!O2:O62) -> 10 | D15: =C15/61 -> 0.16393443
A16: DISTRUST_HYPOCRISY | B16: Emergent | C16: =SUM(Code_Matrix!P2:P62) -> 7 | D16: =C16/61 -> 0.1147541
A17: MORAL_ADVICE | B17: Deductive | C17: =SUM(Code_Matrix!Q2:Q62) -> 11 | D17: =C17/61 -> 0.18032787
A18: HOPE_RESILIENCE | B18: Deductive | C18: =SUM(Code_Matrix!R2:R62) -> 10 | D18: =C18/61 -> 0.16393443
A19: RELIGION_FATE | B19: Deductive | C19: =SUM(Code_Matrix!S2:S62) -> 4 | D19: =C19/61 -> 0.06557377
A20: MORTALITY_RISK | B20: Deductive | C20: =SUM(Code_Matrix!T2:T62) -> 5 | D20: =C20/61 -> 0.081967213
A21: INSTITUTION_CRITIQUE | B21: Deductive | C21: =SUM(Code_Matrix!U2:U62) -> 4 | D21: =C21/61 -> 0.06557377
A22: PLACE_IDENTITY | B22: Deductive | C22: =SUM(Code_Matrix!V2:V62) -> 4 | D22: =C22/61 -> 0.06557377
A23: HUMOR | B23: Deductive | C23: =SUM(Code_Matrix!W2:W62) -> 17 | D23: =C23/61 -> 0.27868852
A24: CODE_MIXING_SLANG | B24: Emergent | C24: =SUM(Code_Matrix!X2:X62) -> 4 | D24: =C24/61 -> 0.06557377
A27: Valence | B27: Count | C27: %
A28: Positive | B28: =COUNTIF(Master_Dataset!Z2:Z62,"Positive") -> 15 | C28: =B28/61 -> 0.24590164
A29: Negative | B29: =COUNTIF(Master_Dataset!Z2:Z62,"Negative") -> 19 | C29: =B29/61 -> 0.31147541
A30: Mixed | B30: =COUNTIF(Master_Dataset!Z2:Z62,"Mixed") -> 25 | C30: =B30/61 -> 0.40983607
A31: Neutral | B31: =COUNTIF(Master_Dataset!Z2:Z62,"Neutral") -> 2 | C31: =B31/61 -> 0.032786885
A34: Confidence | B34: Count | C34: %
A35: High | B35: =COUNTIF(Master_Dataset!AD2:AD62,"High") -> 45 | C35: =B35/61 -> 0.73770492
A36: Medium | B36: =COUNTIF(Master_Dataset!AD2:AD62,"Medium") -> 11 | C36: =B36/61 -> 0.18032787
A37: Low | B37: =COUNTIF(Master_Dataset!AD2:AD62,"Low") -> 5 | C37: =B37/61 -> 0.081967213
A40: Human review | B40: Count
A41: Flagged (Y) | B41: =COUNTIF(Master_Dataset!AF2:AF62,"Y") -> 27

Sheet Co_occurrence
A1: Number of inscriptions carrying both codes (diagonal = code total)
B2: LOVE_ROMANCE | C2: SEPARATION_LOSS | D2: FAMILY | E2: MONEY_MATERIALISM | F2: CLASS_INEQUALITY_CRITIQUE | G2: CONSUMER_STATUS | H2: MIGRATION | I2: EDUCATION | J2: DRIVER_IDENTITY | K2: LABOR_DIGNITY | L2: FARE_LIVELIHOOD | M2: MASCULINITY | N2: WOMEN_REPRESENTATION | O2: SELF_RESPECT | P2: DISTRUST_HYPOCRISY | Q2: MORAL_ADVICE | R2: HOPE_RESILIENCE | S2: RELIGION_FATE | T2: MORTALITY_RISK | U2: INSTITUTION_CRITIQUE | V2: PLACE_IDENTITY | W2: HUMOR | X2: CODE_MIXING_SLANG
A3: LOVE_ROMANCE | B3: =SUMPRODUCT(Code_Matrix!B$2:B$62,Code_Matrix!B$2:B$62) -> 18 | C3: =SUMPRODUCT(Code_Matrix!B$2:B$62,Code_Matrix!C$2:C$62) -> 8 | D3: =SUMPRODUCT(Code_Matrix!B$2:B$62,Code_Matrix!D$2:D$62) -> 0 | E3: =SUMPRODUCT(Code_Matrix!B$2:B$62,Code_Matrix!E$2:E$62) -> 1 | F3: =SUMPRODUCT(Code_Matrix!B$2:B$62,Code_Matrix!F$2:F$62) -> 1 | G3: =SUMPRODUCT(Code_Matrix!B$2:B$62,Code_Matrix!G$2:G$62) -> 2 | H3: =SUMPRODUCT(Code_Matrix!B$2:B$62,Code_Matrix!H$2:H$62) -> 1 | I3: =SUMPRODUCT(Code_Matrix!B$2:B$62,Code_Matrix!I$2:I$62) -> 0 | J3: =SUMPRODUCT(Code_Matrix!B$2:B$62,Code_Matrix!J$2:J$62) -> 3 | K3: =SUMPRODUCT(Code_Matrix!B$2:B$62,Code_Matrix!K$2:K$62) -> 2 | L3: =SUMPRODUCT(Code_Matrix!B$2:B$62,Code_Matrix!L$2:L$62) -> 2 | M3: =SUMPRODUCT(Code_Matrix!B$2:B$62,Code_Matrix!M$2:M$62) -> 1 | N3: =SUMPRODUCT(Code_Matrix!B$2:B$62,Code_Matrix!N$2:N$62) -> 2 | O3: =SUMPRODUCT(Code_Matrix!B$2:B$62,Code_Matrix!O$2:O$62) -> 2 | P3: =SUMPRODUCT(Code_Matrix!B$2:B$62,Code_Matrix!P$2:P$62) -> 0 | Q3: =SUMPRODUCT(Code_Matrix!B$2:B$62,Code_Matrix!Q$2:Q$62) -> 2 | R3: =SUMPRODUCT(Code_Matrix!B$2:B$62,Code_Matrix!R$2:R$62) -> 3 | S3: =SUMPRODUCT(Code_Matrix!B$2:B$62,Code_Matrix!S$2:S$62) -> 1 | T3: =SUMPRODUCT(Code_Matrix!B$2:B$62,Code_Matrix!T$2:T$62) -> 0 | U3: =SUMPRODUCT(Code_Matrix!B$2:B$62,Code_Matrix!U$2:U$62) -> 0 | V3: =SUMPRODUCT(Code_Matrix!B$2:B$62,Code_Matrix!V$2:V$62) -> 1 | W3: =SUMPRODUCT(Code_Matrix!B$2:B$62,Code_Matrix!W$2:W$62) -> 6 | X3: =SUMPRODUCT(Code_Matrix!B$2:B$62,Code_Matrix!X$2:X$62) -> 2
A4: SEPARATION_LOSS | B4: =SUMPRODUCT(Code_Matrix!C$2:C$62,Code_Matrix!B$2:B$62) -> 8 | C4: =SUMPRODUCT(Code_Matrix!C$2:C$62,Code_Matrix!C$2:C$62) -> 8 | D4: =SUMPRODUCT(Code_Matrix!C$2:C$62,Code_Matrix!D$2:D$62) -> 0 | E4: =SUMPRODUCT(Code_Matrix!C$2:C$62,Code_Matrix!E$2:E$62) -> 1 | F4: =SUMPRODUCT(Code_Matrix!C$2:C$62,Code_Matrix!F$2:F$62) -> 1 | G4: =SUMPRODUCT(Code_Matrix!C$2:C$62,Code_Matrix!G$2:G$62) -> 2 | H4: =SUMPRODUCT(Code_Matrix!C$2:C$62,Code_Matrix!H$2:H$62) -> 1 | I4: =SUMPRODUCT(Code_Matrix!C$2:C$62,Code_Matrix!I$2:I$62) -> 0 | J4: =SUMPRODUCT(Code_Matrix!C$2:C$62,Code_Matrix!J$2:J$62) -> 0 | K4: =SUMPRODUCT(Code_Matrix!C$2:C$62,Code_Matrix!K$2:K$62) -> 0 | L4: =SUMPRODUCT(Code_Matrix!C$2:C$62,Code_Matrix!L$2:L$62) -> 0 | M4: =SUMPRODUCT(Code_Matrix!C$2:C$62,Code_Matrix!M$2:M$62) -> 0 | N4: =SUMPRODUCT(Code_Matrix!C$2:C$62,Code_Matrix!N$2:N$62) -> 0 | O4: =SUMPRODUCT(Code_Matrix!C$2:C$62,Code_Matrix!O$2:O$62) -> 0 | P4: =SUMPRODUCT(Code_Matrix!C$2:C$62,Code_Matrix!P$2:P$62) -> 0 | Q4: =SUMPRODUCT(Code_Matrix!C$2:C$62,Code_Matrix!Q$2:Q$62) -> 0 | R4: =SUMPRODUCT(Code_Matrix!C$2:C$62,Code_Matrix!R$2:R$62) -> 1 | S4: =SUMPRODUCT(Code_Matrix!C$2:C$62,Code_Matrix!S$2:S$62) -> 0 | T4: =SUMPRODUCT(Code_Matrix!C$2:C$62,Code_Matrix!T$2:T$62) -> 0 | U4: =SUMPRODUCT(Code_Matrix!C$2:C$62,Code_Matrix!U$2:U$62) -> 0 | V4: =SUMPRODUCT(Code_Matrix!C$2:C$62,Code_Matrix!V$2:V$62) -> 0 | W4: =SUMPRODUCT(Code_Matrix!C$2:C$62,Code_Matrix!W$2:W$62) -> 0 | X4: =SUMPRODUCT(Code_Matrix!C$2:C$62,Code_Matrix!X$2:X$62) -> 0
A5: FAMILY | B5: =SUMPRODUCT(Code_Matrix!D$2:D$62,Code_Matrix!B$2:B$62) -> 0 | C5: =SUMPRODUCT(Code_Matrix!D$2:D$62,Code_Matrix!C$2:C$62) -> 0 | D5: =SUMPRODUCT(Code_Matrix!D$2:D$62,Code_Matrix!D$2:D$62) -> 9 | E5: =SUMPRODUCT(Code_Matrix!D$2:D$62,Code_Matrix!E$2:E$62) -> 5 | F5: =SUMPRODUCT(Code_Matrix!D$2:D$62,Code_Matrix!F$2:F$62) -> 2 | G5: =SUMPRODUCT(Code_Matrix!D$2:D$62,Code_Matrix!G$2:G$62) -> 0 | H5: =SUMPRODUCT(Code_Matrix!D$2:D$62,Code_Matrix!H$2:H$62) -> 1 | I5: =SUMPRODUCT(Code_Matrix!D$2:D$62,Code_Matrix!I$2:I$62) -> 0 | J5: =SUMPRODUCT(Code_Matrix!D$2:D$62,Code_Matrix!J$2:J$62) -> 1 | K5: =SUMPRODUCT(Code_Matrix!D$2:D$62,Code_Matrix!K$2:K$62) -> 2 | L5: =SUMPRODUCT(Code_Matrix!D$2:D$62,Code_Matrix!L$2:L$62) -> 0 | M5: =SUMPRODUCT(Code_Matrix!D$2:D$62,Code_Matrix!M$2:M$62) -> 2 | N5: =SUMPRODUCT(Code_Matrix!D$2:D$62,Code_Matrix!N$2:N$62) -> 1 | O5: =SUMPRODUCT(Code_Matrix!D$2:D$62,Code_Matrix!O$2:O$62) -> 1 | P5: =SUMPRODUCT(Code_Matrix!D$2:D$62,Code_Matrix!P$2:P$62) -> 2 | Q5: =SUMPRODUCT(Code_Matrix!D$2:D$62,Code_Matrix!Q$2:Q$62) -> 2 | R5: =SUMPRODUCT(Code_Matrix!D$2:D$62,Code_Matrix!R$2:R$62) -> 1 | S5: =SUMPRODUCT(Code_Matrix!D$2:D$62,Code_Matrix!S$2:S$62) -> 0 | T5: =SUMPRODUCT(Code_Matrix!D$2:D$62,Code_Matrix!T$2:T$62) -> 0 | U5: =SUMPRODUCT(Code_Matrix!D$2:D$62,Code_Matrix!U$2:U$62) -> 0 | V5: =SUMPRODUCT(Code_Matrix!D$2:D$62,Code_Matrix!V$2:V$62) -> 0 | W5: =SUMPRODUCT(Code_Matrix!D$2:D$62,Code_Matrix!W$2:W$62) -> 0 | X5: =SUMPRODUCT(Code_Matrix!D$2:D$62,Code_Matrix!X$2:X$62) -> 0
A6: MONEY_MATERIALISM | B6: =SUMPRODUCT(Code_Matrix!E$2:E$62,Code_Matrix!B$2:B$62) -> 1 | C6: =SUMPRODUCT(Code_Matrix!E$2:E$62,Code_Matrix!C$2:C$62) -> 1 | D6: =SUMPRODUCT(Code_Matrix!E$2:E$62,Code_Matrix!D$2:D$62) -> 5 | E6: =SUMPRODUCT(Code_Matrix!E$2:E$62,Code_Matrix!E$2:E$62) -> 11 | F6: =SUMPRODUCT(Code_Matrix!E$2:E$62,Code_Matrix!F$2:F$62) -> 4 | G6: =SUMPRODUCT(Code_Matrix!E$2:E$62,Code_Matrix!G$2:G$62) -> 1 | H6: =SUMPRODUCT(Code_Matrix!E$2:E$62,Code_Matrix!H$2:H$62) -> 0 | I6: =SUMPRODUCT(Code_Matrix!E$2:E$62,Code_Matrix!I$2:I$62) -> 0 | J6: =SUMPRODUCT(Code_Matrix!E$2:E$62,Code_Matrix!J$2:J$62) -> 0 | K6: =SUMPRODUCT(Code_Matrix!E$2:E$62,Code_Matrix!K$2:K$62) -> 2 | L6: =SUMPRODUCT(Code_Matrix!E$2:E$62,Code_Matrix!L$2:L$62) -> 1 | M6: =SUMPRODUCT(Code_Matrix!E$2:E$62,Code_Matrix!M$2:M$62) -> 2 | N6: =SUMPRODUCT(Code_Matrix!E$2:E$62,Code_Matrix!N$2:N$62) -> 1 | O6: =SUMPRODUCT(Code_Matrix!E$2:E$62,Code_Matrix!O$2:O$62) -> 1 | P6: =SUMPRODUCT(Code_Matrix!E$2:E$62,Code_Matrix!P$2:P$62) -> 2 | Q6: =SUMPRODUCT(Code_Matrix!E$2:E$62,Code_Matrix!Q$2:Q$62) -> 2 | R6: =SUMPRODUCT(Code_Matrix!E$2:E$62,Code_Matrix!R$2:R$62) -> 0 | S6: =SUMPRODUCT(Code_Matrix!E$2:E$62,Code_Matrix!S$2:S$62) -> 0 | T6: =SUMPRODUCT(Code_Matrix!E$2:E$62,Code_Matrix!T$2:T$62) -> 1 | U6: =SUMPRODUCT(Code_Matrix!E$2:E$62,Code_Matrix!U$2:U$62) -> 0 | V6: =SUMPRODUCT(Code_Matrix!E$2:E$62,Code_Matrix!V$2:V$62) -> 0 | W6: =SUMPRODUCT(Code_Matrix!E$2:E$62,Code_Matrix!W$2:W$62) -> 1 | X6: =SUMPRODUCT(Code_Matrix!E$2:E$62,Code_Matrix!X$2:X$62) -> 0
A7: CLASS_INEQUALITY_CRITIQUE | B7: =SUMPRODUCT(Code_Matrix!F$2:F$62,Code_Matrix!B$2:B$62) -> 1 | C7: =SUMPRODUCT(Code_Matrix!F$2:F$62,Code_Matrix!C$2:C$62) -> 1 | D7: =SUMPRODUCT(Code_Matrix!F$2:F$62,Code_Matrix!D$2:D$62) -> 2 | E7: =SUMPRODUCT(Code_Matrix!F$2:F$62,Code_Matrix!E$2:E$62) -> 4 | F7: =SUMPRODUCT(Code_Matrix!F$2:F$62,Code_Matrix!F$2:F$62) -> 7 | G7: =SUMPRODUCT(Code_Matrix!F$2:F$62,Code_Matrix!G$2:G$62) -> 1 | H7: =SUMPRODUCT(Code_Matrix!F$2:F$62,Code_Matrix!H$2:H$62) -> 0 | I7: =SUMPRODUCT(Code_Matrix!F$2:F$62,Code_Matrix!I$2:I$62) -> 0 | J7: =SUMPRODUCT(Code_Matrix!F$2:F$62,Code_Matrix!J$2:J$62) -> 0 | K7: =SUMPRODUCT(Code_Matrix!F$2:F$62,Code_Matrix!K$2:K$62) -> 0 | L7: =SUMPRODUCT(Code_Matrix!F$2:F$62,Code_Matrix!L$2:L$62) -> 0 | M7: =SUMPRODUCT(Code_Matrix!F$2:F$62,Code_Matrix!M$2:M$62) -> 0 | N7: =SUMPRODUCT(Code_Matrix!F$2:F$62,Code_Matrix!N$2:N$62) -> 0 | O7: =SUMPRODUCT(Code_Matrix!F$2:F$62,Code_Matrix!O$2:O$62) -> 1 | P7: =SUMPRODUCT(Code_Matrix!F$2:F$62,Code_Matrix!P$2:P$62) -> 2 | Q7: =SUMPRODUCT(Code_Matrix!F$2:F$62,Code_Matrix!Q$2:Q$62) -> 1 | R7: =SUMPRODUCT(Code_Matrix!F$2:F$62,Code_Matrix!R$2:R$62) -> 0 | S7: =SUMPRODUCT(Code_Matrix!F$2:F$62,Code_Matrix!S$2:S$62) -> 0 | T7: =SUMPRODUCT(Code_Matrix!F$2:F$62,Code_Matrix!T$2:T$62) -> 1 | U7: =SUMPRODUCT(Code_Matrix!F$2:F$62,Code_Matrix!U$2:U$62) -> 1 | V7: =SUMPRODUCT(Code_Matrix!F$2:F$62,Code_Matrix!V$2:V$62) -> 0 | W7: =SUMPRODUCT(Code_Matrix!F$2:F$62,Code_Matrix!W$2:W$62) -> 1 | X7: =SUMPRODUCT(Code_Matrix!F$2:F$62,Code_Matrix!X$2:X$62) -> 0
A8: CONSUMER_STATUS | B8: =SUMPRODUCT(Code_Matrix!G$2:G$62,Code_Matrix!B$2:B$62) -> 2 | C8: =SUMPRODUCT(Code_Matrix!G$2:G$62,Code_Matrix!C$2:C$62) -> 2 | D8: =SUMPRODUCT(Code_Matrix!G$2:G$62,Code_Matrix!D$2:D$62) -> 0 | E8: =SUMPRODUCT(Code_Matrix!G$2:G$62,Code_Matrix!E$2:E$62) -> 1 | F8: =SUMPRODUCT(Code_Matrix!G$2:G$62,Code_Matrix!F$2:F$62) -> 1 | G8: =SUMPRODUCT(Code_Matrix!G$2:G$62,Code_Matrix!G$2:G$62) -> 2 | H8: =SUMPRODUCT(Code_Matrix!G$2:G$62,Code_Matrix!H$2:H$62) -> 0 | I8: =SUMPRODUCT(Code_Matrix!G$2:G$62,Code_Matrix!I$2:I$62) -> 0 | J8: =SUMPRODUCT(Code_Matrix!G$2:G$62,Code_Matrix!J$2:J$62) -> 0 | K8: =SUMPRODUCT(Code_Matrix!G$2:G$62,Code_Matrix!K$2:K$62) -> 0 | L8: =SUMPRODUCT(Code_Matrix!G$2:G$62,Code_Matrix!L$2:L$62) -> 0 | M8: =SUMPRODUCT(Code_Matrix!G$2:G$62,Code_Matrix!M$2:M$62) -> 0 | N8: =SUMPRODUCT(Code_Matrix!G$2:G$62,Code_Matrix!N$2:N$62) -> 0 | O8: =SUMPRODUCT(Code_Matrix!G$2:G$62,Code_Matrix!O$2:O$62) -> 0 | P8: =SUMPRODUCT(Code_Matrix!G$2:G$62,Code_Matrix!P$2:P$62) -> 0 | Q8: =SUMPRODUCT(Code_Matrix!G$2:G$62,Code_Matrix!Q$2:Q$62) -> 0 | R8: =SUMPRODUCT(Code_Matrix!G$2:G$62,Code_Matrix!R$2:R$62) -> 0 | S8: =SUMPRODUCT(Code_Matrix!G$2:G$62,Code_Matrix!S$2:S$62) -> 0 | T8: =SUMPRODUCT(Code_Matrix!G$2:G$62,Code_Matrix!T$2:T$62) -> 0 | U8: =SUMPRODUCT(Code_Matrix!G$2:G$62,Code_Matrix!U$2:U$62) -> 0 | V8: =SUMPRODUCT(Code_Matrix!G$2:G$62,Code_Matrix!V$2:V$62) -> 0 | W8: =SUMPRODUCT(Code_Matrix!G$2:G$62,Code_Matrix!W$2:W$62) -> 0 | X8: =SUMPRODUCT(Code_Matrix!G$2:G$62,Code_Matrix!X$2:X$62) -> 0
A9: MIGRATION | B9: =SUMPRODUCT(Code_Matrix!H$2:H$62,Code_Matrix!B$2:B$62) -> 1 | C9: =SUMPRODUCT(Code_Matrix!H$2:H$62,Code_Matrix!C$2:C$62) -> 1 | D9: =SUMPRODUCT(Code_Matrix!H$2:H$62,Code_Matrix!D$2:D$62) -> 1 | E9: =SUMPRODUCT(Code_Matrix!H$2:H$62,Code_Matrix!E$2:E$62) -> 0 | F9: =SUMPRODUCT(Code_Matrix!H$2:H$62,Code_Matrix!F$2:F$62) -> 0 | G9: =SUMPRODUCT(Code_Matrix!H$2:H$62,Code_Matrix!G$2:G$62) -> 0 | H9: =SUMPRODUCT(Code_Matrix!H$2:H$62,Code_Matrix!H$2:H$62) -> 4 | I9: =SUMPRODUCT(Code_Matrix!H$2:H$62,Code_Matrix!I$2:I$62) -> 1 | J9: =SUMPRODUCT(Code_Matrix!H$2:H$62,Code_Matrix!J$2:J$62) -> 1 | K9: =SUMPRODUCT(Code_Matrix!H$2:H$62,Code_Matrix!K$2:K$62) -> 1 | L9: =SUMPRODUCT(Code_Matrix!H$2:H$62,Code_Matrix!L$2:L$62) -> 0 | M9: =SUMPRODUCT(Code_Matrix!H$2:H$62,Code_Matrix!M$2:M$62) -> 0 | N9: =SUMPRODUCT(Code_Matrix!H$2:H$62,Code_Matrix!N$2:N$62) -> 0 | O9: =SUMPRODUCT(Code_Matrix!H$2:H$62,Code_Matrix!O$2:O$62) -> 0 | P9: =SUMPRODUCT(Code_Matrix!H$2:H$62,Code_Matrix!P$2:P$62) -> 1 | Q9: =SUMPRODUCT(Code_Matrix!H$2:H$62,Code_Matrix!Q$2:Q$62) -> 0 | R9: =SUMPRODUCT(Code_Matrix!H$2:H$62,Code_Matrix!R$2:R$62) -> 0 | S9: =SUMPRODUCT(Code_Matrix!H$2:H$62,Code_Matrix!S$2:S$62) -> 0 | T9: =SUMPRODUCT(Code_Matrix!H$2:H$62,Code_Matrix!T$2:T$62) -> 0 | U9: =SUMPRODUCT(Code_Matrix!H$2:H$62,Code_Matrix!U$2:U$62) -> 0 | V9: =SUMPRODUCT(Code_Matrix!H$2:H$62,Code_Matrix!V$2:V$62) -> 0 | W9: =SUMPRODUCT(Code_Matrix!H$2:H$62,Code_Matrix!W$2:W$62) -> 2 | X9: =SUMPRODUCT(Code_Matrix!H$2:H$62,Code_Matrix!X$2:X$62) -> 0
A10: EDUCATION | B10: =SUMPRODUCT(Code_Matrix!I$2:I$62,Code_Matrix!B$2:B$62) -> 0 | C10: =SUMPRODUCT(Code_Matrix!I$2:I$62,Code_Matrix!C$2:C$62) -> 0 | D10: =SUMPRODUCT(Code_Matrix!I$2:I$62,Code_Matrix!D$2:D$62) -> 0 | E10: =SUMPRODUCT(Code_Matrix!I$2:I$62,Code_Matrix!E$2:E$62) -> 0 | F10: =SUMPRODUCT(Code_Matrix!I$2:I$62,Code_Matrix!F$2:F$62) -> 0 | G10: =SUMPRODUCT(Code_Matrix!I$2:I$62,Code_Matrix!G$2:G$62) -> 0 | H10: =SUMPRODUCT(Code_Matrix!I$2:I$62,Code_Matrix!H$2:H$62) -> 1 | I10: =SUMPRODUCT(Code_Matrix!I$2:I$62,Code_Matrix!I$2:I$62) -> 1 | J10: =SUMPRODUCT(Code_Matrix!I$2:I$62,Code_Matrix!J$2:J$62) -> 0 | K10: =SUMPRODUCT(Code_Matrix!I$2:I$62,Code_Matrix!K$2:K$62) -> 0 | L10: =SUMPRODUCT(Code_Matrix!I$2:I$62,Code_Matrix!L$2:L$62) -> 0 | M10: =SUMPRODUCT(Code_Matrix!I$2:I$62,Code_Matrix!M$2:M$62) -> 0 | N10: =SUMPRODUCT(Code_Matrix!I$2:I$62,Code_Matrix!N$2:N$62) -> 0 | O10: =SUMPRODUCT(Code_Matrix!I$2:I$62,Code_Matrix!O$2:O$62) -> 0 | P10: =SUMPRODUCT(Code_Matrix!I$2:I$62,Code_Matrix!P$2:P$62) -> 0 | Q10: =SUMPRODUCT(Code_Matrix!I$2:I$62,Code_Matrix!Q$2:Q$62) -> 0 | R10: =SUMPRODUCT(Code_Matrix!I$2:I$62,Code_Matrix!R$2:R$62) -> 0 | S10: =SUMPRODUCT(Code_Matrix!I$2:I$62,Code_Matrix!S$2:S$62) -> 0 | T10: =SUMPRODUCT(Code_Matrix!I$2:I$62,Code_Matrix!T$2:T$62) -> 0 | U10: =SUMPRODUCT(Code_Matrix!I$2:I$62,Code_Matrix!U$2:U$62) -> 0 | V10: =SUMPRODUCT(Code_Matrix!I$2:I$62,Code_Matrix!V$2:V$62) -> 0 | W10: =SUMPRODUCT(Code_Matrix!I$2:I$62,Code_Matrix!W$2:W$62) -> 1 | X10: =SUMPRODUCT(Code_Matrix!I$2:I$62,Code_Matrix!X$2:X$62) -> 0
A11: DRIVER_IDENTITY | B11: =SUMPRODUCT(Code_Matrix!J$2:J$62,Code_Matrix!B$2:B$62) -> 3 | C11: =SUMPRODUCT(Code_Matrix!J$2:J$62,Code_Matrix!C$2:C$62) -> 0 | D11: =SUMPRODUCT(Code_Matrix!J$2:J$62,Code_Matrix!D$2:D$62) -> 1 | E11: =SUMPRODUCT(Code_Matrix!J$2:J$62,Code_Matrix!E$2:E$62) -> 0 | F11: =SUMPRODUCT(Code_Matrix!J$2:J$62,Code_Matrix!F$2:F$62) -> 0 | G11: =SUMPRODUCT(Code_Matrix!J$2:J$62,Code_Matrix!G$2:G$62) -> 0 | H11: =SUMPRODUCT(Code_Matrix!J$2:J$62,Code_Matrix!H$2:H$62) -> 1 | I11: =SUMPRODUCT(Code_Matrix!J$2:J$62,Code_Matrix!I$2:I$62) -> 0 | J11: =SUMPRODUCT(Code_Matrix!J$2:J$62,Code_Matrix!J$2:J$62) -> 8 | K11: =SUMPRODUCT(Code_Matrix!J$2:J$62,Code_Matrix!K$2:K$62) -> 5 | L11: =SUMPRODUCT(Code_Matrix!J$2:J$62,Code_Matrix!L$2:L$62) -> 0 | M11: =SUMPRODUCT(Code_Matrix!J$2:J$62,Code_Matrix!M$2:M$62) -> 1 | N11: =SUMPRODUCT(Code_Matrix!J$2:J$62,Code_Matrix!N$2:N$62) -> 1 | O11: =SUMPRODUCT(Code_Matrix!J$2:J$62,Code_Matrix!O$2:O$62) -> 2 | P11: =SUMPRODUCT(Code_Matrix!J$2:J$62,Code_Matrix!P$2:P$62) -> 1 | Q11: =SUMPRODUCT(Code_Matrix!J$2:J$62,Code_Matrix!Q$2:Q$62) -> 0 | R11: =SUMPRODUCT(Code_Matrix!J$2:J$62,Code_Matrix!R$2:R$62) -> 0 | S11: =SUMPRODUCT(Code_Matrix!J$2:J$62,Code_Matrix!S$2:S$62) -> 1 | T11: =SUMPRODUCT(Code_Matrix!J$2:J$62,Code_Matrix!T$2:T$62) -> 1 | U11: =SUMPRODUCT(Code_Matrix!J$2:J$62,Code_Matrix!U$2:U$62) -> 0 | V11: =SUMPRODUCT(Code_Matrix!J$2:J$62,Code_Matrix!V$2:V$62) -> 1 | W11: =SUMPRODUCT(Code_Matrix!J$2:J$62,Code_Matrix!W$2:W$62) -> 4 | X11: =SUMPRODUCT(Code_Matrix!J$2:J$62,Code_Matrix!X$2:X$62) -> 0
A12: LABOR_DIGNITY | B12: =SUMPRODUCT(Code_Matrix!K$2:K$62,Code_Matrix!B$2:B$62) -> 2 | C12: =SUMPRODUCT(Code_Matrix!K$2:K$62,Code_Matrix!C$2:C$62) -> 0 | D12: =SUMPRODUCT(Code_Matrix!K$2:K$62,Code_Matrix!D$2:D$62) -> 2 | E12: =SUMPRODUCT(Code_Matrix!K$2:K$62,Code_Matrix!E$2:E$62) -> 2 | F12: =SUMPRODUCT(Code_Matrix!K$2:K$62,Code_Matrix!F$2:F$62) -> 0 | G12: =SUMPRODUCT(Code_Matrix!K$2:K$62,Code_Matrix!G$2:G$62) -> 0 | H12: =SUMPRODUCT(Code_Matrix!K$2:K$62,Code_Matrix!H$2:H$62) -> 1 | I12: =SUMPRODUCT(Code_Matrix!K$2:K$62,Code_Matrix!I$2:I$62) -> 0 | J12: =SUMPRODUCT(Code_Matrix!K$2:K$62,Code_Matrix!J$2:J$62) -> 5 | K12: =SUMPRODUCT(Code_Matrix!K$2:K$62,Code_Matrix!K$2:K$62) -> 8 | L12: =SUMPRODUCT(Code_Matrix!K$2:K$62,Code_Matrix!L$2:L$62) -> 2 | M12: =SUMPRODUCT(Code_Matrix!K$2:K$62,Code_Matrix!M$2:M$62) -> 0 | N12: =SUMPRODUCT(Code_Matrix!K$2:K$62,Code_Matrix!N$2:N$62) -> 0 | O12: =SUMPRODUCT(Code_Matrix!K$2:K$62,Code_Matrix!O$2:O$62) -> 2 | P12: =SUMPRODUCT(Code_Matrix!K$2:K$62,Code_Matrix!P$2:P$62) -> 1 | Q12: =SUMPRODUCT(Code_Matrix!K$2:K$62,Code_Matrix!Q$2:Q$62) -> 0 | R12: =SUMPRODUCT(Code_Matrix!K$2:K$62,Code_Matrix!R$2:R$62) -> 0 | S12: =SUMPRODUCT(Code_Matrix!K$2:K$62,Code_Matrix!S$2:S$62) -> 1 | T12: =SUMPRODUCT(Code_Matrix!K$2:K$62,Code_Matrix!T$2:T$62) -> 1 | U12: =SUMPRODUCT(Code_Matrix!K$2:K$62,Code_Matrix!U$2:U$62) -> 0 | V12: =SUMPRODUCT(Code_Matrix!K$2:K$62,Code_Matrix!V$2:V$62) -> 0 | W12: =SUMPRODUCT(Code_Matrix!K$2:K$62,Code_Matrix!W$2:W$62) -> 1 | X12: =SUMPRODUCT(Code_Matrix!K$2:K$62,Code_Matrix!X$2:X$62) -> 0
A13: FARE_LIVELIHOOD | B13: =SUMPRODUCT(Code_Matrix!L$2:L$62,Code_Matrix!B$2:B$62) -> 2 | C13: =SUMPRODUCT(Code_Matrix!L$2:L$62,Code_Matrix!C$2:C$62) -> 0 | D13: =SUMPRODUCT(Code_Matrix!L$2:L$62,Code_Matrix!D$2:D$62) -> 0 | E13: =SUMPRODUCT(Code_Matrix!L$2:L$62,Code_Matrix!E$2:E$62) -> 1 | F13: =SUMPRODUCT(Code_Matrix!L$2:L$62,Code_Matrix!F$2:F$62) -> 0 | G13: =SUMPRODUCT(Code_Matrix!L$2:L$62,Code_Matrix!G$2:G$62) -> 0 | H13: =SUMPRODUCT(Code_Matrix!L$2:L$62,Code_Matrix!H$2:H$62) -> 0 | I13: =SUMPRODUCT(Code_Matrix!L$2:L$62,Code_Matrix!I$2:I$62) -> 0 | J13: =SUMPRODUCT(Code_Matrix!L$2:L$62,Code_Matrix!J$2:J$62) -> 0 | K13: =SUMPRODUCT(Code_Matrix!L$2:L$62,Code_Matrix!K$2:K$62) -> 2 | L13: =SUMPRODUCT(Code_Matrix!L$2:L$62,Code_Matrix!L$2:L$62) -> 4 | M13: =SUMPRODUCT(Code_Matrix!L$2:L$62,Code_Matrix!M$2:M$62) -> 0 | N13: =SUMPRODUCT(Code_Matrix!L$2:L$62,Code_Matrix!N$2:N$62) -> 0 | O13: =SUMPRODUCT(Code_Matrix!L$2:L$62,Code_Matrix!O$2:O$62) -> 1 | P13: =SUMPRODUCT(Code_Matrix!L$2:L$62,Code_Matrix!P$2:P$62) -> 0 | Q13: =SUMPRODUCT(Code_Matrix!L$2:L$62,Code_Matrix!Q$2:Q$62) -> 0 | R13: =SUMPRODUCT(Code_Matrix!L$2:L$62,Code_Matrix!R$2:R$62) -> 2 | S13: =SUMPRODUCT(Code_Matrix!L$2:L$62,Code_Matrix!S$2:S$62) -> 0 | T13: =SUMPRODUCT(Code_Matrix!L$2:L$62,Code_Matrix!T$2:T$62) -> 0 | U13: =SUMPRODUCT(Code_Matrix!L$2:L$62,Code_Matrix!U$2:U$62) -> 0 | V13: =SUMPRODUCT(Code_Matrix!L$2:L$62,Code_Matrix!V$2:V$62) -> 0 | W13: =SUMPRODUCT(Code_Matrix!L$2:L$62,Code_Matrix!W$2:W$62) -> 2 | X13: =SUMPRODUCT(Code_Matrix!L$2:L$62,Code_Matrix!X$2:X$62) -> 1
A14: MASCULINITY | B14: =SUMPRODUCT(Code_Matrix!M$2:M$62,Code_Matrix!B$2:B$62) -> 1 | C14: =SUMPRODUCT(Code_Matrix!M$2:M$62,Code_Matrix!C$2:C$62) -> 0 | D14: =SUMPRODUCT(Code_Matrix!M$2:M$62,Code_Matrix!D$2:D$62) -> 2 | E14: =SUMPRODUCT(Code_Matrix!M$2:M$62,Code_Matrix!E$2:E$62) -> 2 | F14: =SUMPRODUCT(Code_Matrix!M$2:M$62,Code_Matrix!F$2:F$62) -> 0 | G14: =SUMPRODUCT(Code_Matrix!M$2:M$62,Code_Matrix!G$2:G$62) -> 0 | H14: =SUMPRODUCT(Code_Matrix!M$2:M$62,Code_Matrix!H$2:H$62) -> 0 | I14: =SUMPRODUCT(Code_Matrix!M$2:M$62,Code_Matrix!I$2:I$62) -> 0 | J14: =SUMPRODUCT(Code_Matrix!M$2:M$62,Code_Matrix!J$2:J$62) -> 1 | K14: =SUMPRODUCT(Code_Matrix!M$2:M$62,Code_Matrix!K$2:K$62) -> 0 | L14: =SUMPRODUCT(Code_Matrix!M$2:M$62,Code_Matrix!L$2:L$62) -> 0 | M14: =SUMPRODUCT(Code_Matrix!M$2:M$62,Code_Matrix!M$2:M$62) -> 5 | N14: =SUMPRODUCT(Code_Matrix!M$2:M$62,Code_Matrix!N$2:N$62) -> 1 | O14: =SUMPRODUCT(Code_Matrix!M$2:M$62,Code_Matrix!O$2:O$62) -> 1 | P14: =SUMPRODUCT(Code_Matrix!M$2:M$62,Code_Matrix!P$2:P$62) -> 0 | Q14: =SUMPRODUCT(Code_Matrix!M$2:M$62,Code_Matrix!Q$2:Q$62) -> 1 | R14: =SUMPRODUCT(Code_Matrix!M$2:M$62,Code_Matrix!R$2:R$62) -> 0 | S14: =SUMPRODUCT(Code_Matrix!M$2:M$62,Code_Matrix!S$2:S$62) -> 0 | T14: =SUMPRODUCT(Code_Matrix!M$2:M$62,Code_Matrix!T$2:T$62) -> 0 | U14: =SUMPRODUCT(Code_Matrix!M$2:M$62,Code_Matrix!U$2:U$62) -> 0 | V14: =SUMPRODUCT(Code_Matrix!M$2:M$62,Code_Matrix!V$2:V$62) -> 0 | W14: =SUMPRODUCT(Code_Matrix!M$2:M$62,Code_Matrix!W$2:W$62) -> 2 | X14: =SUMPRODUCT(Code_Matrix!M$2:M$62,Code_Matrix!X$2:X$62) -> 0
A15: WOMEN_REPRESENTATION | B15: =SUMPRODUCT(Code_Matrix!N$2:N$62,Code_Matrix!B$2:B$62) -> 2 | C15: =SUMPRODUCT(Code_Matrix!N$2:N$62,Code_Matrix!C$2:C$62) -> 0 | D15: =SUMPRODUCT(Code_Matrix!N$2:N$62,Code_Matrix!D$2:D$62) -> 1 | E15: =SUMPRODUCT(Code_Matrix!N$2:N$62,Code_Matrix!E$2:E$62) -> 1 | F15: =SUMPRODUCT(Code_Matrix!N$2:N$62,Code_Matrix!F$2:F$62) -> 0 | G15: =SUMPRODUCT(Code_Matrix!N$2:N$62,Code_Matrix!G$2:G$62) -> 0 | H15: =SUMPRODUCT(Code_Matrix!N$2:N$62,Code_Matrix!H$2:H$62) -> 0 | I15: =SUMPRODUCT(Code_Matrix!N$2:N$62,Code_Matrix!I$2:I$62) -> 0 | J15: =SUMPRODUCT(Code_Matrix!N$2:N$62,Code_Matrix!J$2:J$62) -> 1 | K15: =SUMPRODUCT(Code_Matrix!N$2:N$62,Code_Matrix!K$2:K$62) -> 0 | L15: =SUMPRODUCT(Code_Matrix!N$2:N$62,Code_Matrix!L$2:L$62) -> 0 | M15: =SUMPRODUCT(Code_Matrix!N$2:N$62,Code_Matrix!M$2:M$62) -> 1 | N15: =SUMPRODUCT(Code_Matrix!N$2:N$62,Code_Matrix!N$2:N$62) -> 4 | O15: =SUMPRODUCT(Code_Matrix!N$2:N$62,Code_Matrix!O$2:O$62) -> 0 | P15: =SUMPRODUCT(Code_Matrix!N$2:N$62,Code_Matrix!P$2:P$62) -> 0 | Q15: =SUMPRODUCT(Code_Matrix!N$2:N$62,Code_Matrix!Q$2:Q$62) -> 0 | R15: =SUMPRODUCT(Code_Matrix!N$2:N$62,Code_Matrix!R$2:R$62) -> 0 | S15: =SUMPRODUCT(Code_Matrix!N$2:N$62,Code_Matrix!S$2:S$62) -> 0 | T15: =SUMPRODUCT(Code_Matrix!N$2:N$62,Code_Matrix!T$2:T$62) -> 0 | U15: =SUMPRODUCT(Code_Matrix!N$2:N$62,Code_Matrix!U$2:U$62) -> 0 | V15: =SUMPRODUCT(Code_Matrix!N$2:N$62,Code_Matrix!V$2:V$62) -> 2 | W15: =SUMPRODUCT(Code_Matrix!N$2:N$62,Code_Matrix!W$2:W$62) -> 2 | X15: =SUMPRODUCT(Code_Matrix!N$2:N$62,Code_Matrix!X$2:X$62) -> 1
A16: SELF_RESPECT | B16: =SUMPRODUCT(Code_Matrix!O$2:O$62,Code_Matrix!B$2:B$62) -> 2 | C16: =SUMPRODUCT(Code_Matrix!O$2:O$62,Code_Matrix!C$2:C$62) -> 0 | D16: =SUMPRODUCT(Code_Matrix!O$2:O$62,Code_Matrix!D$2:D$62) -> 1 | E16: =SUMPRODUCT(Code_Matrix!O$2:O$62,Code_Matrix!E$2:E$62) -> 1 | F16: =SUMPRODUCT(Code_Matrix!O$2:O$62,Code_Matrix!F$2:F$62) -> 1 | G16: =SUMPRODUCT(Code_Matrix!O$2:O$62,Code_Matrix!G$2:G$62) -> 0 | H16: =SUMPRODUCT(Code_Matrix!O$2:O$62,Code_Matrix!H$2:H$62) -> 0 | I16: =SUMPRODUCT(Code_Matrix!O$2:O$62,Code_Matrix!I$2:I$62) -> 0 | J16: =SUMPRODUCT(Code_Matrix!O$2:O$62,Code_Matrix!J$2:J$62) -> 2 | K16: =SUMPRODUCT(Code_Matrix!O$2:O$62,Code_Matrix!K$2:K$62) -> 2 | L16: =SUMPRODUCT(Code_Matrix!O$2:O$62,Code_Matrix!L$2:L$62) -> 1 | M16: =SUMPRODUCT(Code_Matrix!O$2:O$62,Code_Matrix!M$2:M$62) -> 1 | N16: =SUMPRODUCT(Code_Matrix!O$2:O$62,Code_Matrix!N$2:N$62) -> 0 | O16: =SUMPRODUCT(Code_Matrix!O$2:O$62,Code_Matrix!O$2:O$62) -> 10 | P16: =SUMPRODUCT(Code_Matrix!O$2:O$62,Code_Matrix!P$2:P$62) -> 0 | Q16: =SUMPRODUCT(Code_Matrix!O$2:O$62,Code_Matrix!Q$2:Q$62) -> 4 | R16: =SUMPRODUCT(Code_Matrix!O$2:O$62,Code_Matrix!R$2:R$62) -> 0 | S16: =SUMPRODUCT(Code_Matrix!O$2:O$62,Code_Matrix!S$2:S$62) -> 0 | T16: =SUMPRODUCT(Code_Matrix!O$2:O$62,Code_Matrix!T$2:T$62) -> 0 | U16: =SUMPRODUCT(Code_Matrix!O$2:O$62,Code_Matrix!U$2:U$62) -> 0 | V16: =SUMPRODUCT(Code_Matrix!O$2:O$62,Code_Matrix!V$2:V$62) -> 1 | W16: =SUMPRODUCT(Code_Matrix!O$2:O$62,Code_Matrix!W$2:W$62) -> 2 | X16: =SUMPRODUCT(Code_Matrix!O$2:O$62,Code_Matrix!X$2:X$62) -> 1
A17: DISTRUST_HYPOCRISY | B17: =SUMPRODUCT(Code_Matrix!P$2:P$62,Code_Matrix!B$2:B$62) -> 0 | C17: =SUMPRODUCT(Code_Matrix!P$2:P$62,Code_Matrix!C$2:C$62) -> 0 | D17: =SUMPRODUCT(Code_Matrix!P$2:P$62,Code_Matrix!D$2:D$62) -> 2 | E17: =SUMPRODUCT(Code_Matrix!P$2:P$62,Code_Matrix!E$2:E$62) -> 2 | F17: =SUMPRODUCT(Code_Matrix!P$2:P$62,Code_Matrix!F$2:F$62) -> 2 | G17: =SUMPRODUCT(Code_Matrix!P$2:P$62,Code_Matrix!G$2:G$62) -> 0 | H17: =SUMPRODUCT(Code_Matrix!P$2:P$62,Code_Matrix!H$2:H$62) -> 1 | I17: =SUMPRODUCT(Code_Matrix!P$2:P$62,Code_Matrix!I$2:I$62) -> 0 | J17: =SUMPRODUCT(Code_Matrix!P$2:P$62,Code_Matrix!J$2:J$62) -> 1 | K17: =SUMPRODUCT(Code_Matrix!P$2:P$62,Code_Matrix!K$2:K$62) -> 1 | L17: =SUMPRODUCT(Code_Matrix!P$2:P$62,Code_Matrix!L$2:L$62) -> 0 | M17: =SUMPRODUCT(Code_Matrix!P$2:P$62,Code_Matrix!M$2:M$62) -> 0 | N17: =SUMPRODUCT(Code_Matrix!P$2:P$62,Code_Matrix!N$2:N$62) -> 0 | O17: =SUMPRODUCT(Code_Matrix!P$2:P$62,Code_Matrix!O$2:O$62) -> 0 | P17: =SUMPRODUCT(Code_Matrix!P$2:P$62,Code_Matrix!P$2:P$62) -> 7 | Q17: =SUMPRODUCT(Code_Matrix!P$2:P$62,Code_Matrix!Q$2:Q$62) -> 2 | R17: =SUMPRODUCT(Code_Matrix!P$2:P$62,Code_Matrix!R$2:R$62) -> 1 | S17: =SUMPRODUCT(Code_Matrix!P$2:P$62,Code_Matrix!S$2:S$62) -> 0 | T17: =SUMPRODUCT(Code_Matrix!P$2:P$62,Code_Matrix!T$2:T$62) -> 0 | U17: =SUMPRODUCT(Code_Matrix!P$2:P$62,Code_Matrix!U$2:U$62) -> 1 | V17: =SUMPRODUCT(Code_Matrix!P$2:P$62,Code_Matrix!V$2:V$62) -> 0 | W17: =SUMPRODUCT(Code_Matrix!P$2:P$62,Code_Matrix!W$2:W$62) -> 2 | X17: =SUMPRODUCT(Code_Matrix!P$2:P$62,Code_Matrix!X$2:X$62) -> 0
A18: MORAL_ADVICE | B18: =SUMPRODUCT(Code_Matrix!Q$2:Q$62,Code_Matrix!B$2:B$62) -> 2 | C18: =SUMPRODUCT(Code_Matrix!Q$2:Q$62,Code_Matrix!C$2:C$62) -> 0 | D18: =SUMPRODUCT(Code_Matrix!Q$2:Q$62,Code_Matrix!D$2:D$62) -> 2 | E18: =SUMPRODUCT(Code_Matrix!Q$2:Q$62,Code_Matrix!E$2:E$62) -> 2 | F18: =SUMPRODUCT(Code_Matrix!Q$2:Q$62,Code_Matrix!F$2:F$62) -> 1 | G18: =SUMPRODUCT(Code_Matrix!Q$2:Q$62,Code_Matrix!G$2:G$62) -> 0 | H18: =SUMPRODUCT(Code_Matrix!Q$2:Q$62,Code_Matrix!H$2:H$62) -> 0 | I18: =SUMPRODUCT(Code_Matrix!Q$2:Q$62,Code_Matrix!I$2:I$62) -> 0 | J18: =SUMPRODUCT(Code_Matrix!Q$2:Q$62,Code_Matrix!J$2:J$62) -> 0 | K18: =SUMPRODUCT(Code_Matrix!Q$2:Q$62,Code_Matrix!K$2:K$62) -> 0 | L18: =SUMPRODUCT(Code_Matrix!Q$2:Q$62,Code_Matrix!L$2:L$62) -> 0 | M18: =SUMPRODUCT(Code_Matrix!Q$2:Q$62,Code_Matrix!M$2:M$62) -> 1 | N18: =SUMPRODUCT(Code_Matrix!Q$2:Q$62,Code_Matrix!N$2:N$62) -> 0 | O18: =SUMPRODUCT(Code_Matrix!Q$2:Q$62,Code_Matrix!O$2:O$62) -> 4 | P18: =SUMPRODUCT(Code_Matrix!Q$2:Q$62,Code_Matrix!P$2:P$62) -> 2 | Q18: =SUMPRODUCT(Code_Matrix!Q$2:Q$62,Code_Matrix!Q$2:Q$62) -> 11 | R18: =SUMPRODUCT(Code_Matrix!Q$2:Q$62,Code_Matrix!R$2:R$62) -> 0 | S18: =SUMPRODUCT(Code_Matrix!Q$2:Q$62,Code_Matrix!S$2:S$62) -> 1 | T18: =SUMPRODUCT(Code_Matrix!Q$2:Q$62,Code_Matrix!T$2:T$62) -> 1 | U18: =SUMPRODUCT(Code_Matrix!Q$2:Q$62,Code_Matrix!U$2:U$62) -> 0 | V18: =SUMPRODUCT(Code_Matrix!Q$2:Q$62,Code_Matrix!V$2:V$62) -> 0 | W18: =SUMPRODUCT(Code_Matrix!Q$2:Q$62,Code_Matrix!W$2:W$62) -> 0 | X18: =SUMPRODUCT(Code_Matrix!Q$2:Q$62,Code_Matrix!X$2:X$62) -> 0
A19: HOPE_RESILIENCE | B19: =SUMPRODUCT(Code_Matrix!R$2:R$62,Code_Matrix!B$2:B$62) -> 3 | C19: =SUMPRODUCT(Code_Matrix!R$2:R$62,Code_Matrix!C$2:C$62) -> 1 | D19: =SUMPRODUCT(Code_Matrix!R$2:R$62,Code_Matrix!D$2:D$62) -> 1 | E19: =SUMPRODUCT(Code_Matrix!R$2:R$62,Code_Matrix!E$2:E$62) -> 0 | F19: =SUMPRODUCT(Code_Matrix!R$2:R$62,Code_Matrix!F$2:F$62) -> 0 | G19: =SUMPRODUCT(Code_Matrix!R$2:R$62,Code_Matrix!G$2:G$62) -> 0 | H19: =SUMPRODUCT(Code_Matrix!R$2:R$62,Code_Matrix!H$2:H$62) -> 0 | I19: =SUMPRODUCT(Code_Matrix!R$2:R$62,Code_Matrix!I$2:I$62) -> 0 | J19: =SUMPRODUCT(Code_Matrix!R$2:R$62,Code_Matrix!J$2:J$62) -> 0 | K19: =SUMPRODUCT(Code_Matrix!R$2:R$62,Code_Matrix!K$2:K$62) -> 0 | L19: =SUMPRODUCT(Code_Matrix!R$2:R$62,Code_Matrix!L$2:L$62) -> 2 | M19: =SUMPRODUCT(Code_Matrix!R$2:R$62,Code_Matrix!M$2:M$62) -> 0 | N19: =SUMPRODUCT(Code_Matrix!R$2:R$62,Code_Matrix!N$2:N$62) -> 0 | O19: =SUMPRODUCT(Code_Matrix!R$2:R$62,Code_Matrix!O$2:O$62) -> 0 | P19: =SUMPRODUCT(Code_Matrix!R$2:R$62,Code_Matrix!P$2:P$62) -> 1 | Q19: =SUMPRODUCT(Code_Matrix!R$2:R$62,Code_Matrix!Q$2:Q$62) -> 0 | R19: =SUMPRODUCT(Code_Matrix!R$2:R$62,Code_Matrix!R$2:R$62) -> 10 | S19: =SUMPRODUCT(Code_Matrix!R$2:R$62,Code_Matrix!S$2:S$62) -> 2 | T19: =SUMPRODUCT(Code_Matrix!R$2:R$62,Code_Matrix!T$2:T$62) -> 1 | U19: =SUMPRODUCT(Code_Matrix!R$2:R$62,Code_Matrix!U$2:U$62) -> 0 | V19: =SUMPRODUCT(Code_Matrix!R$2:R$62,Code_Matrix!V$2:V$62) -> 0 | W19: =SUMPRODUCT(Code_Matrix!R$2:R$62,Code_Matrix!W$2:W$62) -> 3 | X19: =SUMPRODUCT(Code_Matrix!R$2:R$62,Code_Matrix!X$2:X$62) -> 1
A20: RELIGION_FATE | B20: =SUMPRODUCT(Code_Matrix!S$2:S$62,Code_Matrix!B$2:B$62) -> 1 | C20: =SUMPRODUCT(Code_Matrix!S$2:S$62,Code_Matrix!C$2:C$62) -> 0 | D20: =SUMPRODUCT(Code_Matrix!S$2:S$62,Code_Matrix!D$2:D$62) -> 0 | E20: =SUMPRODUCT(Code_Matrix!S$2:S$62,Code_Matrix!E$2:E$62) -> 0 | F20: =SUMPRODUCT(Code_Matrix!S$2:S$62,Code_Matrix!F$2:F$62) -> 0 | G20: =SUMPRODUCT(Code_Matrix!S$2:S$62,Code_Matrix!G$2:G$62) -> 0 | H20: =SUMPRODUCT(Code_Matrix!S$2:S$62,Code_Matrix!H$2:H$62) -> 0 | I20: =SUMPRODUCT(Code_Matrix!S$2:S$62,Code_Matrix!I$2:I$62) -> 0 | J20: =SUMPRODUCT(Code_Matrix!S$2:S$62,Code_Matrix!J$2:J$62) -> 1 | K20: =SUMPRODUCT(Code_Matrix!S$2:S$62,Code_Matrix!K$2:K$62) -> 1 | L20: =SUMPRODUCT(Code_Matrix!S$2:S$62,Code_Matrix!L$2:L$62) -> 0 | M20: =SUMPRODUCT(Code_Matrix!S$2:S$62,Code_Matrix!M$2:M$62) -> 0 | N20: =SUMPRODUCT(Code_Matrix!S$2:S$62,Code_Matrix!N$2:N$62) -> 0 | O20: =SUMPRODUCT(Code_Matrix!S$2:S$62,Code_Matrix!O$2:O$62) -> 0 | P20: =SUMPRODUCT(Code_Matrix!S$2:S$62,Code_Matrix!P$2:P$62) -> 0 | Q20: =SUMPRODUCT(Code_Matrix!S$2:S$62,Code_Matrix!Q$2:Q$62) -> 1 | R20: =SUMPRODUCT(Code_Matrix!S$2:S$62,Code_Matrix!R$2:R$62) -> 2 | S20: =SUMPRODUCT(Code_Matrix!S$2:S$62,Code_Matrix!S$2:S$62) -> 4 | T20: =SUMPRODUCT(Code_Matrix!S$2:S$62,Code_Matrix!T$2:T$62) -> 1 | U20: =SUMPRODUCT(Code_Matrix!S$2:S$62,Code_Matrix!U$2:U$62) -> 0 | V20: =SUMPRODUCT(Code_Matrix!S$2:S$62,Code_Matrix!V$2:V$62) -> 0 | W20: =SUMPRODUCT(Code_Matrix!S$2:S$62,Code_Matrix!W$2:W$62) -> 1 | X20: =SUMPRODUCT(Code_Matrix!S$2:S$62,Code_Matrix!X$2:X$62) -> 0
A21: MORTALITY_RISK | B21: =SUMPRODUCT(Code_Matrix!T$2:T$62,Code_Matrix!B$2:B$62) -> 0 | C21: =SUMPRODUCT(Code_Matrix!T$2:T$62,Code_Matrix!C$2:C$62) -> 0 | D21: =SUMPRODUCT(Code_Matrix!T$2:T$62,Code_Matrix!D$2:D$62) -> 0 | E21: =SUMPRODUCT(Code_Matrix!T$2:T$62,Code_Matrix!E$2:E$62) -> 1 | F21: =SUMPRODUCT(Code_Matrix!T$2:T$62,Code_Matrix!F$2:F$62) -> 1 | G21: =SUMPRODUCT(Code_Matrix!T$2:T$62,Code_Matrix!G$2:G$62) -> 0 | H21: =SUMPRODUCT(Code_Matrix!T$2:T$62,Code_Matrix!H$2:H$62) -> 0 | I21: =SUMPRODUCT(Code_Matrix!T$2:T$62,Code_Matrix!I$2:I$62) -> 0 | J21: =SUMPRODUCT(Code_Matrix!T$2:T$62,Code_Matrix!J$2:J$62) -> 1 | K21: =SUMPRODUCT(Code_Matrix!T$2:T$62,Code_Matrix!K$2:K$62) -> 1 | L21: =SUMPRODUCT(Code_Matrix!T$2:T$62,Code_Matrix!L$2:L$62) -> 0 | M21: =SUMPRODUCT(Code_Matrix!T$2:T$62,Code_Matrix!M$2:M$62) -> 0 | N21: =SUMPRODUCT(Code_Matrix!T$2:T$62,Code_Matrix!N$2:N$62) -> 0 | O21: =SUMPRODUCT(Code_Matrix!T$2:T$62,Code_Matrix!O$2:O$62) -> 0 | P21: =SUMPRODUCT(Code_Matrix!T$2:T$62,Code_Matrix!P$2:P$62) -> 0 | Q21: =SUMPRODUCT(Code_Matrix!T$2:T$62,Code_Matrix!Q$2:Q$62) -> 1 | R21: =SUMPRODUCT(Code_Matrix!T$2:T$62,Code_Matrix!R$2:R$62) -> 1 | S21: =SUMPRODUCT(Code_Matrix!T$2:T$62,Code_Matrix!S$2:S$62) -> 1 | T21: =SUMPRODUCT(Code_Matrix!T$2:T$62,Code_Matrix!T$2:T$62) -> 5 | U21: =SUMPRODUCT(Code_Matrix!T$2:T$62,Code_Matrix!U$2:U$62) -> 0 | V21: =SUMPRODUCT(Code_Matrix!T$2:T$62,Code_Matrix!V$2:V$62) -> 0 | W21: =SUMPRODUCT(Code_Matrix!T$2:T$62,Code_Matrix!W$2:W$62) -> 0 | X21: =SUMPRODUCT(Code_Matrix!T$2:T$62,Code_Matrix!X$2:X$62) -> 0
A22: INSTITUTION_CRITIQUE | B22: =SUMPRODUCT(Code_Matrix!U$2:U$62,Code_Matrix!B$2:B$62) -> 0 | C22: =SUMPRODUCT(Code_Matrix!U$2:U$62,Code_Matrix!C$2:C$62) -> 0 | D22: =SUMPRODUCT(Code_Matrix!U$2:U$62,Code_Matrix!D$2:D$62) -> 0 | E22: =SUMPRODUCT(Code_Matrix!U$2:U$62,Code_Matrix!E$2:E$62) -> 0 | F22: =SUMPRODUCT(Code_Matrix!U$2:U$62,Code_Matrix!F$2:F$62) -> 1 | G22: =SUMPRODUCT(Code_Matrix!U$2:U$62,Code_Matrix!G$2:G$62) -> 0 | H22: =SUMPRODUCT(Code_Matrix!U$2:U$62,Code_Matrix!H$2:H$62) -> 0 | I22: =SUMPRODUCT(Code_Matrix!U$2:U$62,Code_Matrix!I$2:I$62) -> 0 | J22: =SUMPRODUCT(Code_Matrix!U$2:U$62,Code_Matrix!J$2:J$62) -> 0 | K22: =SUMPRODUCT(Code_Matrix!U$2:U$62,Code_Matrix!K$2:K$62) -> 0 | L22: =SUMPRODUCT(Code_Matrix!U$2:U$62,Code_Matrix!L$2:L$62) -> 0 | M22: =SUMPRODUCT(Code_Matrix!U$2:U$62,Code_Matrix!M$2:M$62) -> 0 | N22: =SUMPRODUCT(Code_Matrix!U$2:U$62,Code_Matrix!N$2:N$62) -> 0 | O22: =SUMPRODUCT(Code_Matrix!U$2:U$62,Code_Matrix!O$2:O$62) -> 0 | P22: =SUMPRODUCT(Code_Matrix!U$2:U$62,Code_Matrix!P$2:P$62) -> 1 | Q22: =SUMPRODUCT(Code_Matrix!U$2:U$62,Code_Matrix!Q$2:Q$62) -> 0 | R22: =SUMPRODUCT(Code_Matrix!U$2:U$62,Code_Matrix!R$2:R$62) -> 0 | S22: =SUMPRODUCT(Code_Matrix!U$2:U$62,Code_Matrix!S$2:S$62) -> 0 | T22: =SUMPRODUCT(Code_Matrix!U$2:U$62,Code_Matrix!T$2:T$62) -> 0 | U22: =SUMPRODUCT(Code_Matrix!U$2:U$62,Code_Matrix!U$2:U$62) -> 4 | V22: =SUMPRODUCT(Code_Matrix!U$2:U$62,Code_Matrix!V$2:V$62) -> 1 | W22: =SUMPRODUCT(Code_Matrix!U$2:U$62,Code_Matrix!W$2:W$62) -> 3 | X22: =SUMPRODUCT(Code_Matrix!U$2:U$62,Code_Matrix!X$2:X$62) -> 0
A23: PLACE_IDENTITY | B23: =SUMPRODUCT(Code_Matrix!V$2:V$62,Code_Matrix!B$2:B$62) -> 1 | C23: =SUMPRODUCT(Code_Matrix!V$2:V$62,Code_Matrix!C$2:C$62) -> 0 | D23: =SUMPRODUCT(Code_Matrix!V$2:V$62,Code_Matrix!D$2:D$62) -> 0 | E23: =SUMPRODUCT(Code_Matrix!V$2:V$62,Code_Matrix!E$2:E$62) -> 0 | F23: =SUMPRODUCT(Code_Matrix!V$2:V$62,Code_Matrix!F$2:F$62) -> 0 | G23: =SUMPRODUCT(Code_Matrix!V$2:V$62,Code_Matrix!G$2:G$62) -> 0 | H23: =SUMPRODUCT(Code_Matrix!V$2:V$62,Code_Matrix!H$2:H$62) -> 0 | I23: =SUMPRODUCT(Code_Matrix!V$2:V$62,Code_Matrix!I$2:I$62) -> 0 | J23: =SUMPRODUCT(Code_Matrix!V$2:V$62,Code_Matrix!J$2:J$62) -> 1 | K23: =SUMPRODUCT(Code_Matrix!V$2:V$62,Code_Matrix!K$2:K$62) -> 0 | L23: =SUMPRODUCT(Code_Matrix!V$2:V$62,Code_Matrix!L$2:L$62) -> 0 | M23: =SUMPRODUCT(Code_Matrix!V$2:V$62,Code_Matrix!M$2:M$62) -> 0 | N23: =SUMPRODUCT(Code_Matrix!V$2:V$62,Code_Matrix!N$2:N$62) -> 2 | O23: =SUMPRODUCT(Code_Matrix!V$2:V$62,Code_Matrix!O$2:O$62) -> 1 | P23: =SUMPRODUCT(Code_Matrix!V$2:V$62,Code_Matrix!P$2:P$62) -> 0 | Q23: =SUMPRODUCT(Code_Matrix!V$2:V$62,Code_Matrix!Q$2:Q$62) -> 0 | R23: =SUMPRODUCT(Code_Matrix!V$2:V$62,Code_Matrix!R$2:R$62) -> 0 | S23: =SUMPRODUCT(Code_Matrix!V$2:V$62,Code_Matrix!S$2:S$62) -> 0 | T23: =SUMPRODUCT(Code_Matrix!V$2:V$62,Code_Matrix!T$2:T$62) -> 0 | U23: =SUMPRODUCT(Code_Matrix!V$2:V$62,Code_Matrix!U$2:U$62) -> 1 | V23: =SUMPRODUCT(Code_Matrix!V$2:V$62,Code_Matrix!V$2:V$62) -> 4 | W23: =SUMPRODUCT(Code_Matrix!V$2:V$62,Code_Matrix!W$2:W$62) -> 3 | X23: =SUMPRODUCT(Code_Matrix!V$2:V$62,Code_Matrix!X$2:X$62) -> 0
A24: HUMOR | B24: =SUMPRODUCT(Code_Matrix!W$2:W$62,Code_Matrix!B$2:B$62) -> 6 | C24: =SUMPRODUCT(Code_Matrix!W$2:W$62,Code_Matrix!C$2:C$62) -> 0 | D24: =SUMPRODUCT(Code_Matrix!W$2:W$62,Code_Matrix!D$2:D$62) -> 0 | E24: =SUMPRODUCT(Code_Matrix!W$2:W$62,Code_Matrix!E$2:E$62) -> 1 | F24: =SUMPRODUCT(Code_Matrix!W$2:W$62,Code_Matrix!F$2:F$62) -> 1 | G24: =SUMPRODUCT(Code_Matrix!W$2:W$62,Code_Matrix!G$2:G$62) -> 0 | H24: =SUMPRODUCT(Code_Matrix!W$2:W$62,Code_Matrix!H$2:H$62) -> 2 | I24: =SUMPRODUCT(Code_Matrix!W$2:W$62,Code_Matrix!I$2:I$62) -> 1 | J24: =SUMPRODUCT(Code_Matrix!W$2:W$62,Code_Matrix!J$2:J$62) -> 4 | K24: =SUMPRODUCT(Code_Matrix!W$2:W$62,Code_Matrix!K$2:K$62) -> 1 | L24: =SUMPRODUCT(Code_Matrix!W$2:W$62,Code_Matrix!L$2:L$62) -> 2 | M24: =SUMPRODUCT(Code_Matrix!W$2:W$62,Code_Matrix!M$2:M$62) -> 2 | N24: =SUMPRODUCT(Code_Matrix!W$2:W$62,Code_Matrix!N$2:N$62) -> 2 | O24: =SUMPRODUCT(Code_Matrix!W$2:W$62,Code_Matrix!O$2:O$62) -> 2 | P24: =SUMPRODUCT(Code_Matrix!W$2:W$62,Code_Matrix!P$2:P$62) -> 2 | Q24: =SUMPRODUCT(Code_Matrix!W$2:W$62,Code_Matrix!Q$2:Q$62) -> 0 | R24: =SUMPRODUCT(Code_Matrix!W$2:W$62,Code_Matrix!R$2:R$62) -> 3 | S24: =SUMPRODUCT(Code_Matrix!W$2:W$62,Code_Matrix!S$2:S$62) -> 1 | T24: =SUMPRODUCT(Code_Matrix!W$2:W$62,Code_Matrix!T$2:T$62) -> 0 | U24: =SUMPRODUCT(Code_Matrix!W$2:W$62,Code_Matrix!U$2:U$62) -> 3 | V24: =SUMPRODUCT(Code_Matrix!W$2:W$62,Code_Matrix!V$2:V$62) -> 3 | W24: =SUMPRODUCT(Code_Matrix!W$2:W$62,Code_Matrix!W$2:W$62) -> 17 | X24: =SUMPRODUCT(Code_Matrix!W$2:W$62,Code_Matrix!X$2:X$62) -> 3
A25: CODE_MIXING_SLANG | B25: =SUMPRODUCT(Code_Matrix!X$2:X$62,Code_Matrix!B$2:B$62) -> 2 | C25: =SUMPRODUCT(Code_Matrix!X$2:X$62,Code_Matrix!C$2:C$62) -> 0 | D25: =SUMPRODUCT(Code_Matrix!X$2:X$62,Code_Matrix!D$2:D$62) -> 0 | E25: =SUMPRODUCT(Code_Matrix!X$2:X$62,Code_Matrix!E$2:E$62) -> 0 | F25: =SUMPRODUCT(Code_Matrix!X$2:X$62,Code_Matrix!F$2:F$62) -> 0 | G25: =SUMPRODUCT(Code_Matrix!X$2:X$62,Code_Matrix!G$2:G$62) -> 0 | H25: =SUMPRODUCT(Code_Matrix!X$2:X$62,Code_Matrix!H$2:H$62) -> 0 | I25: =SUMPRODUCT(Code_Matrix!X$2:X$62,Code_Matrix!I$2:I$62) -> 0 | J25: =SUMPRODUCT(Code_Matrix!X$2:X$62,Code_Matrix!J$2:J$62) -> 0 | K25: =SUMPRODUCT(Code_Matrix!X$2:X$62,Code_Matrix!K$2:K$62) -> 0 | L25: =SUMPRODUCT(Code_Matrix!X$2:X$62,Code_Matrix!L$2:L$62) -> 1 | M25: =SUMPRODUCT(Code_Matrix!X$2:X$62,Code_Matrix!M$2:M$62) -> 0 | N25: =SUMPRODUCT(Code_Matrix!X$2:X$62,Code_Matrix!N$2:N$62) -> 1 | O25: =SUMPRODUCT(Code_Matrix!X$2:X$62,Code_Matrix!O$2:O$62) -> 1 | P25: =SUMPRODUCT(Code_Matrix!X$2:X$62,Code_Matrix!P$2:P$62) -> 0 | Q25: =SUMPRODUCT(Code_Matrix!X$2:X$62,Code_Matrix!Q$2:Q$62) -> 0 | R25: =SUMPRODUCT(Code_Matrix!X$2:X$62,Code_Matrix!R$2:R$62) -> 1 | S25: =SUMPRODUCT(Code_Matrix!X$2:X$62,Code_Matrix!S$2:S$62) -> 0 | T25: =SUMPRODUCT(Code_Matrix!X$2:X$62,Code_Matrix!T$2:T$62) -> 0 | U25: =SUMPRODUCT(Code_Matrix!X$2:X$62,Code_Matrix!U$2:U$62) -> 0 | V25: =SUMPRODUCT(Code_Matrix!X$2:X$62,Code_Matrix!V$2:V$62) -> 0 | W25: =SUMPRODUCT(Code_Matrix!X$2:X$62,Code_Matrix!W$2:W$62) -> 3 | X25: =SUMPRODUCT(Code_Matrix!X$2:X$62,Code_Matrix!X$2:X$62) -> 4

Sheet Clusters
A1: Cluster (emergent) | B1: Member IDs | C1: Description
A2: Romantic loss and longing | B2: 10,11,12,16,19,26,38,41 | C2: Heartbreak, waiting and abandonment; often tied to a wealthier rival.
A3: Love and money | B3: 3,11,12,20,23,58 | C3: Affection measured against wealth, status goods or the fare.
A4: The fare and the driver's dignity | B4: 1,17,20,21,23,36,40,49 | C4: The occupation defended against stigma; the fare as moral flashpoint.
A5: Wealth, class and fair-weather kin | B5: 3,28,30,31,42,58,61 | C5: Money organizes kinship, respect and even death.
A6: Gulf migration as default exit | B6: 10,14,24,54 | C6: Qatar/Saudi as fallback for failed study or work.
A7: Masculine burden and display | B7: 2,7,32,51,52 | C7: Provider pressure, speed, manhood norms, hidden paternal suffering.
A8: Family and parents | B8: 24,29,35,42,46,52,58 | C8: Addresses to Āmā; filial responsibility; sons and fathers.
A9: Hope, patience, endurance | B9: 9/47,20,23,26,29,45,53,59 | C9: Hardship framed as temporary passage.
A10: Distrust of the world | B10: 6,24,27,30,37,43 | C10: Selfish world, two-faced people, jealous relatives, lying courts.
A11: Self-assertion and swagger | B11: 18,22,34,42,44,48,50 | C11: Refusal to bow; boasting; place-based pride.
A12: Political satire | B12: 37,55,56,57 | C12: Courts, politicians, campaign slogans, national nostalgia.
... A15: Youth humour and code-mixing | B15: 5,13,18,20,51 | C15: English/Hindi loans and slang as comic register.

Sheet Human_Review
A1: ID | B1: Original_Nepali | C1: Priority | D1: Issue
A2: 1 | B2: भाडा लिऊँ भने इष्ट बाङ्गो; भाडा नलिऊँ भने आफू नाङ्गो। | C2: High — meaning changes | D2: Translation renders इष्ट as 'people'; it means relatives/close ones, which is the core of the dilemma.
A3: 2 | B3: तिमी स्त्री हौ, तिमीलाई हरकोहीकी प्यारी हुने हक छ। म त पुरुष हुँ, आफ्नै घरको प्यारो हुन पनि धन कमाउनुपर्छ। | C3: Medium | D3: Original theme label 'patriarchy' is an interpretation; text explicitly describes the male breadwinner burden. Check label wording.
A4: 4 | B4: एक्कासी बाढी आयो, घर-आँगन बगायो। हेर्दाहेर्दै त्यो भेलले जिन्दगीभरको धन बगायो। घर त फेरि बन्ला, धन फेरि कमाइएला; कठैबरा, छिनभरमै कैयौँको जीवन बगायो। | C4: Medium | D4: Likely refers to a specific flood; date/location of the inscription unknown.
A5: 5 | B5: नेपालीमा ‘माया’ अरे, हिन्दीमा ‘प्यार’; दुई बच्चाकी आमाले पनि ‘अङ्कल’ भन्छे यार। | C5: High — meaning changes | D5: Original translation ('calls someone uncle') misses that the speaker is the one called uncle.
A6: 6 | B6: लुटेराको बस्तीमा जिन्दगी बित्यो मस्तीमा। | C6: Medium | D6: Referent of 'looters' ambiguous.
A7: 8 | B7: प्रभु येशू, म असल गोठालो हुँ। असल गोठालोले आफ्ना भेडाहरूका निम्ति आफ्नो प्राण अर्पण गर्छ। | C7: Medium | D7: Nepali reads as the speaker addressing Jesus while saying 'I am the good shepherd' (in John 10:11 Jesus speaks). Verify the painted wording. Transliteration 'goṭhāle' ≠ गोठालोले.
A8: 9 | B8: ढिला हुन्छ, तर सबै राम्रो हुन्छ; समय खराब हो, जिन्दगी होइन, साथी। | C8: Medium | D8: Duplicate of #47 (one-character variant होइन/हैन). Keep one, record the other as variant.
A9: 10 | B9: किन पर्खी बस्थ्यौ र? खाडी जानेलाई धेरै–धेरै बधाई छ; छाडी जानेलाई तिम्रो बाँकी जिन्दगी सुखद अनि सफल बितोस्। यही शुभकामना टाढी जानेलाई माया। | C9: High — meaning changes | D9: 'छाडी जाने' = the one who left (me), not 'those leaving'. First clause appears garbled.
A10: 11 | B10: केलाउँछु धागोको माला, हार पाएपछि; के हिँड्थ्यो मसँग, कार पाएपछि? | C10: High — meaning changes | D10: Original translation ('I will string a thread garland') misreads a rhetorical question.
A11: 13 | B11: हाइ भन्दा ‘बाइ’ रे, नम्बर देऊ भन्दा ‘नाइ’ रे; रिस उठेर ‘लभ यू’ भन्देको, ‘ठट्टा नगर्नु दाइ’ रे। | C11: High — meaning changes | D11: Translation field contains an appended bold English line ('I call her I call her darling but she calls me dustbin') absent from the Nepali; likely a separate inscription. Split or remove.
A12: 14 | B12: दुवै नभए कतार छ, हामीलाई अलिक हतार छ। | C12: Medium | D12: 'दुवै' (both) has no referent; likely a fragment of a longer couplet (cf. #54).
A13: 15 | B13: गाडी हो मुगालीको, आवाज दिन्छ फाइबरको; दुनियाँका छोरी पोइल जान्छन्, दोष किन ड्राइभरको? | C13: High — meaning changes | D13: 'पोइल जानु' means a woman eloping/leaving with a man, not 'marry and leave'. 'Mugali' is a demonym, not a name. 'आवाज दिन्छ फाइबरको' unclear.
... A28: 57 | B28: देश त पुरानै ठीक थियो। | C28: Medium | D28: Do not code as royalist without evidence.

Sheet QC_Log
A1: Check | B1: Finding | C1: Rows
A2: Row count | B2: Filename says 52; the table has 61 entries plus one empty row. | C2: —
A3: Missing text | B3: Nepali cell reads 'gem'. | C3: 52
A4: Exact/near duplicates | B4: Identical except होइन/हैन. | C4: 9, 47
A5: Template variants | B5: Same fare-and-love template; record as variants. | C5: 20, 23
A6: Shared rhyme formula | B6: कतार/हतार used in both. | C6: 14, 54
A7: Contaminated field | B7: Unrelated English line appended in bold to translation. | C7: 13
A8: Transliteration error | B8: '-pardcha' for पर्छ (should be 'parcha'). | C8: 2, 17, 35, 45, 48
A9: Transliteration mismatch | B9: 'goṭhāle' vs गोठालोले; 'restoran' vs रेस्टुरेन्ट. | C9: 8, 12
A10: Probable transcription errors | B10: भोलि likely बोली; पठाएको likely पटाएको. | C10: 43, 49
A11: Mistranslations | B11: See Human_Review (High priority). | C11: 1, 5, 10, 11, 15, 55
A12: Theme column format | B12: Mix of commas and semicolons; some trailing periods. Normalize to '|' before NLP. | C12: All
... A14: Escaped characters | B14: Markdown backslashes (\-, \!) removed in this workbook. | C14: 4, 38, 42

Sheet Dashboard_Data
A1: Theme | B1: Code | C1: Inscriptions | E1: Valence | F1: Count | H1: Domain | I1: Any theme | J1: Positive | K1: Negative | L1: Mixed | M1: Neutral
A2: Education | B2: EDUCATION | C2: =INDEX(Frequencies!$C$2:$C$24,MATCH(B2,Frequencies!$A$2:$A$24,0)) -> 1 | E2: Mixed | F2: =COUNTIF(Master_Dataset!$Z$2:$Z$62,"Mixed") -> 25 | H2: Love & Relationships | I2: =SUMPRODUCT(--((Code_Matrix!B$2:B$62+Code_Matrix!C$2:C$62+Code_Matrix!D$2:D$62)>0)) -> 27 | J2: =SUMPRODUCT(--((Code_Matrix!B$2:B$62+Code_Matrix!C$2:C$62+Code_Matrix!D$2:D$62)>0),--(Master_Dataset!$Z$2:$Z$62="Positive")) -> 6 | K2: =SUMPRODUCT(--((Code_Matrix!B$2:B$62+Code_Matrix!C$2:C$62+Code_Matrix!D$2:D$62)>0),--(Master_Dataset!$Z$2:$Z$62="Negative")) -> 9 | L2: =SUMPRODUCT(--((Code_Matrix!B$2:B$62+Code_Matrix!C$2:C$62+Code_Matrix!D$2:D$62)>0),--(Master_Dataset!$Z$2:$Z$62="Mixed")) -> 10 | M2: =SUMPRODUCT(--((Code_Matrix!B$2:B$62+Code_Matrix!C$2:C$62+Code_Matrix!D$2:D$62)>0),--(Master_Dataset!$Z$2:$Z$62="Neutral")) -> 2
A3: Status Goods | B3: CONSUMER_STATUS | C3: =INDEX(Frequencies!$C$2:$C$24,MATCH(B3,Frequencies!$A$2:$A$24,0)) -> 2 | E3: Negative | F3: =COUNTIF(Master_Dataset!$Z$2:$Z$62,"Negative") -> 19 | H3: Money & Class | I3: =SUMPRODUCT(--((Code_Matrix!E$2:E$62+Code_Matrix!F$2:F$62+Code_Matrix!G$2:G$62+Code_Matrix!H$2:H$62+Code_Matrix!I$2:I$62)>0)) -> 18 | J3: =SUMPRODUCT(--((Code_Matrix!E$2:E$62+Code_Matrix!F$2:F$62+Code_Matrix!G$2:G$62+Code_Matrix!H$2:H$62+Code_Matrix!I$2:I$62)>0),--(Master_Dataset!$Z$2:$Z$62="Positive")) -> 2 | K3: =SUMPRODUCT(--((Code_Matrix!E$2:E$62+Code_Matrix!F$2:F$62+Code_Matrix!G$2:G$62+Code_Matrix!H$2:H$62+Code_Matrix!I$2:I$62)>0),--(Master_Dataset!$Z$2:$Z$62="Negative")) -> 11 | L3: =SUMPRODUCT(--((Code_Matrix!E$2:E$62+Code_Matrix!F$2:F$62+Code_Matrix!G$2:G$62+Code_Matrix!H$2:H$62+Code_Matrix!I$2:I$62)>0),--(Master_Dataset!$Z$2:$Z$62="Mixed")) -> 5 | M3: =SUMPRODUCT(--((Code_Matrix!E$2:E$62+Code_Matrix!F$2:F$62+Code_Matrix!G$2:G$62+Code_Matrix!H$2:H$62+Code_Matrix!I$2:I$62)>0),--(Master_Dataset!$Z$2:$Z$62="Neutral")) -> 0
A4: Gulf Migration | B4: MIGRATION | C4: =INDEX(Frequencies!$C$2:$C$24,MATCH(B4,Frequencies!$A$2:$A$24,0)) -> 4 | E4: Positive | F4: =COUNTIF(Master_Dataset!$Z$2:$Z$62,"Positive") -> 15 | H4: Driver & Work | I4: =SUMPRODUCT(--((Code_Matrix!J$2:J$62+Code_Matrix!K$2:K$62+Code_Matrix!L$2:L$62)>0)) -> 13 | J4: =SUMPRODUCT(--((Code_Matrix!J$2:J$62+Code_Matrix!K$2:K$62+Code_Matrix!L$2:L$62)>0),--(Master_Dataset!$Z$2:$Z$62="Positive")) -> 4 | K4: =SUMPRODUCT(--((Code_Matrix!J$2:J$62+Code_Matrix!K$2:K$62+Code_Matrix!L$2:L$62)>0),--(Master_Dataset!$Z$2:$Z$62="Negative")) -> 4 | L4: =SUMPRODUCT(--((Code_Matrix!J$2:J$62+Code_Matrix!K$2:K$62+Code_Matrix!L$2:L$62)>0),--(Master_Dataset!$Z$2:$Z$62="Mixed")) -> 5 | M4: =SUMPRODUCT(--((Code_Matrix!J$2:J$62+Code_Matrix!K$2:K$62+Code_Matrix!L$2:L$62)>0),--(Master_Dataset!$Z$2:$Z$62="Neutral")) -> 0
A5: The Fare | B5: FARE_LIVELIHOOD | C5: =INDEX(Frequencies!$C$2:$C$24,MATCH(B5,Frequencies!$A$2:$A$24,0)) -> 4 | E5: Neutral | F5: =COUNTIF(Master_Dataset!$Z$2:$Z$62,"Neutral") -> 2 | H5: Gender | I5: =SUMPRODUCT(--((Code_Matrix!M$2:M$62+Code_Matrix!N$2:N$62)>0)) -> 8 | J5: =SUMPRODUCT(--((Code_Matrix!M$2:M$62+Code_Matrix!N$2:N$62)>0),--(Master_Dataset!$Z$2:$Z$62="Positive")) -> 3 | K5: =SUMPRODUCT(--((Code_Matrix!M$2:M$62+Code_Matrix!N$2:N$62)>0),--(Master_Dataset!$Z$2:$Z$62="Negative")) -> 1 | L5: =SUMPRODUCT(--((Code_Matrix!M$2:M$62+Code_Matrix!N$2:N$62)>0),--(Master_Dataset!$Z$2:$Z$62="Mixed")) -> 4 | M5: =SUMPRODUCT(--((Code_Matrix!M$2:M$62+Code_Matrix!N$2:N$62)>0),--(Master_Dataset!$Z$2:$Z$62="Neutral")) -> 0
A6: Women Represented | B6: WOMEN_REPRESENTATION | C6: =INDEX(Frequencies!$C$2:$C$24,MATCH(B6,Frequencies!$A$2:$A$24,0)) -> 4 | H6: Self & Morality | I6: =SUMPRODUCT(--((Code_Matrix!O$2:O$62+Code_Matrix!P$2:P$62+Code_Matrix!Q$2:Q$62+Code_Matrix!R$2:R$62)>0)) -> 31 | J6: =SUMPRODUCT(--((Code_Matrix!O$2:O$62+Code_Matrix!P$2:P$62+Code_Matrix!Q$2:Q$62+Code_Matrix!R$2:R$62)>0),--(Master_Dataset!$Z$2:$Z$62="Positive")) -> 11 | K6: =SUMPRODUCT(--((Code_Matrix!O$2:O$62+Code_Matrix!P$2:P$62+Code_Matrix!Q$2:Q$62+Code_Matrix!R$2:R$62)>0),--(Master_Dataset!$Z$2:$Z$62="Negative")) -> 4 | L6: =SUMPRODUCT(--((Code_Matrix!O$2:O$62+Code_Matrix!P$2:P$62+Code_Matrix!Q$2:Q$62+Code_Matrix!R$2:R$62)>0),--(Master_Dataset!$Z$2:$Z$62="Mixed")) -> 14 | M6: =SUMPRODUCT(--((Code_Matrix!O$2:O$62+Code_Matrix!P$2:P$62+Code_Matrix!Q$2:Q$62+Code_Matrix!R$2:R$62)>0),--(Master_Dataset!$Z$2:$Z$62="Neutral")) -> 2
A7: Faith & Mythology | B7: RELIGION_FATE | C7: =INDEX(Frequencies!$C$2:$C$24,MATCH(B7,Frequencies!$A$2:$A$24,0)) -> 4 | H7: Faith & Mortality | I7: =SUMPRODUCT(--((Code_Matrix!S$2:S$62+Code_Matrix!T$2:T$62)>0)) -> 8 | J7: =SUMPRODUCT(--((Code_Matrix!S$2:S$62+Code_Matrix!T$2:T$62)>0),--(Master_Dataset!$Z$2:$Z$62="Positive")) -> 3 | K7: =SUMPRODUCT(--((Code_Matrix!S$2:S$62+Code_Matrix!T$2:T$62)>0),--(Master_Dataset!$Z$2:$Z$62="Negative")) -> 3 | L7: =SUMPRODUCT(--((Code_Matrix!S$2:S$62+Code_Matrix!T$2:T$62)>0),--(Master_Dataset!$Z$2:$Z$62="Mixed")) -> 2 | M7: =SUMPRODUCT(--((Code_Matrix!S$2:S$62+Code_Matrix!T$2:T$62)>0),--(Master_Dataset!$Z$2:$Z$62="Neutral")) -> 0
A8: Politics & Institutions | B8: INSTITUTION_CRITIQUE | C8: =INDEX(Frequencies!$C$2:$C$24,MATCH(B8,Frequencies!$A$2:$A$24,0)) -> 4 | E8: Confidence | F8: Count | H8: Politics & Place | I8: =SUMPRODUCT(--((Code_Matrix!U$2:U$62+Code_Matrix!V$2:V$62)>0)) -> 7 | J8: =SUMPRODUCT(--((Code_Matrix!U$2:U$62+Code_Matrix!V$2:V$62)>0),--(Master_Dataset!$Z$2:$Z$62="Positive")) -> 1 | K8: =SUMPRODUCT(--((Code_Matrix!U$2:U$62+Code_Matrix!V$2:V$62)>0),--(Master_Dataset!$Z$2:$Z$62="Negative")) -> 4 | L8: =SUMPRODUCT(--((Code_Matrix!U$2:U$62+Code_Matrix!V$2:V$62)>0),--(Master_Dataset!$Z$2:$Z$62="Mixed")) -> 2 | M8: =SUMPRODUCT(--((Code_Matrix!U$2:U$62+Code_Matrix!V$2:V$62)>0),--(Master_Dataset!$Z$2:$Z$62="Neutral")) -> 0
A9: Place & Region | B9: PLACE_IDENTITY | C9: =INDEX(Frequencies!$C$2:$C$24,MATCH(B9,Frequencies!$A$2:$A$24,0)) -> 4 | E9: High | F9: =COUNTIF(Master_Dataset!$AD$2:$AD$62,"High") -> 45 | H9: Style & Register | I9: =SUMPRODUCT(--((Code_Matrix!W$2:W$62+Code_Matrix!X$2:X$62)>0)) -> 18 | J9: =SUMPRODUCT(--((Code_Matrix!W$2:W$62+Code_Matrix!X$2:X$62)>0),--(Master_Dataset!$Z$2:$Z$62="Positive")) -> 5 | K9: =SUMPRODUCT(--((Code_Matrix!W$2:W$62+Code_Matrix!X$2:X$62)>0),--(Master_Dataset!$Z$2:$Z$62="Negative")) -> 3 | L9: =SUMPRODUCT(--((Code_Matrix!W$2:W$62+Code_Matrix!X$2:X$62)>0),--(Master_Dataset!$Z$2:$Z$62="Mixed")) -> 10 | M9: =SUMPRODUCT(--((Code_Matrix!W$2:W$62+Code_Matrix!X$2:X$62)>0),--(Master_Dataset!$Z$2:$Z$62="Neutral")) -> 0
A10: Slang & Code-mixing | B10: CODE_MIXING_SLANG | C10: =INDEX(Frequencies!$C$2:$C$24,MATCH(B10,Frequencies!$A$2:$A$24,0)) -> 4 | E10: Medium | F10: =COUNTIF(Master_Dataset!$AD$2:$AD$62,"Medium") -> 11
A11: Masculinity | B11: MASCULINITY | C11: =INDEX(Frequencies!$C$2:$C$24,MATCH(B11,Frequencies!$A$2:$A$24,0)) -> 5 | E11: Low | F11: =COUNTIF(Master_Dataset!$AD$2:$AD$62,"Low") -> 5
A12: Death & Risk | B12: MORTALITY_RISK | C12: =INDEX(Frequencies!$C$2:$C$24,MATCH(B12,Frequencies!$A$2:$A$24,0)) -> 5 | E12: Origin | F12: Tag assignments | H12: Cluster | I12: Members
A13: Class & Inequality | B13: CLASS_INEQUALITY_CRITIQUE | C13: =INDEX(Frequencies!$C$2:$C$24,MATCH(B13,Frequencies!$A$2:$A$24,0)) -> 7 | E13: Deductive | F13: =SUMIF(Frequencies!$B$2:$B$24,"Deductive",Frequencies!$C$2:$C$24) -> 122 | H13: Romantic loss and longing | I13: 8
A14: Distrust & Hypocrisy | B14: DISTRUST_HYPOCRISY | C14: =INDEX(Frequencies!$C$2:$C$24,MATCH(B14,Frequencies!$A$2:$A$24,0)) -> 7 | E14: Emergent | F14: =SUMIF(Frequencies!$B$2:$B$24,"Emergent",Frequencies!$C$2:$C$24) -> 43 | H14: Love and money | I14: 6
A15: Heartbreak & Separation | B15: SEPARATION_LOSS | C15: =INDEX(Frequencies!$C$2:$C$24,MATCH(B15,Frequencies!$A$2:$A$24,0)) -> 8 | H15: The fare and the driver's dignity | I15: 8
A16: Driver's Voice | B16: DRIVER_IDENTITY | C16: =INDEX(Frequencies!$C$2:$C$24,MATCH(B16,Frequencies!$A$2:$A$24,0)) -> 8 | H16: Wealth, class and fair-weather kin | I16: 7
A17: Dignity of Labour | B17: LABOR_DIGNITY | C17: =INDEX(Frequencies!$C$2:$C$24,MATCH(B17,Frequencies!$A$2:$A$24,0)) -> 8 | H17: Gulf migration as default exit | I17: 4
A18: Family & Parents | B18: FAMILY | C18: =INDEX(Frequencies!$C$2:$C$24,MATCH(B18,Frequencies!$A$2:$A$24,0)) -> 9 | H18: Masculine burden and display | I18: 5
A19: Self-Respect & Swagger | B19: SELF_RESPECT | C19: =INDEX(Frequencies!$C$2:$C$24,MATCH(B19,Frequencies!$A$2:$A$24,0)) -> 10 | H19: Family and parents | I19: 7
A20: Hope & Resilience | B20: HOPE_RESILIENCE | C20: =INDEX(Frequencies!$C$2:$C$24,MATCH(B20,Frequencies!$A$2:$A$24,0)) -> 10 | H20: Hope, patience, endurance | I20: 8
A21: Money & Wealth | B21: MONEY_MATERIALISM | C21: =INDEX(Frequencies!$C$2:$C$24,MATCH(B21,Frequencies!$A$2:$A$24,0)) -> 11 | H21: Distrust of the world | I21: 6
A22: Moral Advice | B22: MORAL_ADVICE | C22: =INDEX(Frequencies!$C$2:$C$24,MATCH(B22,Frequencies!$A$2:$A$24,0)) -> 11 | H22: Self-assertion and swagger | I22: 7
A23: Humour & Satire | B23: HUMOR | C23: =INDEX(Frequencies!$C$2:$C$24,MATCH(B23,Frequencies!$A$2:$A$24,0)) -> 17 | H23: Political satire | I23: 4
A24: Love & Romance | B24: LOVE_ROMANCE | C24: =INDEX(Frequencies!$C$2:$C$24,MATCH(B24,Frequencies!$A$2:$A$24,0)) -> 18 | H24: Mortality and the road | I24: 5
H25: Karnali place-names | I25: 3
A26: Chart source tables for the Dashboard sheet. All values are formulas; edit Master_Dataset (Codes / Valence / Confidence) and they update. | H26: Youth humour and code-mixing | I26: 5
